Workbook

Sheet 안내
A1: TRACE 사업비 원인추적기 v0.5 (프로토타입)
A2: Excel 2016 호환 · 계산은 수식, 자동화는 VBA(modTrace.bas) · 예시 데이터는 가상 수치 (원본 단위: 원, 보고 단위: 백만원)
A4: 이름의 뜻
A5: 글자 | B5: 뜻 | C5: 도구에서 하는 일 (시트)
A6: T | B6: Trend 추이 | C6: 전월·전분기·전년동월 대비 변동 (변동분석 · 월별집계 · 계정변동)
A7: R | B7: Risk 예산 위험 | C7: 부서 × 계정 × 분기 한도 점검(변동분석 AJ~AO열)과 연간 전망(P~Y열)
A8: A | B8: Anomaly 이상치 | C8: 평소 변동폭을 벗어난 항목을 점수로 골라냄 (주의대상)
A9: C | B9: Cause 원인 | C9: 증가분을 거래처·전표로 쪼개 원인 후보와 근거 전표 제시 (원인분석 · 키워드사전)
A10: E | B10: Expense 사업비 | C10: 분석 대상: 사업비 계정 (계정매핑에서 사업비 여부 Y)
A12: 흐름 단계와 시트
A13: 단계 | B13: 하는 일 | C13: 시트
A14: ① 자료 넣기 | B14: SAP 예산판·TB·전표·BS·PL을 원본 시트 A열부터 붙여넣기 | C14: 예산판_원본 · TB_원본 · 전표_원본 · BS_원본 · PL_원본
A15: ② 불러오기·대사 | B15: 매핑 적용, 전표 = TB = 예산판 실적 대사, 데이터 점검 | C15: 자가진단 · 계정변동
A16: ③ 변동 분석 | B16: 전월·전분기·전년동월 대비 증감 (부서 × 계정) | C16: 변동분석 F~O열 · 월별집계 · 계정변동
A17: ④ 예산 점검 | B17: 분기 한도(배정+조정) 대비 분기 실적·분기말 예상 → 여유/주의/초과 예상/한도 초과, 연간 전망은 참고 | C17: 변동분석 AJ~AO열 · P~Y열
A18: ⑤ 주의 대상 | B18: 증가액·증가율·이상치·예산 점수 합산 → TOP 10 | C18: 주의대상 · 변동분석 AA열 이후
A19: ⑥ 원인 추정 | B19: 선택 항목을 거래처·전표로 분해, 8가지 패턴 판정, 근거 전표 | C19: 원인분석 · 키워드사전
A20: ⑦ 보고·확인 | B20: 보고서·대시보드, 확인된 원인을 코멘트로 누적 | C20: 리포트 · 대시보드 · 차트데이터 · 코멘트 · TRACE_대시보드.html
A21: ⑧ IFRS 17 연결 | B21: 계정대체(직접대체 → 재산관리비 → 부서별 비율) → 상품·포트폴리오 → 예정 대비 경험차이 → CSM(GMM)·당기손익, 계리 변동표와 대사 | C21: IFRS17_사업비 · 계정대체기준 · 계정매핑 · 예정사업비 · 부채변동표
A23: 매월 사용 순서
A24: 1. 설정 시트에서 기준연도·기준월 변경
A25: 2. [예산판·TB·전표·BS·PL 불러오기] 버튼으로 SAP에서 내려받은 파일 선택 (매크로 없이: 원본 시트 A열부터 붙여넣고 보조수식 끌어 채우기)
A26: 3. 자가진단이 '전체 정상'인지 확인
A27: 4. 주의대상 TOP 10 확인 → 원인분석 시트 C5에 순위 입력 (비교 기준은 C6) → 원인 후보와 근거 전표 확인
A28: 5. 담당 부서 확인 결과를 코멘트 시트에 입력 → 주의대상·리포트에 표시
A29: 6. 새로 알게 된 적요 표현은 키워드사전에 추가 → 다음 달 원인 추정에 반영
A30: 7. [예정사업비·부채변동표 불러오기] (분기·월 결산 후) → IFRS17_사업비 시트에서 CSM·손익 영향과 근거 전표 확인
A31: 8. [대시보드 내보내기] 버튼 → 같은 폴더에 data.js 생성 → TRACE_대시보드.html을 열면 최신 결과 표시
A33: 매크로 설치 (1회)
A34: 1. Alt+F11 → [파일] → [파일 가져오기] → modTrace.bas
A35: 2. Alt+F8 → SetupButtons 실행 → 설정 시트 오른쪽에 버튼 10개 생성
... A66: 포트폴리오: GMM(보장성·저축성)과 VFA(변액)는 신계약비 차이가 CSM을 조정하고 유지·수금비 차이는 당기손익, PAA(단체)는 손익 영향만 봅니다. 변액은 특별계정 구분계리 대상이지만 손익에 영향을 주므로 분석에 포함합니다.

Sheet 설정
A1: TRACE · 설정
A2: 노란 칸만 바꾸세요
B4: 항목 | C4: 값 | D4: 설명 | F4: 단위 | G4: 원 환산
B5: 회사명 | C5: 예시보험㈜ | F5: 원 | G5: 1
B6: 기준연도 | C6: 2026 | F6: 천원 | G6: 1000
B7: 기준월 | C7: 9 | D7: 1~12 | F7: 백만원 | G7: 1000000
B8: 원본 금액단위 | C8: 원 | D8: 예산판·TB·전표 공통
B9: 보고 단위 | C9: 백만원 | D9: 모든 분석 표시 단위
B10: 증감 기준금액 (보고단위) | C10: 10 | D10: 이 금액 미만의 작은 증감은 주의 점수를 30%로 낮춤 · 증가액 점수 만점 = 5배
B11: 예산 '주의' 기준 (예상 소진율) | C11: 0.9 | D11: 예상 연간 실적 ÷ 가용예산이 이 값 초과면 주의
B12: 예산 '부족 예상' 기준 | C12: 1 | D12: 이 값 초과면 부족 예상
B13: 이상치 기준 (z) | C13: 2 | D13: 직전 12개월 평균 대비 표준편차 배수
B14: 원인: 단건 비중 | C14: 0.5 | D14: 전표 1건이 증가분의 이 비율 이상이고, 그 거래처 평소 월평균의 3배 이상이면 '일회성 대형' (내부 거래처 제외)
B15: 원인: 신규 거래처 비중 | C15: 0.3 | D15: 최근 12개월 거래 없던 거래처의 증가분 비중
B16: 원인: SA 대체 비중 | C16: 0.3 | D16: 수기 대체전표(SA) 순증의 증가분 비중
B17: 원인: 키워드 비중 | C17: 0.3 | D17: 키워드사전 해당 전표의 증가분 비중
B18: 원인: 단가 상승률 | C18: 0.05 | D18: 같은 건수에서 이 비율 이상, 50% 이하로 오르면 '단가 인상'
B19: 고갈 추세 기울기 | C19: 연내누적 | D19: 연내누적(연초~기준월 누계에 맞춘 직선) / 최근월(당월 사용액) / 최근분기(최근 3개월 평균) / 전년추세(작년 같은 남은 기간의 월평균)
B20: (계산) 기준 기간번호 | C20: =C6*12+C7 | D20: 연도×12+월. 기간 비교에 사용
B21: (계산) 기준 분기 | C21: =ROUNDUP(C7/3,0)
B22: (계산) 분기 시작 기간번호 | C22: =C6*12+(C21-1)*3+1
B23: (계산) 금액 환산계수 | C23: =INDEX($G$5:$G$7,MATCH(C8,$F$5:$F$7,0))/INDEX($G$5:$G$7,MATCH(C9,$F$5:$F$7,0)) | D23: 원본 금액 × 계수 = 보고단위

Sheet 헤더설정
A1: TRACE · 헤더설정 (불러오기가 찾는 열 이름)
A2: 노란 칸만 고치세요 · SAP 화면에서 내려받은 파일의 머리글과 똑같이 적으면 그 열을 찾아 표준 위치에 넣습니다
B3: 찾는 순서: ① '찾을 헤더 이름' → ② '대체 이름'(쉼표로 여러 개) 중 먼저 맞는 열. 띄어쓰기·대소문자·줄바꿈은 무시합니다.
B4: 필수 열을 찾지 못하면 불러오기를 멈추고 어떤 열이 없는지 알려줍니다. 선택 열은 없으면 빈칸으로 두고 '없을 때'에 적힌 기능만 빠집니다.
B5: 수식은 표준 열 기준이라 이 표를 고쳐도 다른 시트는 건드릴 필요가 없습니다.
B7: 예산판_원본 (빈 행 판정 열: 부서코드)
B8: 표준 열 (원본 시트) | C8: 찾을 헤더 이름 | D8: 대체 이름 (쉼표로 구분) | E8: 필수 | F8: 없을 때
B9: A열 회계연도 | C9: 회계연도 | D9: 연도,년도,GJAHR | E9: 필수
B10: B열 부서코드 | C10: 부서코드 | D10: 부서,팀코드,조직코드 | E10: 필수
B11: C열 부서명 | C11: 부서명 | D11: 팀명,조직명 | E11: 선택 | F11: 부서매핑의 부서명 사용
B12: D열 G/L계정 | C12: G/L계정 | D12: 계정,계정코드,예산계정,G/L,RACCT,HKONT | E12: 필수
B13: E열 계정명 | C13: 계정명 | D13: 계정과목명,TXT50 | E13: 선택 | F13: 계정매핑의 계정명 사용
B14: F열 분기 | C14: 분기 | D14: 분기구분,QTR | E14: 필수 | F14: 1~4, Q1, 1분기 모두 가능
B15: G열 배정 | C15: 배정 | D15: 배정액,배정예산,예산 | E15: 필수
B16: H열 조정 | C16: 조정 | D16: 조정액,전용 | E16: 선택 | F16: 0으로 처리
B17: I열 실적 | C17: 실적 | D17: 집행,집행액,실적액 | E17: 선택 | F17: 예산판↔전표 대사 불가
B18: J열 잔여 | C18: 잔여 | D18: 잔액,잔여예산 | E18: 선택 | F18: 참고용
B21: TB_원본 (빈 행 판정 열: G/L계정)
B22: 표준 열 (원본 시트) | C22: 찾을 헤더 이름 | D22: 대체 이름 (쉼표로 구분) | E22: 필수 | F22: 없을 때
B23: A열 회계연도 | C23: 회계연도 | D23: 연도,GJAHR,RYEAR | E23: 필수
B24: B열 기간 | C24: 기간 | D24: 월,회계기간,POPER | E24: 필수 | F24: 1~12 또는 001~012
B25: C열 G/L계정 | C25: G/L계정 | D25: 계정,계정코드,G/L,RACCT | E25: 필수
B26: D열 계정명 | C26: 계정명 | D26: 계정과목명,TXT50 | E26: 선택
B27: E열 당기차변 | C27: 당기차변 | D27: 차변,당월차변,차변금액 | E27: 필수
B28: F열 당기대변 | C28: 당기대변 | D28: 대변,당월대변,대변금액 | E28: 필수
B29: G열 기말잔액 | C29: 기말잔액 | D29: 잔액,기말 | E29: 선택 | F29: 참고용
B32: 전표_원본 (빈 행 판정 열: G/L계정)
B33: 표준 열 (원본 시트) | C33: 찾을 헤더 이름 | D33: 대체 이름 (쉼표로 구분) | E33: 필수 | F33: 없을 때
B34: A열 회계연도 | C34: 회계연도 | D34: 연도,GJAHR | E34: 필수
B35: B열 기간 | C35: 기간 | D35: 월,회계기간,POPER | E35: 필수
B36: C열 전표번호 | C36: 전표번호 | D36: BELNR,문서번호 | E36: 선택 | F36: 근거 전표에 번호 없이 표시
B37: D열 전기일 | C37: 전기일 | D37: 전기일자,일자,BUDAT | E37: 선택
B38: E열 전표유형 | C38: 전표유형 | D38: 문서유형,BLART | E38: 선택 | F38: '재분류' 패턴 판정 불가
B39: F열 G/L계정 | C39: G/L계정 | D39: 계정,계정코드,HKONT,RACCT | E39: 필수
B40: G열 코스트센터 | C40: 코스트센터 | D40: 비용센터,KOSTL,CC | E40: 필수
B41: H열 금액 | C41: 금액 | D41: 금액(원),현지통화금액,DMBTR,HSL | E41: 필수 | F41: 차대구분 방식이면 양수 금액
B42: I열 적요 | C42: 적요 | D42: 텍스트,내역,SGTXT | E42: 선택 | F42: '적요 키워드' 패턴 판정 불가
B43: J열 거래처코드 | C43: 거래처코드 | D43: 거래처,공급업체,LIFNR | E43: 선택
B44: K열 거래처명 | C44: 거래처명 | D44: 거래처명칭,공급업체명,NAME1 | E44: 선택 | F44: 거래처코드로 대신 표시 (둘 다 없으면 거래처 분석 불가)
B47: BS_원본 (빈 행 판정 열: 항목코드)
B48: 표준 열 (원본 시트) | C48: 찾을 헤더 이름 | D48: 대체 이름 (쉼표로 구분) | E48: 필수 | F48: 없을 때
B49: A열 회계연도 | C49: 회계연도 | D49: 연도,GJAHR | E49: 필수
B50: B열 기간 | C50: 기간 | D50: 월,회계기간 | E50: 필수
B51: C열 항목코드 | C51: 항목코드 | D51: 코드,계정코드 | E51: 필수 | F51: 없으면 항목명으로 매핑
B52: D열 항목명 | C52: 항목명 | D52: 항목,계정명,과목 | E52: 선택
B53: E열 구분 | C53: 구분 | E53: 선택
B54: F열 레벨 | C54: 레벨 | D54: 수준,LEVEL | E54: 선택
B55: G열 기말잔액 | C55: 기말잔액 | D55: 당월말,잔액,금액 | E55: 필수
B58: PL_원본 (빈 행 판정 열: 항목코드)
B59: 표준 열 (원본 시트) | C59: 찾을 헤더 이름 | D59: 대체 이름 (쉼표로 구분) | E59: 필수 | F59: 없을 때
B60: A열 회계연도 | C60: 회계연도 | D60: 연도,GJAHR | E60: 필수
B61: B열 기간 | C61: 기간 | D61: 월,회계기간 | E61: 필수
B62: C열 항목코드 | C62: 항목코드 | D62: 코드,계정코드 | E62: 필수 | F62: 없으면 항목명으로 매핑
B63: D열 항목명 | C63: 항목명 | D63: 항목,계정명,과목 | E63: 선택
B64: E열 구분 | C64: 구분 | E64: 선택
B65: F열 레벨 | C65: 레벨 | D65: 수준,LEVEL | E65: 선택
B66: G열 당월금액 | C66: 당월금액 | D66: 당월,금액 | E66: 필수
B67: H열 누계금액 | C67: 누계금액 | D67: 누계,누적 | E67: 권장 | F67: 당기순이익 누계 KPI가 0으로 표시
B70: 예정사업비 (빈 행 판정 열: 포트폴리오)
B71: 표준 열 (원본 시트) | C71: 찾을 헤더 이름 | D71: 대체 이름 (쉼표로 구분) | E71: 필수 | F71: 없을 때
B72: A열 회계연도 | C72: 회계연도 | D72: 연도 | E72: 필수
B73: B열 기간 | C73: 기간 | D73: 월,회계기간 | E73: 필수
B74: C열 포트폴리오 | C74: 포트폴리오 | D74: 포트폴리오코드,PF | E74: 필수
B75: D열 포트폴리오명 | C75: 포트폴리오명 | E75: 선택
B76: E열 신계약비 | C76: 신계약비 | D76: 예정신계약비 | E76: 필수
B77: F열 유지비 | C77: 유지비 | D77: 예정유지비 | E77: 필수
B78: G열 수금비 | C78: 수금비 | D78: 예정수금비 | E78: 필수
B81: 부채변동표 (빈 행 판정 열: 포트폴리오)
B82: 표준 열 (원본 시트) | C82: 찾을 헤더 이름 | D82: 대체 이름 (쉼표로 구분) | E82: 필수 | F82: 없을 때
B83: A열 회계연도 | C83: 회계연도 | D83: 연도 | E83: 선택 | F83: 설정의 기준연도로 채우고 그 달 자료만 교체
B84: B열 기간 | C84: 기간 | D84: 월,회계기간 | E84: 선택 | F84: 설정의 기준월로 채움
B85: C열 포트폴리오 | C85: 포트폴리오 | D85: 포트폴리오코드,PF | E85: 필수
B86: D열 포트폴리오명 | C86: 포트폴리오명 | E86: 선택
B87: E열 측정모형 | C87: 측정모형 | D87: 모형,측정방법 | E87: 필수 | F87: GMM·PAA·VFA
B88: F열 변동요인코드 | C88: 변동요인코드 | D88: 요인코드,코드 | E88: 필수 | F88: 없으면 변동요인명으로 매핑
B89: G열 변동요인 | C89: 변동요인 | D89: 요인,항목,변동내역 | E89: 선택
B90: H열 BEL | C90: BEL | D90: 최선추정부채,최선추정 | E90: 필수
B91: I열 RA | C91: RA | D91: 위험조정 | E91: 필수
B92: J열 CSM | C92: CSM | D92: 보험계약마진,계약서비스마진 | E92: 필수

Sheet 입력옵션
A1: TRACE · 입력옵션
A2: 노란 칸만 고치세요 · 불러오기 규칙과 BS·PL 항목 매핑
A4: 불러오기 규칙
B5: 제외할 행 키워드 | C5: 합계,소계,총계,Total | D5: 빈 행 판정 열에 이 단어가 있으면 불러오지 않음 (쉼표로 구분)
B6: 머리글 찾는 범위 (행) | C6: 20 | D6: 파일 위쪽 이 행 수 안에서 헤더 이름이 가장 많이 맞는 행을 머리글로 사용
B8: 전표 금액 방식 | C8: 부호 있는 금액 | D8: '부호 있는 금액' 또는 '차대구분+양수금액' (SAP 차대구분 S/H)
B9: 차대구분 헤더 이름 | C9: 차대구분 | D9: 차대구분+양수금액 방식일 때 찾을 열 이름 (예: SHKZG)
B10: 차변 표시 값 | C10: S
B11: 대변 표시 값 | C11: H | D11: 이 값인 행은 금액에 −를 붙여 불러옴
B13: BS·PL 양식 형태 | C13: 세로 (기간×항목) | D13: '감독원 (가로)'이면 항목이 행, 금액이 열인 양식을 기준월 한 달씩 불러와 기존 자료에 합침
B14: 가로: 당기 금액 헤더 | C14: 당기 | D14: BS 기말잔액 · PL 당월 금액 열 이름 (쉼표로 대체 이름)
B15: 가로: 전기 금액 헤더 | C15: 전기 | D15: BS 비교 열 (없으면 비워둠)
B16: 가로: PL 누계 헤더 | C16: 당기누계 | D16: PL 누계 금액 열
B17: 가로: 전기 열의 기간 | C17: 전년말 | D17: '전년말'(전년 12월) 또는 '전년동월'
A20: BS·PL 항목 매핑 — 회사 재무제표의 항목코드(없으면 항목명)를 표준 코드에 연결. 차트·KPI·검산은 표준 코드만 사용
B21: 구분 | C21: 표준 코드 | D21: 표준 항목명 | E21: 실제 항목코드 | F21: 실제 항목명
B22: BS | C22: A000 | D22: 자산총계 | E22: 10000 | F22: 자산총계
B23: BS | C23: A100 | D23: 운용자산 | E23: 11000 | F23: 운용자산
B24: BS | C24: A110 | D24: 현금및예치금 | E24: 11100 | F24: 현금및예치금
B25: BS | C25: A120 | D25: 유가증권 | E25: 11200 | F25: 유가증권
B26: BS | C26: A130 | D26: 대출채권 | E26: 11300 | F26: 대출채권
B27: BS | C27: A140 | D27: 투자부동산 | E27: 11400 | F27: 투자부동산
B28: BS | C28: A200 | D28: 보험계약자산 | E28: 12000 | F28: 보험계약자산
B29: BS | C29: A300 | D29: 재보험계약자산 | E29: 13000 | F29: 재보험계약자산
B30: BS | C30: A900 | D30: 기타자산 | E30: 19000 | F30: 기타자산
B31: BS | C31: L000 | D31: 부채총계 | E31: 20000 | F31: 부채총계
B32: BS | C32: L100 | D32: 보험계약부채 | E32: 21000 | F32: 보험계약부채
... B53: PL | C53: P600 | D53: 당기순이익 | E53: 90000 | F53: 당기순이익
A56: 부채변동표 변동요인 매핑 — 감독원 양식의 요인코드(없으면 요인명)를 TRACE 요인코드에 연결
B57: 구분 | C57: TRACE 요인코드 | D57: TRACE 요인명 | E57: 실제 요인코드 | F57: 실제 요인명
B58: 변동표 | C58: F00 | D58: 기초잔액 | E58: B00 | F58: 기초
B59: 변동표 | C59: F10 | D59: 신계약 효과 | E59: B10 | F59: 신계약
B60: 변동표 | C60: F21 | D60: 가정변경-사업비 | E60: B21 | F60: 추정변경(사업비)
B61: 변동표 | C61: F22 | D61: 가정변경-기타 | E61: B22 | F61: 추정변경(기타)
B62: 변동표 | C62: F31 | D62: 경험조정-취득현금흐름 | E62: B31 | F62: 경험조정(보험취득현금흐름)
B63: 변동표 | C63: F32 | D63: 경험조정-보험료 등 | E63: B32 | F63: 경험조정(기타)
B64: 변동표 | C64: F40 | D64: 보험금융비용(이자부리) | E64: B40 | F64: 보험금융비용
B65: 변동표 | C65: F51 | D65: CSM 상각 | E65: B51 | F65: 보험계약마진 상각
B66: 변동표 | C66: F52 | D66: RA 해제 | E66: B52 | F66: 위험조정 변동(당기)
B67: 변동표 | C67: F60 | D67: 현금흐름 및 기타 | E67: B60 | F67: 현금흐름 및 기타
B68: 변동표 | C68: F99 | D68: 기말잔액 | E68: B99 | F68: 기말

Sheet 자가진단
A1: TRACE · 자가진단
A2: 외부망으로 오류를 알릴 때는 [점검 항목]과 [상태]만 전달하세요
A4: 종합 | B4: =IF(COUNTIF(D7:D39,"확인필요")=0,"전체 정상"&IF(COUNTIF(D7:D39,"참고")>0," (참고 "&COUNTIF(D7:D39,"참고")&"건)",""),"확인필요 "&COUNTIF(D7:D39,"확인필요")&"건")
A6: No | B6: 점검 항목 | C6: 결과 | D6: 상태 | E6: 조치 방법
A7: 1 | B7: 설정값 | C7: =IF(AND(ISNUMBER(설정!$C$7),설정!$C$7>=1,설정!$C$7<=12,ISNUMBER(설정!$C$23)),"정상","기준월 또는 단위 오류") | D7: =IF(C7="정상","OK","확인필요") | E7: 설정 시트 기준월(1~12)·단위 확인
A8: 2 | B8: 전표_원본 머리글 | C8: =IF(IF(전표_원본!A4<>"회계연도","A ","")&IF(전표_원본!B4<>"기간","B ","")&IF(전표_원본!C4<>"전표번호","C ","")&IF(전표_원본!D4<>"전기일","D ","")&IF(전표_원본!E4<>"전표유형","E ","")&IF(전표_원본!F4<>"G/L계정","F ","")&IF(전표_원본!G4<>"코스트센터","G ","")&IF(전표_원본!H4<>"금액","H ","")&IF(전표_원본!I4<>"적요","I ","")&IF(전표_원본!J4<>"거래처코드","J ","")&IF(전표_원본!K4<>"거래처명","K ","")="","일치","불일치 열: "&IF(전표_원본!A4<>"회계연도","A ","")&IF(전표_원본!B4<>"기간","B ","")&IF(전표_원본!C4<>"전표번호","C ","")&IF(전표_원본!D4<>"전기일","D ","")&IF(전표_원본!E4<>"전표유형","E ","")&IF(전표_원본!F4<>"G/L계정","F ","")&IF(전표_원본!G4<>"코스트센터","G ","")&IF(전표_원본!H4<>"금액","H ","")&IF(전표_원본!I4<>"적요","I ","")&IF(전표_원본!J4<>"거래처코드","J ","")&IF(전표_원본!K4<>"거래처명","K ","")) | D8: =IF(C8="일치","OK","확인필요") | E8: 4행 머리글을 표준 이름으로
A9: 3 | B9: TB_원본 머리글 | C9: =IF(IF(TB_원본!A4<>"회계연도","A ","")&IF(TB_원본!B4<>"기간","B ","")&IF(TB_원본!C4<>"G/L계정","C ","")&IF(TB_원본!D4<>"계정명","D ","")&IF(TB_원본!E4<>"당기차변","E ","")&IF(TB_원본!F4<>"당기대변","F ","")&IF(TB_원본!G4<>"기말잔액","G ","")="","일치","불일치 열: "&IF(TB_원본!A4<>"회계연도","A ","")&IF(TB_원본!B4<>"기간","B ","")&IF(TB_원본!C4<>"G/L계정","C ","")&IF(TB_원본!D4<>"계정명","D ","")&IF(TB_원본!E4<>"당기차변","E ","")&IF(TB_원본!F4<>"당기대변","F ","")&IF(TB_원본!G4<>"기말잔액","G ","")) | D9: =IF(C9="일치","OK","확인필요") | E9: 4행 머리글을 표준 이름으로
A10: 4 | B10: 예산판_원본 머리글 | C10: =IF(IF(예산판_원본!A4<>"회계연도","A ","")&IF(예산판_원본!B4<>"부서코드","B ","")&IF(예산판_원본!C4<>"부서명","C ","")&IF(예산판_원본!D4<>"G/L계정","D ","")&IF(예산판_원본!E4<>"계정명","E ","")&IF(예산판_원본!F4<>"분기","F ","")&IF(예산판_원본!G4<>"배정","G ","")&IF(예산판_원본!H4<>"조정","H ","")&IF(예산판_원본!I4<>"실적","I ","")&IF(예산판_원본!J4<>"잔여","J ","")="","일치","불일치 열: "&IF(예산판_원본!A4<>"회계연도","A ","")&IF(예산판_원본!B4<>"부서코드","B ","")&IF(예산판_원본!C4<>"부서명","C ","")&IF(예산판_원본!D4<>"G/L계정","D ","")&IF(예산판_원본!E4<>"계정명","E ","")&IF(예산판_원본!F4<>"분기","F ","")&IF(예산판_원본!G4<>"배정","G ","")&IF(예산판_원본!H4<>"조정","H ","")&IF(예산판_원본!I4<>"실적","I ","")&IF(예산판_원본!J4<>"잔여","J ","")) | D10: =IF(C10="일치","OK","확인필요") | E10: 4행 머리글을 표준 이름으로
A11: 5 | B11: 전표 보조수식 범위 | C11: =COUNTA(전표_원본!A5:A100000)&"행 / 보조 "&COUNTA(전표_원본!O5:O100000)&"행" | D11: =IF(COUNTA(전표_원본!O5:O100000)>=COUNTA(전표_원본!A5:A100000),"OK","확인필요") | E11: M~X열을 데이터 마지막 행까지 채우기
A12: 6 | B12: TB 보조수식 범위 | C12: =COUNTA(TB_원본!A5:A20000)&"행 / 보조 "&COUNTA(TB_원본!I5:I20000)&"행" | D12: =IF(COUNTA(TB_원본!I5:I20000)>=COUNTA(TB_원본!A5:A20000),"OK","확인필요") | E12: I~K열을 데이터 마지막 행까지 채우기
A13: 7 | B13: 예산판 보조수식 범위 | C13: =COUNTA(예산판_원본!A5:A5000)&"행 / 보조 "&COUNTA(예산판_원본!L5:L5000)&"행" | D13: =IF(COUNTA(예산판_원본!L5:L5000)>=COUNTA(예산판_원본!A5:A5000),"OK","확인필요") | E13: L~R열을 데이터 마지막 행까지 채우기
A14: 8 | B14: 기준월 전표 존재 | C14: =COUNTIF(전표_원본!$M$5:$M$100000,설정!$C$20)&"건" | D14: =IF(COUNTIF(전표_원본!$M$5:$M$100000,설정!$C$20)>0,"OK","확인필요") | E14: 기준월 전표가 들어 있는지 확인
A15: 9 | B15: 기준월 TB 존재 | C15: =COUNTIF(TB_원본!$I$5:$I$20000,설정!$C$20)&"행" | D15: =IF(COUNTIF(TB_원본!$I$5:$I$20000,설정!$C$20)>0,"OK","확인필요") | E15: 기준월 TB가 들어 있는지 확인
A16: 10 | B16: 전년 동월 전표 존재 | C16: =COUNTIF(전표_원본!$M$5:$M$100000,설정!$C$20-12)&"건" | D16: =IF(COUNTIF(전표_원본!$M$5:$M$100000,설정!$C$20-12)>0,"OK","참고") | E16: 전년동월 비교·이상치 판정에 필요 (최근 24개월 권장)
A17: 11 | B17: 미매핑 코스트센터 | C17: =COUNTIF(전표_원본!$N$5:$N$100000,"미매핑")&"건"&IF(COUNTIF(전표_원본!$N$5:$N$100000,"미매핑")>0," (예: "&INDEX(전표_원본!$G$5:$G$100000,MATCH("미매핑",전표_원본!$N$5:$N$100000,0))&")","") | D17: =IF(COUNTIF(전표_원본!$N$5:$N$100000,"미매핑")=0,"OK","확인필요") | E17: 부서매핑에 코스트센터 추가
A18: 12 | B18: 미매핑 G/L 계정 | C18: =COUNTIF(전표_원본!$W$5:$W$100000,"미매핑")&"건"&IF(COUNTIF(전표_원본!$W$5:$W$100000,"미매핑")>0," (예: "&INDEX(전표_원본!$F$5:$F$100000,MATCH("미매핑",전표_원본!$W$5:$W$100000,0))&")","") | D18: =IF(COUNTIF(전표_원본!$W$5:$W$100000,"미매핑")=0,"OK","확인필요") | E18: 계정매핑에 계정 추가
A19: 13 | B19: TB ↔ 전표 당월 대사 | C19: ="차이 "&TEXT(계정변동!L25,"#,##0.0") | D19: =IF(ABS(계정변동!L25)<0.05,"OK","확인필요") | E19: 계정변동 시트에서 차이 나는 계정 확인 (전표 추출 범위 누락 등)
A20: 14 | B20: 예산판 ↔ 전표 당분기 대사 | C20: ="차이 "&TEXT(계정변동!O25,"#,##0.0") | D20: =IF(ABS(계정변동!O25)<0.05,"OK","확인필요") | E20: 예산판 추출 시점과 전표 기간 일치 여부 확인
A21: 15 | B21: 변동분석에 없는 조합 (전표) | C21: =COUNTIFS(전표_원본!$V$5:$V$100000,"N",전표_원본!$A$5:$A$100000,설정!$C$6)&"건" | D21: =IF(COUNTIFS(전표_원본!$V$5:$V$100000,"N",전표_원본!$A$5:$A$100000,설정!$C$6)=0,"OK","확인필요") | E21: 변동분석에 부서코드·G/L 행 추가
A22: 16 | B22: 변동분석에 없는 조합 (예산판) | C22: =COUNTIFS(예산판_원본!$Q$5:$Q$5000,"N",예산판_원본!$M$5:$M$5000,설정!$C$6)&"행" | D22: =IF(COUNTIFS(예산판_원본!$Q$5:$Q$5000,"N",예산판_원본!$M$5:$M$5000,설정!$C$6)=0,"OK","확인필요") | E22: 변동분석에 부서코드·G/L 행 추가
A23: 17 | B23: 무예산 집행 | C23: =COUNTIF(변동분석!$AO$7:$AO$506,"무예산")&"건" | D23: =IF(COUNTIF(변동분석!$AO$7:$AO$506,"무예산")=0,"OK","참고") | E23: 업무상 예외 - 전용·추가 배정 여부 확인
A24: 18 | B24: 원인분석 선택 항목 | C24: =원인분석!$E$9&" · 당기 전표 "&COUNTIF(전표_원본!$Q$5:$Q$100000,"당기")&"건" | D24: =IF(COUNTIF(전표_원본!$Q$5:$Q$100000,"당기")>0,"OK","참고") | E24: 원인분석 C5~C8 선택값 확인
A25: 19 | B25: BS_원본 머리글 | C25: =IF(IF(BS_원본!A4<>"회계연도","A ","")&IF(BS_원본!B4<>"기간","B ","")&IF(BS_원본!C4<>"항목코드","C ","")&IF(BS_원본!D4<>"항목명","D ","")&IF(BS_원본!E4<>"구분","E ","")&IF(BS_원본!F4<>"레벨","F ","")&IF(BS_원본!G4<>"기말잔액","G ","")="","일치","불일치 열: "&IF(BS_원본!A4<>"회계연도","A ","")&IF(BS_원본!B4<>"기간","B ","")&IF(BS_원본!C4<>"항목코드","C ","")&IF(BS_원본!D4<>"항목명","D ","")&IF(BS_원본!E4<>"구분","E ","")&IF(BS_원본!F4<>"레벨","F ","")&IF(BS_원본!G4<>"기말잔액","G ","")) | D25: =IF(C25="일치","OK","확인필요") | E25: 4행 머리글을 표준 이름으로
A26: 20 | B26: PL_원본 머리글 | C26: =IF(IF(PL_원본!A4<>"회계연도","A ","")&IF(PL_원본!B4<>"기간","B ","")&IF(PL_원본!C4<>"항목코드","C ","")&IF(PL_원본!D4<>"항목명","D ","")&IF(PL_원본!E4<>"구분","E ","")&IF(PL_원본!F4<>"레벨","F ","")&IF(PL_원본!G4<>"당월금액","G ","")&IF(PL_원본!H4<>"누계금액","H ","")="","일치","불일치 열: "&IF(PL_원본!A4<>"회계연도","A ","")&IF(PL_원본!B4<>"기간","B ","")&IF(PL_원본!C4<>"항목코드","C ","")&IF(PL_원본!D4<>"항목명","D ","")&IF(PL_원본!E4<>"구분","E ","")&IF(PL_원본!F4<>"레벨","F ","")&IF(PL_원본!G4<>"당월금액","G ","")&IF(PL_원본!H4<>"누계금액","H ","")) | D26: =IF(C26="일치","OK","확인필요") | E26: 4행 머리글을 표준 이름으로
A27: 21 | B27: BS·PL 보조수식 범위 | C27: ="BS "&COUNTA(BS_원본!A5:A20000)&"/"&COUNTA(BS_원본!I5:I20000)&" · PL "&COUNTA(PL_원본!A5:A20000)&"/"&COUNTA(PL_원본!J5:J20000) | D27: =IF(AND(COUNTA(BS_원본!I5:I20000)>=COUNTA(BS_원본!A5:A20000),COUNTA(PL_원본!J5:J20000)>=COUNTA(PL_원본!A5:A20000)),"OK","확인필요") | E27: 보조수식을 데이터 마지막 행까지 채우기
A28: 22 | B28: 기준월 BS·PL 존재 | C28: ="BS "&COUNTIF(BS_원본!$I$5:$I$20000,설정!$C$20)&"행 · PL "&COUNTIF(PL_원본!$J$5:$J$20000,설정!$C$20)&"행" | D28: =IF(AND(COUNTIF(BS_원본!$I$5:$I$20000,설정!$C$20)>0,COUNTIF(PL_원본!$J$5:$J$20000,설정!$C$20)>0),"OK","확인필요") | E28: 기준월 BS·PL이 들어 있는지 확인
A29: 23 | B29: BS 대차 (자산 = 부채 + 자본) | C29: ="차이 "&TEXT(SUMIFS(BS_원본!$K$5:$K$20000,BS_원본!$J$5:$J$20000,"A000",BS_원본!$I$5:$I$20000,설정!$C$20)-SUMIFS(BS_원본!$K$5:$K$20000,BS_원본!$J$5:$J$20000,"L000",BS_원본!$I$5:$I$20000,설정!$C$20)-SUMIFS(BS_원본!$K$5:$K$20000,BS_원본!$J$5:$J$20000,"E000",BS_원본!$I$5:$I$20000,설정!$C$20),"#,##0") | D29: =IF(ABS(SUMIFS(BS_원본!$K$5:$K$20000,BS_원본!$J$5:$J$20000,"A000",BS_원본!$I$5:$I$20000,설정!$C$20)-SUMIFS(BS_원본!$K$5:$K$20000,BS_원본!$J$5:$J$20000,"L000",BS_원본!$I$5:$I$20000,설정!$C$20)-SUMIFS(BS_원본!$K$5:$K$20000,BS_원본!$J$5:$J$20000,"E000",BS_원본!$I$5:$I$20000,설정!$C$20))<1,"OK","확인필요") | E29: BS 합계 행(A000·L000·E000) 확인
A30: 24 | B30: PL 당기순이익 검산 | C30: ="차이 "&TEXT(SUMIFS(PL_원본!$L$5:$L$20000,PL_원본!$K$5:$K$20000,"P100",PL_원본!$J$5:$J$20000,설정!$C$20)+SUMIFS(PL_원본!$L$5:$L$20000,PL_원본!$K$5:$K$20000,"P200",PL_원본!$J$5:$J$20000,설정!$C$20)-SUMIFS(PL_원본!$L$5:$L$20000,PL_원본!$K$5:$K$20000,"P300",PL_원본!$J$5:$J$20000,설정!$C$20)-SUMIFS(PL_원본!$L$5:$L$20000,PL_원본!$K$5:$K$20000,"P500",PL_원본!$J$5:$J$20000,설정!$C$20)-SUMIFS(PL_원본!$L$5:$L$20000,PL_원본!$K$5:$K$20000,"P600",PL_원본!$J$5:$J$20000,설정!$C$20),"#,##0.0") | D30: =IF(ABS(SUMIFS(PL_원본!$L$5:$L$20000,PL_원본!$K$5:$K$20000,"P100",PL_원본!$J$5:$J$20000,설정!$C$20)+SUMIFS(PL_원본!$L$5:$L$20000,PL_원본!$K$5:$K$20000,"P200",PL_원본!$J$5:$J$20000,설정!$C$20)-SUMIFS(PL_원본!$L$5:$L$20000,PL_원본!$K$5:$K$20000,"P300",PL_원본!$J$5:$J$20000,설정!$C$20)-SUMIFS(PL_원본!$L$5:$L$20000,PL_원본!$K$5:$K$20000,"P500",PL_원본!$J$5:$J$20000,설정!$C$20)-SUMIFS(PL_원본!$L$5:$L$20000,PL_원본!$K$5:$K$20000,"P600",PL_원본!$J$5:$J$20000,설정!$C$20))<0.05,"OK","확인필요") | E30: 보험손익+투자손익−사업비−법인세 = 당기순이익
A31: 25 | B31: PL 기타사업비용 ↔ 비귀속 사업비 | C31: ="차이 "&TEXT(SUMIFS(PL_원본!$L$5:$L$20000,PL_원본!$K$5:$K$20000,"P300",PL_원본!$J$5:$J$20000,설정!$C$20)-SUMIFS(전표_원본!$Y$5:$Y$100000,전표_원본!$M$5:$M$100000,설정!$C$20),"#,##0.0") | D31: =IF(ABS(SUMIFS(PL_원본!$L$5:$L$20000,PL_원본!$K$5:$K$20000,"P300",PL_원본!$J$5:$J$20000,설정!$C$20)-SUMIFS(전표_원본!$Y$5:$Y$100000,전표_원본!$M$5:$M$100000,설정!$C$20))<0.5,"OK","확인필요") | E31: 직접대체·부서별 비율의 비귀속과 PL 기타사업비용 범위 확인
A32: 26 | B32: 대체비율 합계 100% | C32: ="부서 "&SUMPRODUCT((계정대체기준!$A$20:$A$49<>"")*(ABS(계정대체기준!$G$20:$G$49-1)>0.0001))&"행 · 포트폴리오 "&(ABS(계정대체기준!$D$64-1)+ABS(계정대체기준!$E$64-1)+ABS(계정대체기준!$F$64-1)>0.0001)*1 | D32: =IF(SUMPRODUCT((계정대체기준!$A$20:$A$49<>"")*(ABS(계정대체기준!$G$20:$G$49-1)>0.0001))+(ABS(계정대체기준!$D$64-1)+ABS(계정대체기준!$E$64-1)+ABS(계정대체기준!$F$64-1)>0.0001)=0,"OK","확인필요") | E32: 계정대체기준 시트에서 합계가 100%가 아닌 행 수정
A33: 27 | B33: 대체비율표에 없는 부서 (공통비) | C33: =SUMPRODUCT((전표_원본!$AE$5:$AE$100000="공통비")*(COUNTIF(계정대체기준!$A$20:$A$49,전표_원본!$N$5:$N$100000)=0))&"건 (전액 비귀속 처리)" | D33: =IF(SUMPRODUCT((전표_원본!$AE$5:$AE$100000="공통비")*(COUNTIF(계정대체기준!$A$20:$A$49,전표_원본!$N$5:$N$100000)=0))=0,"OK","확인필요") | E33: 계정대체기준 부서별 비율표에 부서 추가
A34: 28 | B34: 계정대체 전후 합계 | C34: ="차이 "&TEXT(SUMIFS(전표_원본!$P$5:$P$100000,전표_원본!$M$5:$M$100000,설정!$C$20)-SUMIFS(전표_원본!$Y$5:$Y$100000,전표_원본!$M$5:$M$100000,설정!$C$20)-SUMIFS(전표_원본!$Z$5:$Z$100000,전표_원본!$M$5:$M$100000,설정!$C$20)-SUMIFS(전표_원본!$AA$5:$AA$100000,전표_원본!$M$5:$M$100000,설정!$C$20)-SUMIFS(전표_원본!$AB$5:$AB$100000,전표_원본!$M$5:$M$100000,설정!$C$20)-SUMIFS(전표_원본!$AD$5:$AD$100000,전표_원본!$M$5:$M$100000,설정!$C$20),"#,##0.0") | D34: =IF(ABS(SUMIFS(전표_원본!$P$5:$P$100000,전표_원본!$M$5:$M$100000,설정!$C$20)-SUMIFS(전표_원본!$Y$5:$Y$100000,전표_원본!$M$5:$M$100000,설정!$C$20)-SUMIFS(전표_원본!$Z$5:$Z$100000,전표_원본!$M$5:$M$100000,설정!$C$20)-SUMIFS(전표_원본!$AA$5:$AA$100000,전표_원본!$M$5:$M$100000,설정!$C$20)-SUMIFS(전표_원본!$AB$5:$AB$100000,전표_원본!$M$5:$M$100000,설정!$C$20)-SUMIFS(전표_원본!$AD$5:$AD$100000,전표_원본!$M$5:$M$100000,설정!$C$20))<0.05,"OK","확인필요") | E34: 직접대체 계정 지정, 부서별 비율 합계 확인
A35: 29 | B35: PL 재산관리비 ↔ 재산관리비 대체액 | C35: ="차이 "&TEXT(SUMIFS(PL_원본!$L$5:$L$20000,PL_원본!$K$5:$K$20000,"P230",PL_원본!$J$5:$J$20000,설정!$C$20)-SUMIFS(전표_원본!$AD$5:$AD$100000,전표_원본!$M$5:$M$100000,설정!$C$20),"#,##0.0") | D35: =IF(ABS(SUMIFS(PL_원본!$L$5:$L$20000,PL_원본!$K$5:$K$20000,"P230",PL_원본!$J$5:$J$20000,설정!$C$20)-SUMIFS(전표_원본!$AD$5:$AD$100000,전표_원본!$M$5:$M$100000,설정!$C$20))<0.5,"OK","확인필요") | E35: 투자관련부서 목록·재산관리비 비율, PL 재산관리비 범위 확인
A36: 30 | B36: 기준월 예정사업비 존재 | C36: =COUNTIF(예정사업비!$I$5:$I$20000,설정!$C$20)&"행" | D36: =IF(COUNTIF(예정사업비!$I$5:$I$20000,설정!$C$20)>0,"OK","확인필요") | E36: 계리 예정사업비 기준월 자료 확인
A37: 31 | B37: 부채변동표 롤포워드 | C37: ="차이 "&TEXT(SUMIFS(부채변동표!$M$5:$M$20000,부채변동표!$L$5:$L$20000,설정!$C$20,부채변동표!$P$5:$P$20000,"<>F99")-SUMIFS(부채변동표!$M$5:$M$20000,부채변동표!$L$5:$L$20000,설정!$C$20,부채변동표!$P$5:$P$20000,"F99"),"#,##0.0")&" / "&TEXT(SUMIFS(부채변동표!$O$5:$O$20000,부채변동표!$L$5:$L$20000,설정!$C$20,부채변동표!$P$5:$P$20000,"<>F99")-SUMIFS(부채변동표!$O$5:$O$20000,부채변동표!$L$5:$L$20000,설정!$C$20,부채변동표!$P$5:$P$20000,"F99"),"#,##0.0") | D37: =IF(ABS(SUMIFS(부채변동표!$M$5:$M$20000,부채변동표!$L$5:$L$20000,설정!$C$20,부채변동표!$P$5:$P$20000,"<>F99")-SUMIFS(부채변동표!$M$5:$M$20000,부채변동표!$L$5:$L$20000,설정!$C$20,부채변동표!$P$5:$P$20000,"F99"))+ABS(SUMIFS(부채변동표!$N$5:$N$20000,부채변동표!$L$5:$L$20000,설정!$C$20,부채변동표!$P$5:$P$20000,"<>F99")-SUMIFS(부채변동표!$N$5:$N$20000,부채변동표!$L$5:$L$20000,설정!$C$20,부채변동표!$P$5:$P$20000,"F99"))+ABS(SUMIFS(부채변동표!$O$5:$O$20000,부채변동표!$L$5:$L$20000,설정!$C$20,부채변동표!$P$5:$P$20000,"<>F99")-SUMIFS(부채변동표!$O$5:$O$20000,부채변동표!$L$5:$L$20000,설정!$C$20,부채변동표!$P$5:$P$20000,"F99"))<1,"OK","확인필요") | E37: 기초 + 요인 합계 = 기말인지, 변동요인 매핑(입력옵션) 누락 확인
A38: 32 | B38: 변동표 기말 ↔ BS (BEL·RA·CSM) | C38: ="차이 "&TEXT(SUMIFS(부채변동표!$M$5:$M$20000,부채변동표!$L$5:$L$20000,설정!$C$20,부채변동표!$P$5:$P$20000,"F99")-SUMIFS(BS_원본!$K$5:$K$20000,BS_원본!$J$5:$J$20000,"L110",BS_원본!$I$5:$I$20000,설정!$C$20),"#,##0")&" / "&TEXT(SUMIFS(부채변동표!$N$5:$N$20000,부채변동표!$L$5:$L$20000,설정!$C$20,부채변동표!$P$5:$P$20000,"F99")-SUMIFS(BS_원본!$K$5:$K$20000,BS_원본!$J$5:$J$20000,"L120",BS_원본!$I$5:$I$20000,설정!$C$20),"#,##0")&" / "&TEXT(SUMIFS(부채변동표!$O$5:$O$20000,부채변동표!$L$5:$L$20000,설정!$C$20,부채변동표!$P$5:$P$20000,"F99")-SUMIFS(BS_원본!$K$5:$K$20000,BS_원본!$J$5:$J$20000,"L130",BS_원본!$I$5:$I$20000,설정!$C$20),"#,##0") | D38: =IF(ABS(SUMIFS(부채변동표!$M$5:$M$20000,부채변동표!$L$5:$L$20000,설정!$C$20,부채변동표!$P$5:$P$20000,"F99")-SUMIFS(BS_원본!$K$5:$K$20000,BS_원본!$J$5:$J$20000,"L110",BS_원본!$I$5:$I$20000,설정!$C$20))+ABS(SUMIFS(부채변동표!$N$5:$N$20000,부채변동표!$L$5:$L$20000,설정!$C$20,부채변동표!$P$5:$P$20000,"F99")-SUMIFS(BS_원본!$K$5:$K$20000,BS_원본!$J$5:$J$20000,"L120",BS_원본!$I$5:$I$20000,설정!$C$20))+ABS(SUMIFS(부채변동표!$O$5:$O$20000,부채변동표!$L$5:$L$20000,설정!$C$20,부채변동표!$P$5:$P$20000,"F99")-SUMIFS(BS_원본!$K$5:$K$20000,BS_원본!$J$5:$J$20000,"L130",BS_원본!$I$5:$I$20000,설정!$C$20))<1,"OK","확인필요") | E38: BS 항목 매핑(L110·L120·L130)과 변동표 포트폴리오 범위 확인
A39: 33 | B39: 변동표 F31 ↔ TRACE 신계약비 경험차이 | C39: =COUNTIF(IFRS17_사업비!$F$39:$F$42,"차이 확인")&"개 포트폴리오 차이" | D39: =IF(COUNTIF(IFRS17_사업비!$F$39:$F$42,"차이 확인")=0,"OK","참고") | E39: 배분 드라이버·예정사업비 기준이 계리와 같은지 확인 (차이는 정보성)

Sheet 대시보드
A1: =설정!$C$5&" TRACE 대시보드 ("&INT((설정!$C$20-1)/12)&"-"&TEXT(MOD(설정!$C$20-1,12)+1,"00")&")"
A2: ="단위: "&설정!$C$9&" · 자가진단: "&자가진단!$B$4&" · 3자 대사: "&계정변동!$P$25
A4: 총자산 | C4: 자본총계 | E4: CSM | G4: 당기순이익 누계 | I4: 사업비 누계 | K4: 분기 한도 초과(예상)
A5: =차트데이터!B91 | C5: =차트데이터!B92 | E5: =차트데이터!B93 | G5: =차트데이터!B94 | I5: =차트데이터!B95 | K5: =차트데이터!B97
A6: =차트데이터!E91&" 대비 "&TEXT(차트데이터!D91,"+0.0%;-0.0%;0.0%") | C6: =차트데이터!E92&" 대비 "&TEXT(차트데이터!D92,"+0.0%;-0.0%;0.0%") | E6: =차트데이터!E93&" 대비 "&TEXT(차트데이터!D93,"+0.0%;-0.0%;0.0%") | G6: =차트데이터!E94&" 대비 "&TEXT(차트데이터!D94,"+0.0%;-0.0%;0.0%") | I6: =차트데이터!E95&" 대비 "&TEXT(차트데이터!D95,"+0.0%;-0.0%;0.0%") | K6: ="주의 "&차트데이터!C97&"건"
A58: 주의 대상 TOP 10
A59: 순위 | B59: 부서 | C59: 계정 | D59: 당월 | E59: 전월대비 | F59: 예산 | G59: 신호
A60: =주의대상!A6 | B60: =주의대상!B6 | C60: =주의대상!C6 | D60: =주의대상!D6 | E60: =주의대상!E6 | F60: =주의대상!G6 | G60: =주의대상!J6
A61: =주의대상!A7 | B61: =주의대상!B7 | C61: =주의대상!C7 | D61: =주의대상!D7 | E61: =주의대상!E7 | F61: =주의대상!G7 | G61: =주의대상!J7
A62: =주의대상!A8 | B62: =주의대상!B8 | C62: =주의대상!C8 | D62: =주의대상!D8 | E62: =주의대상!E8 | F62: =주의대상!G8 | G62: =주의대상!J8
A63: =주의대상!A9 | B63: =주의대상!B9 | C63: =주의대상!C9 | D63: =주의대상!D9 | E63: =주의대상!E9 | F63: =주의대상!G9 | G63: =주의대상!J9
A64: =주의대상!A10 | B64: =주의대상!B10 | C64: =주의대상!C10 | D64: =주의대상!D10 | E64: =주의대상!E10 | F64: =주의대상!G10 | G64: =주의대상!J10
A65: =주의대상!A11 | B65: =주의대상!B11 | C65: =주의대상!C11 | D65: =주의대상!D11 | E65: =주의대상!E11 | F65: =주의대상!G11 | G65: =주의대상!J11
A66: =주의대상!A12 | B66: =주의대상!B12 | C66: =주의대상!C12 | D66: =주의대상!D12 | E66: =주의대상!E12 | F66: =주의대상!G12 | G66: =주의대상!J12
A67: =주의대상!A13 | B67: =주의대상!B13 | C67: =주의대상!C13 | D67: =주의대상!D13 | E67: =주의대상!E13 | F67: =주의대상!G13 | G67: =주의대상!J13
A68: =주의대상!A14 | B68: =주의대상!B14 | C68: =주의대상!C14 | D68: =주의대상!D14 | E68: =주의대상!E14 | F68: =주의대상!G14 | G68: =주의대상!J14
A69: =주의대상!A15 | B69: =주의대상!B15 | C69: =주의대상!C15 | D69: =주의대상!D15 | E69: =주의대상!E15 | F69: =주의대상!G15 | G69: =주의대상!J15
A71: 선택 항목 원인 (원인분석 시트)
A72: =원인분석!A18
A75: IFRS 17 사업비 영향 (GMM · VFA)
A76: =IFRS17_사업비!A5

Sheet IFRS17_사업비
A1: TRACE · IFRS 17 사업비 영향 (GMM · VFA · PAA)
A2: 사업비 전표 → 계정대체 → 포트폴리오 → 예정 대비 경험차이 → CSM(GMM·VFA)·당기손익 · 금액: 보고단위
A3: ="기준: "&INT((설정!$C$20-1)/12)&"-"&TEXT(MOD(설정!$C$20-1,12)+1,"00")&" · 단위: "&설정!$C$9
A5: ="GMM CSM 당월 변동 "&TEXT(E57,"+#,##0;-#,##0;0")&" 중 사업비 관련 "&TEXT(E58,"+#,##0.0;-#,##0.0;0")&" (취득현금흐름 경험조정 "&TEXT(E50,"+#,##0.0;-#,##0.0;0")&", 사업비 가정변경 "&TEXT(E48,"+#,##0.0;-#,##0.0;0")&"). "&"신계약비 실제가 예정보다 "&TEXT(ABS(SUMIFS($G$20:$G$31,$D$20:$D$31,"신계약비")),"#,##0.0")&IF(SUMIFS($G$20:$G$31,$D$20:$D$31,"신계약비")<0," 많았고"," 적었고")&IF(B79="","",", 증가 기여 1위는 "&B79&" "&C79&" ("&TEXT(F79,"+#,##0.0;-#,##0.0;0")&")")&IF(B87="","",", 대표 전표는 "&E87&" '"&F87&"' "&TEXT(H87,"#,##0.0"))&". "&"당기손익 반영 경험차이 "&TEXT(G34,"+#,##0.0;-#,##0.0;0")&". "&"VFA(변액) CSM 당월 변동 "&TEXT(E74,"+#,##0;-#,##0;0")&" 중 사업비 관련 "&TEXT(E75,"+#,##0.0;-#,##0.0;0")&"."
L6: 키 | M6: 당월 신계약 | N6: 전월 신계약 | O6: 증감 | P6: 정렬키
L7: =IF(변동분석!$A7="","",변동분석!$E7) | M7: =IF(L7="",0,SUMIFS(전표_원본!$Z$5:$Z$100000,전표_원본!$O$5:$O$100000,L7,전표_원본!$M$5:$M$100000,설정!$C$20)) | N7: =IF(L7="",0,SUMIFS(전표_원본!$Z$5:$Z$100000,전표_원본!$O$5:$O$100000,L7,전표_원본!$M$5:$M$100000,설정!$C$20-1)) | O7: =M7-N7 | P7: =IF(L7="","",O7+ROW()/1000000)
A8: 1. 계정대체 결과 요약 (전표 기준) | L8: =IF(변동분석!$A8="","",변동분석!$E8) | M8: =IF(L8="",0,SUMIFS(전표_원본!$Z$5:$Z$100000,전표_원본!$O$5:$O$100000,L8,전표_원본!$M$5:$M$100000,설정!$C$20)) | N8: =IF(L8="",0,SUMIFS(전표_원본!$Z$5:$Z$100000,전표_원본!$O$5:$O$100000,L8,전표_원본!$M$5:$M$100000,설정!$C$20-1)) | O8: =M8-N8 | P8: =IF(L8="","",O8+ROW()/1000000)
A9: 구분 | B9: 당월 | C9: 전월 | D9: 누계 | E9: 당월 비중 | L9: =IF(변동분석!$A9="","",변동분석!$E9) | M9: =IF(L9="",0,SUMIFS(전표_원본!$Z$5:$Z$100000,전표_원본!$O$5:$O$100000,L9,전표_원본!$M$5:$M$100000,설정!$C$20)) | N9: =IF(L9="",0,SUMIFS(전표_원본!$Z$5:$Z$100000,전표_원본!$O$5:$O$100000,L9,전표_원본!$M$5:$M$100000,설정!$C$20-1)) | O9: =M9-N9 | P9: =IF(L9="","",O9+ROW()/1000000)
A10: 비귀속 | B10: =SUMIFS(전표_원본!$Y$5:$Y$100000,전표_원본!$M$5:$M$100000,설정!$C$20) | C10: =SUMIFS(전표_원본!$Y$5:$Y$100000,전표_원본!$M$5:$M$100000,설정!$C$20-1) | D10: =SUMIFS(전표_원본!$Y$5:$Y$100000,전표_원본!$M$5:$M$100000,">="&(설정!$C$6*12+1),전표_원본!$M$5:$M$100000,"<="&설정!$C$20) | E10: =IF($B$15=0,0,B10/$B$15) | L10: =IF(변동분석!$A10="","",변동분석!$E10) | M10: =IF(L10="",0,SUMIFS(전표_원본!$Z$5:$Z$100000,전표_원본!$O$5:$O$100000,L10,전표_원본!$M$5:$M$100000,설정!$C$20)) | N10: =IF(L10="",0,SUMIFS(전표_원본!$Z$5:$Z$100000,전표_원본!$O$5:$O$100000,L10,전표_원본!$M$5:$M$100000,설정!$C$20-1)) | O10: =M10-N10 | P10: =IF(L10="","",O10+ROW()/1000000)
A11: 신계약비 | B11: =SUMIFS(전표_원본!$Z$5:$Z$100000,전표_원본!$M$5:$M$100000,설정!$C$20) | C11: =SUMIFS(전표_원본!$Z$5:$Z$100000,전표_원본!$M$5:$M$100000,설정!$C$20-1) | D11: =SUMIFS(전표_원본!$Z$5:$Z$100000,전표_원본!$M$5:$M$100000,">="&(설정!$C$6*12+1),전표_원본!$M$5:$M$100000,"<="&설정!$C$20) | E11: =IF($B$15=0,0,B11/$B$15) | L11: =IF(변동분석!$A11="","",변동분석!$E11) | M11: =IF(L11="",0,SUMIFS(전표_원본!$Z$5:$Z$100000,전표_원본!$O$5:$O$100000,L11,전표_원본!$M$5:$M$100000,설정!$C$20)) | N11: =IF(L11="",0,SUMIFS(전표_원본!$Z$5:$Z$100000,전표_원본!$O$5:$O$100000,L11,전표_원본!$M$5:$M$100000,설정!$C$20-1)) | O11: =M11-N11 | P11: =IF(L11="","",O11+ROW()/1000000)
A12: 유지비 | B12: =SUMIFS(전표_원본!$AA$5:$AA$100000,전표_원본!$M$5:$M$100000,설정!$C$20) | C12: =SUMIFS(전표_원본!$AA$5:$AA$100000,전표_원본!$M$5:$M$100000,설정!$C$20-1) | D12: =SUMIFS(전표_원본!$AA$5:$AA$100000,전표_원본!$M$5:$M$100000,">="&(설정!$C$6*12+1),전표_원본!$M$5:$M$100000,"<="&설정!$C$20) | E12: =IF($B$15=0,0,B12/$B$15) | L12: =IF(변동분석!$A12="","",변동분석!$E12) | M12: =IF(L12="",0,SUMIFS(전표_원본!$Z$5:$Z$100000,전표_원본!$O$5:$O$100000,L12,전표_원본!$M$5:$M$100000,설정!$C$20)) | N12: =IF(L12="",0,SUMIFS(전표_원본!$Z$5:$Z$100000,전표_원본!$O$5:$O$100000,L12,전표_원본!$M$5:$M$100000,설정!$C$20-1)) | O12: =M12-N12 | P12: =IF(L12="","",O12+ROW()/1000000)
A13: 수금비 | B13: =SUMIFS(전표_원본!$AB$5:$AB$100000,전표_원본!$M$5:$M$100000,설정!$C$20) | C13: =SUMIFS(전표_원본!$AB$5:$AB$100000,전표_원본!$M$5:$M$100000,설정!$C$20-1) | D13: =SUMIFS(전표_원본!$AB$5:$AB$100000,전표_원본!$M$5:$M$100000,">="&(설정!$C$6*12+1),전표_원본!$M$5:$M$100000,"<="&설정!$C$20) | E13: =IF($B$15=0,0,B13/$B$15) | L13: =IF(변동분석!$A13="","",변동분석!$E13) | M13: =IF(L13="",0,SUMIFS(전표_원본!$Z$5:$Z$100000,전표_원본!$O$5:$O$100000,L13,전표_원본!$M$5:$M$100000,설정!$C$20)) | N13: =IF(L13="",0,SUMIFS(전표_원본!$Z$5:$Z$100000,전표_원본!$O$5:$O$100000,L13,전표_원본!$M$5:$M$100000,설정!$C$20-1)) | O13: =M13-N13 | P13: =IF(L13="","",O13+ROW()/1000000)
A14: 재산관리비 | B14: =SUMIFS(전표_원본!$AD$5:$AD$100000,전표_원본!$M$5:$M$100000,설정!$C$20) | C14: =SUMIFS(전표_원본!$AD$5:$AD$100000,전표_원본!$M$5:$M$100000,설정!$C$20-1) | D14: =SUMIFS(전표_원본!$AD$5:$AD$100000,전표_원본!$M$5:$M$100000,">="&(설정!$C$6*12+1),전표_원본!$M$5:$M$100000,"<="&설정!$C$20) | E14: =IF($B$15=0,0,B14/$B$15) | L14: =IF(변동분석!$A14="","",변동분석!$E14) | M14: =IF(L14="",0,SUMIFS(전표_원본!$Z$5:$Z$100000,전표_원본!$O$5:$O$100000,L14,전표_원본!$M$5:$M$100000,설정!$C$20)) | N14: =IF(L14="",0,SUMIFS(전표_원본!$Z$5:$Z$100000,전표_원본!$O$5:$O$100000,L14,전표_원본!$M$5:$M$100000,설정!$C$20-1)) | O14: =M14-N14 | P14: =IF(L14="","",O14+ROW()/1000000)
A15: 합계 (= 전표 사업비) | B15: =SUM(B10:B14) | C15: =SUM(C10:C14) | D15: =SUM(D10:D14) | E15: =SUM(E10:E14) | L15: =IF(변동분석!$A15="","",변동분석!$E15) | M15: =IF(L15="",0,SUMIFS(전표_원본!$Z$5:$Z$100000,전표_원본!$O$5:$O$100000,L15,전표_원본!$M$5:$M$100000,설정!$C$20)) | N15: =IF(L15="",0,SUMIFS(전표_원본!$Z$5:$Z$100000,전표_원본!$O$5:$O$100000,L15,전표_원본!$M$5:$M$100000,설정!$C$20-1)) | O15: =M15-N15 | P15: =IF(L15="","",O15+ROW()/1000000)
A16: 재산관리비는 IFRS 17 이행현금흐름 밖 (PL 투자손익에서 차감) · 비귀속은 기타사업비용 | L16: =IF(변동분석!$A16="","",변동분석!$E16) | M16: =IF(L16="",0,SUMIFS(전표_원본!$Z$5:$Z$100000,전표_원본!$O$5:$O$100000,L16,전표_원본!$M$5:$M$100000,설정!$C$20)) | N16: =IF(L16="",0,SUMIFS(전표_원본!$Z$5:$Z$100000,전표_원본!$O$5:$O$100000,L16,전표_원본!$M$5:$M$100000,설정!$C$20-1)) | O16: =M16-N16 | P16: =IF(L16="","",O16+ROW()/1000000)
L17: =IF(변동분석!$A17="","",변동분석!$E17) | M17: =IF(L17="",0,SUMIFS(전표_원본!$Z$5:$Z$100000,전표_원본!$O$5:$O$100000,L17,전표_원본!$M$5:$M$100000,설정!$C$20)) | N17: =IF(L17="",0,SUMIFS(전표_원본!$Z$5:$Z$100000,전표_원본!$O$5:$O$100000,L17,전표_원본!$M$5:$M$100000,설정!$C$20-1)) | O17: =M17-N17 | P17: =IF(L17="","",O17+ROW()/1000000)
A18: 2. 포트폴리오별 경험차이 (당월, 예정 − 실제 · 음수 = 불리) | L18: =IF(변동분석!$A18="","",변동분석!$E18) | M18: =IF(L18="",0,SUMIFS(전표_원본!$Z$5:$Z$100000,전표_원본!$O$5:$O$100000,L18,전표_원본!$M$5:$M$100000,설정!$C$20)) | N18: =IF(L18="",0,SUMIFS(전표_원본!$Z$5:$Z$100000,전표_원본!$O$5:$O$100000,L18,전표_원본!$M$5:$M$100000,설정!$C$20-1)) | O18: =M18-N18 | P18: =IF(L18="","",O18+ROW()/1000000)
A19: 포트폴리오 | B19: 포트폴리오명 | C19: 측정모형 | D19: 구분 | E19: 실제 | F19: 예정 | G19: 경험차이 | H19: 반영처 | I19: CSM 반영 | J19: 당기손익 반영 | L19: =IF(변동분석!$A19="","",변동분석!$E19) | M19: =IF(L19="",0,SUMIFS(전표_원본!$Z$5:$Z$100000,전표_원본!$O$5:$O$100000,L19,전표_원본!$M$5:$M$100000,설정!$C$20)) | N19: =IF(L19="",0,SUMIFS(전표_원본!$Z$5:$Z$100000,전표_원본!$O$5:$O$100000,L19,전표_원본!$M$5:$M$100000,설정!$C$20-1)) | O19: =M19-N19 | P19: =IF(L19="","",O19+ROW()/1000000)
A20: PF01 | B20: =IFERROR(INDEX(계정대체기준!$B$54:$B$63,MATCH($A20,계정대체기준!$A$54:$A$63,0)),"") | C20: =IFERROR(INDEX(계정대체기준!$C$54:$C$63,MATCH($A20,계정대체기준!$A$54:$A$63,0)),"") | D20: 신계약비 | E20: =$B$11*IFERROR(INDEX(계정대체기준!$D$54:$D$63,MATCH($A20,계정대체기준!$A$54:$A$63,0)),0) | F20: =SUMIFS(예정사업비!$J$5:$J$20000,예정사업비!$I$5:$I$20000,설정!$C$20,예정사업비!$C$5:$C$20000,$A20) | G20: =F20-E20 | H20: =IF(D20<>"신계약비","당기손익(보험서비스결과)",IF(C20="PAA",IF(계정대체기준!$C$68="이연 후 상각","잔여보장부채 이연(상각)","당기손익"),IF((IFERROR(INDEX(계정대체기준!$I$54:$I$63,MATCH($A20,계정대체기준!$A$54:$A$63,0)),"N")="Y"),"당기손익(손실요소)",IF(IF(계정대체기준!$C$67="전액 CSM",1,IF(계정대체기준!$C$67="전액 당기손익",0,IFERROR(INDEX(계정대체기준!$H$54:$H$63,MATCH($A20,계정대체기준!$A$54:$A$63,0)),0)))>=1,"CSM 조정 ("&C20&")",IF(IF(계정대체기준!$C$67="전액 CSM",1,IF(계정대체기준!$C$67="전액 당기손익",0,IFERROR(INDEX(계정대체기준!$H$54:$H$63,MATCH($A20,계정대체기준!$A$54:$A$63,0)),0)))<=0,"당기손익","CSM "&TEXT(IF(계정대체기준!$C$67="전액 CSM",1,IF(계정대체기준!$C$67="전액 당기손익",0,IFERROR(INDEX(계정대체기준!$H$54:$H$63,MATCH($A20,계정대체기준!$A$54:$A$63,0)),0))),"0%")&" ("&C20&") · 나머지 손익"))))) | I20: =IF(AND(D20="신계약비",OR(C20="GMM",C20="VFA"),NOT((IFERROR(INDEX(계정대체기준!$I$54:$I$63,MATCH($A20,계정대체기준!$A$54:$A$63,0)),"N")="Y"))),G20*IF(계정대체기준!$C$67="전액 CSM",1,IF(계정대체기준!$C$67="전액 당기손익",0,IFERROR(INDEX(계정대체기준!$H$54:$H$63,MATCH($A20,계정대체기준!$A$54:$A$63,0)),0))),0) | J20: =IF(AND(D20="신계약비",C20="PAA",계정대체기준!$C$68="이연 후 상각"),0,G20-I20) | L20: =IF(변동분석!$A20="","",변동분석!$E20) | M20: =IF(L20="",0,SUMIFS(전표_원본!$Z$5:$Z$100000,전표_원본!$O$5:$O$100000,L20,전표_원본!$M$5:$M$100000,설정!$C$20)) | N20: =IF(L20="",0,SUMIFS(전표_원본!$Z$5:$Z$100000,전표_원본!$O$5:$O$100000,L20,전표_원본!$M$5:$M$100000,설정!$C$20-1)) | O20: =M20-N20 | P20: =IF(L20="","",O20+ROW()/1000000)
A21: PF01 | B21: =IFERROR(INDEX(계정대체기준!$B$54:$B$63,MATCH($A21,계정대체기준!$A$54:$A$63,0)),"") | C21: =IFERROR(INDEX(계정대체기준!$C$54:$C$63,MATCH($A21,계정대체기준!$A$54:$A$63,0)),"") | D21: 유지비 | E21: =$B$12*IFERROR(INDEX(계정대체기준!$E$54:$E$63,MATCH($A21,계정대체기준!$A$54:$A$63,0)),0) | F21: =SUMIFS(예정사업비!$K$5:$K$20000,예정사업비!$I$5:$I$20000,설정!$C$20,예정사업비!$C$5:$C$20000,$A21) | G21: =F21-E21 | H21: =IF(D21<>"신계약비","당기손익(보험서비스결과)",IF(C21="PAA",IF(계정대체기준!$C$68="이연 후 상각","잔여보장부채 이연(상각)","당기손익"),IF((IFERROR(INDEX(계정대체기준!$I$54:$I$63,MATCH($A21,계정대체기준!$A$54:$A$63,0)),"N")="Y"),"당기손익(손실요소)",IF(IF(계정대체기준!$C$67="전액 CSM",1,IF(계정대체기준!$C$67="전액 당기손익",0,IFERROR(INDEX(계정대체기준!$H$54:$H$63,MATCH($A21,계정대체기준!$A$54:$A$63,0)),0)))>=1,"CSM 조정 ("&C21&")",IF(IF(계정대체기준!$C$67="전액 CSM",1,IF(계정대체기준!$C$67="전액 당기손익",0,IFERROR(INDEX(계정대체기준!$H$54:$H$63,MATCH($A21,계정대체기준!$A$54:$A$63,0)),0)))<=0,"당기손익","CSM "&TEXT(IF(계정대체기준!$C$67="전액 CSM",1,IF(계정대체기준!$C$67="전액 당기손익",0,IFERROR(INDEX(계정대체기준!$H$54:$H$63,MATCH($A21,계정대체기준!$A$54:$A$63,0)),0))),"0%")&" ("&C21&") · 나머지 손익"))))) | I21: =IF(AND(D21="신계약비",OR(C21="GMM",C21="VFA"),NOT((IFERROR(INDEX(계정대체기준!$I$54:$I$63,MATCH($A21,계정대체기준!$A$54:$A$63,0)),"N")="Y"))),G21*IF(계정대체기준!$C$67="전액 CSM",1,IF(계정대체기준!$C$67="전액 당기손익",0,IFERROR(INDEX(계정대체기준!$H$54:$H$63,MATCH($A21,계정대체기준!$A$54:$A$63,0)),0))),0) | J21: =IF(AND(D21="신계약비",C21="PAA",계정대체기준!$C$68="이연 후 상각"),0,G21-I21) | L21: =IF(변동분석!$A21="","",변동분석!$E21) | M21: =IF(L21="",0,SUMIFS(전표_원본!$Z$5:$Z$100000,전표_원본!$O$5:$O$100000,L21,전표_원본!$M$5:$M$100000,설정!$C$20)) | N21: =IF(L21="",0,SUMIFS(전표_원본!$Z$5:$Z$100000,전표_원본!$O$5:$O$100000,L21,전표_원본!$M$5:$M$100000,설정!$C$20-1)) | O21: =M21-N21 | P21: =IF(L21="","",O21+ROW()/1000000)
A22: PF01 | B22: =IFERROR(INDEX(계정대체기준!$B$54:$B$63,MATCH($A22,계정대체기준!$A$54:$A$63,0)),"") | C22: =IFERROR(INDEX(계정대체기준!$C$54:$C$63,MATCH($A22,계정대체기준!$A$54:$A$63,0)),"") | D22: 수금비 | E22: =$B$13*IFERROR(INDEX(계정대체기준!$F$54:$F$63,MATCH($A22,계정대체기준!$A$54:$A$63,0)),0) | F22: =SUMIFS(예정사업비!$L$5:$L$20000,예정사업비!$I$5:$I$20000,설정!$C$20,예정사업비!$C$5:$C$20000,$A22) | G22: =F22-E22 | H22: =IF(D22<>"신계약비","당기손익(보험서비스결과)",IF(C22="PAA",IF(계정대체기준!$C$68="이연 후 상각","잔여보장부채 이연(상각)","당기손익"),IF((IFERROR(INDEX(계정대체기준!$I$54:$I$63,MATCH($A22,계정대체기준!$A$54:$A$63,0)),"N")="Y"),"당기손익(손실요소)",IF(IF(계정대체기준!$C$67="전액 CSM",1,IF(계정대체기준!$C$67="전액 당기손익",0,IFERROR(INDEX(계정대체기준!$H$54:$H$63,MATCH($A22,계정대체기준!$A$54:$A$63,0)),0)))>=1,"CSM 조정 ("&C22&")",IF(IF(계정대체기준!$C$67="전액 CSM",1,IF(계정대체기준!$C$67="전액 당기손익",0,IFERROR(INDEX(계정대체기준!$H$54:$H$63,MATCH($A22,계정대체기준!$A$54:$A$63,0)),0)))<=0,"당기손익","CSM "&TEXT(IF(계정대체기준!$C$67="전액 CSM",1,IF(계정대체기준!$C$67="전액 당기손익",0,IFERROR(INDEX(계정대체기준!$H$54:$H$63,MATCH($A22,계정대체기준!$A$54:$A$63,0)),0))),"0%")&" ("&C22&") · 나머지 손익"))))) | I22: =IF(AND(D22="신계약비",OR(C22="GMM",C22="VFA"),NOT((IFERROR(INDEX(계정대체기준!$I$54:$I$63,MATCH($A22,계정대체기준!$A$54:$A$63,0)),"N")="Y"))),G22*IF(계정대체기준!$C$67="전액 CSM",1,IF(계정대체기준!$C$67="전액 당기손익",0,IFERROR(INDEX(계정대체기준!$H$54:$H$63,MATCH($A22,계정대체기준!$A$54:$A$63,0)),0))),0) | J22: =IF(AND(D22="신계약비",C22="PAA",계정대체기준!$C$68="이연 후 상각"),0,G22-I22) | L22: =IF(변동분석!$A22="","",변동분석!$E22) | M22: =IF(L22="",0,SUMIFS(전표_원본!$Z$5:$Z$100000,전표_원본!$O$5:$O$100000,L22,전표_원본!$M$5:$M$100000,설정!$C$20)) | N22: =IF(L22="",0,SUMIFS(전표_원본!$Z$5:$Z$100000,전표_원본!$O$5:$O$100000,L22,전표_원본!$M$5:$M$100000,설정!$C$20-1)) | O22: =M22-N22 | P22: =IF(L22="","",O22+ROW()/1000000)
A23: PF02 | B23: =IFERROR(INDEX(계정대체기준!$B$54:$B$63,MATCH($A23,계정대체기준!$A$54:$A$63,0)),"") | C23: =IFERROR(INDEX(계정대체기준!$C$54:$C$63,MATCH($A23,계정대체기준!$A$54:$A$63,0)),"") | D23: 신계약비 | E23: =$B$11*IFERROR(INDEX(계정대체기준!$D$54:$D$63,MATCH($A23,계정대체기준!$A$54:$A$63,0)),0) | F23: =SUMIFS(예정사업비!$J$5:$J$20000,예정사업비!$I$5:$I$20000,설정!$C$20,예정사업비!$C$5:$C$20000,$A23) | G23: =F23-E23 | H23: =IF(D23<>"신계약비","당기손익(보험서비스결과)",IF(C23="PAA",IF(계정대체기준!$C$68="이연 후 상각","잔여보장부채 이연(상각)","당기손익"),IF((IFERROR(INDEX(계정대체기준!$I$54:$I$63,MATCH($A23,계정대체기준!$A$54:$A$63,0)),"N")="Y"),"당기손익(손실요소)",IF(IF(계정대체기준!$C$67="전액 CSM",1,IF(계정대체기준!$C$67="전액 당기손익",0,IFERROR(INDEX(계정대체기준!$H$54:$H$63,MATCH($A23,계정대체기준!$A$54:$A$63,0)),0)))>=1,"CSM 조정 ("&C23&")",IF(IF(계정대체기준!$C$67="전액 CSM",1,IF(계정대체기준!$C$67="전액 당기손익",0,IFERROR(INDEX(계정대체기준!$H$54:$H$63,MATCH($A23,계정대체기준!$A$54:$A$63,0)),0)))<=0,"당기손익","CSM "&TEXT(IF(계정대체기준!$C$67="전액 CSM",1,IF(계정대체기준!$C$67="전액 당기손익",0,IFERROR(INDEX(계정대체기준!$H$54:$H$63,MATCH($A23,계정대체기준!$A$54:$A$63,0)),0))),"0%")&" ("&C23&") · 나머지 손익"))))) | I23: =IF(AND(D23="신계약비",OR(C23="GMM",C23="VFA"),NOT((IFERROR(INDEX(계정대체기준!$I$54:$I$63,MATCH($A23,계정대체기준!$A$54:$A$63,0)),"N")="Y"))),G23*IF(계정대체기준!$C$67="전액 CSM",1,IF(계정대체기준!$C$67="전액 당기손익",0,IFERROR(INDEX(계정대체기준!$H$54:$H$63,MATCH($A23,계정대체기준!$A$54:$A$63,0)),0))),0) | J23: =IF(AND(D23="신계약비",C23="PAA",계정대체기준!$C$68="이연 후 상각"),0,G23-I23) | L23: =IF(변동분석!$A23="","",변동분석!$E23) | M23: =IF(L23="",0,SUMIFS(전표_원본!$Z$5:$Z$100000,전표_원본!$O$5:$O$100000,L23,전표_원본!$M$5:$M$100000,설정!$C$20)) | N23: =IF(L23="",0,SUMIFS(전표_원본!$Z$5:$Z$100000,전표_원본!$O$5:$O$100000,L23,전표_원본!$M$5:$M$100000,설정!$C$20-1)) | O23: =M23-N23 | P23: =IF(L23="","",O23+ROW()/1000000)
A24: PF02 | B24: =IFERROR(INDEX(계정대체기준!$B$54:$B$63,MATCH($A24,계정대체기준!$A$54:$A$63,0)),"") | C24: =IFERROR(INDEX(계정대체기준!$C$54:$C$63,MATCH($A24,계정대체기준!$A$54:$A$63,0)),"") | D24: 유지비 | E24: =$B$12*IFERROR(INDEX(계정대체기준!$E$54:$E$63,MATCH($A24,계정대체기준!$A$54:$A$63,0)),0) | F24: =SUMIFS(예정사업비!$K$5:$K$20000,예정사업비!$I$5:$I$20000,설정!$C$20,예정사업비!$C$5:$C$20000,$A24) | G24: =F24-E24 | H24: =IF(D24<>"신계약비","당기손익(보험서비스결과)",IF(C24="PAA",IF(계정대체기준!$C$68="이연 후 상각","잔여보장부채 이연(상각)","당기손익"),IF((IFERROR(INDEX(계정대체기준!$I$54:$I$63,MATCH($A24,계정대체기준!$A$54:$A$63,0)),"N")="Y"),"당기손익(손실요소)",IF(IF(계정대체기준!$C$67="전액 CSM",1,IF(계정대체기준!$C$67="전액 당기손익",0,IFERROR(INDEX(계정대체기준!$H$54:$H$63,MATCH($A24,계정대체기준!$A$54:$A$63,0)),0)))>=1,"CSM 조정 ("&C24&")",IF(IF(계정대체기준!$C$67="전액 CSM",1,IF(계정대체기준!$C$67="전액 당기손익",0,IFERROR(INDEX(계정대체기준!$H$54:$H$63,MATCH($A24,계정대체기준!$A$54:$A$63,0)),0)))<=0,"당기손익","CSM "&TEXT(IF(계정대체기준!$C$67="전액 CSM",1,IF(계정대체기준!$C$67="전액 당기손익",0,IFERROR(INDEX(계정대체기준!$H$54:$H$63,MATCH($A24,계정대체기준!$A$54:$A$63,0)),0))),"0%")&" ("&C24&") · 나머지 손익"))))) | I24: =IF(AND(D24="신계약비",OR(C24="GMM",C24="VFA"),NOT((IFERROR(INDEX(계정대체기준!$I$54:$I$63,MATCH($A24,계정대체기준!$A$54:$A$63,0)),"N")="Y"))),G24*IF(계정대체기준!$C$67="전액 CSM",1,IF(계정대체기준!$C$67="전액 당기손익",0,IFERROR(INDEX(계정대체기준!$H$54:$H$63,MATCH($A24,계정대체기준!$A$54:$A$63,0)),0))),0) | J24: =IF(AND(D24="신계약비",C24="PAA",계정대체기준!$C$68="이연 후 상각"),0,G24-I24) | L24: =IF(변동분석!$A24="","",변동분석!$E24) | M24: =IF(L24="",0,SUMIFS(전표_원본!$Z$5:$Z$100000,전표_원본!$O$5:$O$100000,L24,전표_원본!$M$5:$M$100000,설정!$C$20)) | N24: =IF(L24="",0,SUMIFS(전표_원본!$Z$5:$Z$100000,전표_원본!$O$5:$O$100000,L24,전표_원본!$M$5:$M$100000,설정!$C$20-1)) | O24: =M24-N24 | P24: =IF(L24="","",O24+ROW()/1000000)
A25: PF02 | B25: =IFERROR(INDEX(계정대체기준!$B$54:$B$63,MATCH($A25,계정대체기준!$A$54:$A$63,0)),"") | C25: =IFERROR(INDEX(계정대체기준!$C$54:$C$63,MATCH($A25,계정대체기준!$A$54:$A$63,0)),"") | D25: 수금비 | E25: =$B$13*IFERROR(INDEX(계정대체기준!$F$54:$F$63,MATCH($A25,계정대체기준!$A$54:$A$63,0)),0) | F25: =SUMIFS(예정사업비!$L$5:$L$20000,예정사업비!$I$5:$I$20000,설정!$C$20,예정사업비!$C$5:$C$20000,$A25) | G25: =F25-E25 | H25: =IF(D25<>"신계약비","당기손익(보험서비스결과)",IF(C25="PAA",IF(계정대체기준!$C$68="이연 후 상각","잔여보장부채 이연(상각)","당기손익"),IF((IFERROR(INDEX(계정대체기준!$I$54:$I$63,MATCH($A25,계정대체기준!$A$54:$A$63,0)),"N")="Y"),"당기손익(손실요소)",IF(IF(계정대체기준!$C$67="전액 CSM",1,IF(계정대체기준!$C$67="전액 당기손익",0,IFERROR(INDEX(계정대체기준!$H$54:$H$63,MATCH($A25,계정대체기준!$A$54:$A$63,0)),0)))>=1,"CSM 조정 ("&C25&")",IF(IF(계정대체기준!$C$67="전액 CSM",1,IF(계정대체기준!$C$67="전액 당기손익",0,IFERROR(INDEX(계정대체기준!$H$54:$H$63,MATCH($A25,계정대체기준!$A$54:$A$63,0)),0)))<=0,"당기손익","CSM "&TEXT(IF(계정대체기준!$C$67="전액 CSM",1,IF(계정대체기준!$C$67="전액 당기손익",0,IFERROR(INDEX(계정대체기준!$H$54:$H$63,MATCH($A25,계정대체기준!$A$54:$A$63,0)),0))),"0%")&" ("&C25&") · 나머지 손익"))))) | I25: =IF(AND(D25="신계약비",OR(C25="GMM",C25="VFA"),NOT((IFERROR(INDEX(계정대체기준!$I$54:$I$63,MATCH($A25,계정대체기준!$A$54:$A$63,0)),"N")="Y"))),G25*IF(계정대체기준!$C$67="전액 CSM",1,IF(계정대체기준!$C$67="전액 당기손익",0,IFERROR(INDEX(계정대체기준!$H$54:$H$63,MATCH($A25,계정대체기준!$A$54:$A$63,0)),0))),0) | J25: =IF(AND(D25="신계약비",C25="PAA",계정대체기준!$C$68="이연 후 상각"),0,G25-I25) | L25: =IF(변동분석!$A25="","",변동분석!$E25) | M25: =IF(L25="",0,SUMIFS(전표_원본!$Z$5:$Z$100000,전표_원본!$O$5:$O$100000,L25,전표_원본!$M$5:$M$100000,설정!$C$20)) | N25: =IF(L25="",0,SUMIFS(전표_원본!$Z$5:$Z$100000,전표_원본!$O$5:$O$100000,L25,전표_원본!$M$5:$M$100000,설정!$C$20-1)) | O25: =M25-N25 | P25: =IF(L25="","",O25+ROW()/1000000)
A26: PF03 | B26: =IFERROR(INDEX(계정대체기준!$B$54:$B$63,MATCH($A26,계정대체기준!$A$54:$A$63,0)),"") | C26: =IFERROR(INDEX(계정대체기준!$C$54:$C$63,MATCH($A26,계정대체기준!$A$54:$A$63,0)),"") | D26: 신계약비 | E26: =$B$11*IFERROR(INDEX(계정대체기준!$D$54:$D$63,MATCH($A26,계정대체기준!$A$54:$A$63,0)),0) | F26: =SUMIFS(예정사업비!$J$5:$J$20000,예정사업비!$I$5:$I$20000,설정!$C$20,예정사업비!$C$5:$C$20000,$A26) | G26: =F26-E26 | H26: =IF(D26<>"신계약비","당기손익(보험서비스결과)",IF(C26="PAA",IF(계정대체기준!$C$68="이연 후 상각","잔여보장부채 이연(상각)","당기손익"),IF((IFERROR(INDEX(계정대체기준!$I$54:$I$63,MATCH($A26,계정대체기준!$A$54:$A$63,0)),"N")="Y"),"당기손익(손실요소)",IF(IF(계정대체기준!$C$67="전액 CSM",1,IF(계정대체기준!$C$67="전액 당기손익",0,IFERROR(INDEX(계정대체기준!$H$54:$H$63,MATCH($A26,계정대체기준!$A$54:$A$63,0)),0)))>=1,"CSM 조정 ("&C26&")",IF(IF(계정대체기준!$C$67="전액 CSM",1,IF(계정대체기준!$C$67="전액 당기손익",0,IFERROR(INDEX(계정대체기준!$H$54:$H$63,MATCH($A26,계정대체기준!$A$54:$A$63,0)),0)))<=0,"당기손익","CSM "&TEXT(IF(계정대체기준!$C$67="전액 CSM",1,IF(계정대체기준!$C$67="전액 당기손익",0,IFERROR(INDEX(계정대체기준!$H$54:$H$63,MATCH($A26,계정대체기준!$A$54:$A$63,0)),0))),"0%")&" ("&C26&") · 나머지 손익"))))) | I26: =IF(AND(D26="신계약비",OR(C26="GMM",C26="VFA"),NOT((IFERROR(INDEX(계정대체기준!$I$54:$I$63,MATCH($A26,계정대체기준!$A$54:$A$63,0)),"N")="Y"))),G26*IF(계정대체기준!$C$67="전액 CSM",1,IF(계정대체기준!$C$67="전액 당기손익",0,IFERROR(INDEX(계정대체기준!$H$54:$H$63,MATCH($A26,계정대체기준!$A$54:$A$63,0)),0))),0) | J26: =IF(AND(D26="신계약비",C26="PAA",계정대체기준!$C$68="이연 후 상각"),0,G26-I26) | L26: =IF(변동분석!$A26="","",변동분석!$E26) | M26: =IF(L26="",0,SUMIFS(전표_원본!$Z$5:$Z$100000,전표_원본!$O$5:$O$100000,L26,전표_원본!$M$5:$M$100000,설정!$C$20)) | N26: =IF(L26="",0,SUMIFS(전표_원본!$Z$5:$Z$100000,전표_원본!$O$5:$O$100000,L26,전표_원본!$M$5:$M$100000,설정!$C$20-1)) | O26: =M26-N26 | P26: =IF(L26="","",O26+ROW()/1000000)
A27: PF03 | B27: =IFERROR(INDEX(계정대체기준!$B$54:$B$63,MATCH($A27,계정대체기준!$A$54:$A$63,0)),"") | C27: =IFERROR(INDEX(계정대체기준!$C$54:$C$63,MATCH($A27,계정대체기준!$A$54:$A$63,0)),"") | D27: 유지비 | E27: =$B$12*IFERROR(INDEX(계정대체기준!$E$54:$E$63,MATCH($A27,계정대체기준!$A$54:$A$63,0)),0) | F27: =SUMIFS(예정사업비!$K$5:$K$20000,예정사업비!$I$5:$I$20000,설정!$C$20,예정사업비!$C$5:$C$20000,$A27) | G27: =F27-E27 | H27: =IF(D27<>"신계약비","당기손익(보험서비스결과)",IF(C27="PAA",IF(계정대체기준!$C$68="이연 후 상각","잔여보장부채 이연(상각)","당기손익"),IF((IFERROR(INDEX(계정대체기준!$I$54:$I$63,MATCH($A27,계정대체기준!$A$54:$A$63,0)),"N")="Y"),"당기손익(손실요소)",IF(IF(계정대체기준!$C$67="전액 CSM",1,IF(계정대체기준!$C$67="전액 당기손익",0,IFERROR(INDEX(계정대체기준!$H$54:$H$63,MATCH($A27,계정대체기준!$A$54:$A$63,0)),0)))>=1,"CSM 조정 ("&C27&")",IF(IF(계정대체기준!$C$67="전액 CSM",1,IF(계정대체기준!$C$67="전액 당기손익",0,IFERROR(INDEX(계정대체기준!$H$54:$H$63,MATCH($A27,계정대체기준!$A$54:$A$63,0)),0)))<=0,"당기손익","CSM "&TEXT(IF(계정대체기준!$C$67="전액 CSM",1,IF(계정대체기준!$C$67="전액 당기손익",0,IFERROR(INDEX(계정대체기준!$H$54:$H$63,MATCH($A27,계정대체기준!$A$54:$A$63,0)),0))),"0%")&" ("&C27&") · 나머지 손익"))))) | I27: =IF(AND(D27="신계약비",OR(C27="GMM",C27="VFA"),NOT((IFERROR(INDEX(계정대체기준!$I$54:$I$63,MATCH($A27,계정대체기준!$A$54:$A$63,0)),"N")="Y"))),G27*IF(계정대체기준!$C$67="전액 CSM",1,IF(계정대체기준!$C$67="전액 당기손익",0,IFERROR(INDEX(계정대체기준!$H$54:$H$63,MATCH($A27,계정대체기준!$A$54:$A$63,0)),0))),0) | J27: =IF(AND(D27="신계약비",C27="PAA",계정대체기준!$C$68="이연 후 상각"),0,G27-I27) | L27: =IF(변동분석!$A27="","",변동분석!$E27) | M27: =IF(L27="",0,SUMIFS(전표_원본!$Z$5:$Z$100000,전표_원본!$O$5:$O$100000,L27,전표_원본!$M$5:$M$100000,설정!$C$20)) | N27: =IF(L27="",0,SUMIFS(전표_원본!$Z$5:$Z$100000,전표_원본!$O$5:$O$100000,L27,전표_원본!$M$5:$M$100000,설정!$C$20-1)) | O27: =M27-N27 | P27: =IF(L27="","",O27+ROW()/1000000)
A28: PF03 | B28: =IFERROR(INDEX(계정대체기준!$B$54:$B$63,MATCH($A28,계정대체기준!$A$54:$A$63,0)),"") | C28: =IFERROR(INDEX(계정대체기준!$C$54:$C$63,MATCH($A28,계정대체기준!$A$54:$A$63,0)),"") | D28: 수금비 | E28: =$B$13*IFERROR(INDEX(계정대체기준!$F$54:$F$63,MATCH($A28,계정대체기준!$A$54:$A$63,0)),0) | F28: =SUMIFS(예정사업비!$L$5:$L$20000,예정사업비!$I$5:$I$20000,설정!$C$20,예정사업비!$C$5:$C$20000,$A28) | G28: =F28-E28 | H28: =IF(D28<>"신계약비","당기손익(보험서비스결과)",IF(C28="PAA",IF(계정대체기준!$C$68="이연 후 상각","잔여보장부채 이연(상각)","당기손익"),IF((IFERROR(INDEX(계정대체기준!$I$54:$I$63,MATCH($A28,계정대체기준!$A$54:$A$63,0)),"N")="Y"),"당기손익(손실요소)",IF(IF(계정대체기준!$C$67="전액 CSM",1,IF(계정대체기준!$C$67="전액 당기손익",0,IFERROR(INDEX(계정대체기준!$H$54:$H$63,MATCH($A28,계정대체기준!$A$54:$A$63,0)),0)))>=1,"CSM 조정 ("&C28&")",IF(IF(계정대체기준!$C$67="전액 CSM",1,IF(계정대체기준!$C$67="전액 당기손익",0,IFERROR(INDEX(계정대체기준!$H$54:$H$63,MATCH($A28,계정대체기준!$A$54:$A$63,0)),0)))<=0,"당기손익","CSM "&TEXT(IF(계정대체기준!$C$67="전액 CSM",1,IF(계정대체기준!$C$67="전액 당기손익",0,IFERROR(INDEX(계정대체기준!$H$54:$H$63,MATCH($A28,계정대체기준!$A$54:$A$63,0)),0))),"0%")&" ("&C28&") · 나머지 손익"))))) | I28: =IF(AND(D28="신계약비",OR(C28="GMM",C28="VFA"),NOT((IFERROR(INDEX(계정대체기준!$I$54:$I$63,MATCH($A28,계정대체기준!$A$54:$A$63,0)),"N")="Y"))),G28*IF(계정대체기준!$C$67="전액 CSM",1,IF(계정대체기준!$C$67="전액 당기손익",0,IFERROR(INDEX(계정대체기준!$H$54:$H$63,MATCH($A28,계정대체기준!$A$54:$A$63,0)),0))),0) | J28: =IF(AND(D28="신계약비",C28="PAA",계정대체기준!$C$68="이연 후 상각"),0,G28-I28) | L28: =IF(변동분석!$A28="","",변동분석!$E28) | M28: =IF(L28="",0,SUMIFS(전표_원본!$Z$5:$Z$100000,전표_원본!$O$5:$O$100000,L28,전표_원본!$M$5:$M$100000,설정!$C$20)) | N28: =IF(L28="",0,SUMIFS(전표_원본!$Z$5:$Z$100000,전표_원본!$O$5:$O$100000,L28,전표_원본!$M$5:$M$100000,설정!$C$20-1)) | O28: =M28-N28 | P28: =IF(L28="","",O28+ROW()/1000000)
A29: PF04 | B29: =IFERROR(INDEX(계정대체기준!$B$54:$B$63,MATCH($A29,계정대체기준!$A$54:$A$63,0)),"") | C29: =IFERROR(INDEX(계정대체기준!$C$54:$C$63,MATCH($A29,계정대체기준!$A$54:$A$63,0)),"") | D29: 신계약비 | E29: =$B$11*IFERROR(INDEX(계정대체기준!$D$54:$D$63,MATCH($A29,계정대체기준!$A$54:$A$63,0)),0) | F29: =SUMIFS(예정사업비!$J$5:$J$20000,예정사업비!$I$5:$I$20000,설정!$C$20,예정사업비!$C$5:$C$20000,$A29) | G29: =F29-E29 | H29: =IF(D29<>"신계약비","당기손익(보험서비스결과)",IF(C29="PAA",IF(계정대체기준!$C$68="이연 후 상각","잔여보장부채 이연(상각)","당기손익"),IF((IFERROR(INDEX(계정대체기준!$I$54:$I$63,MATCH($A29,계정대체기준!$A$54:$A$63,0)),"N")="Y"),"당기손익(손실요소)",IF(IF(계정대체기준!$C$67="전액 CSM",1,IF(계정대체기준!$C$67="전액 당기손익",0,IFERROR(INDEX(계정대체기준!$H$54:$H$63,MATCH($A29,계정대체기준!$A$54:$A$63,0)),0)))>=1,"CSM 조정 ("&C29&")",IF(IF(계정대체기준!$C$67="전액 CSM",1,IF(계정대체기준!$C$67="전액 당기손익",0,IFERROR(INDEX(계정대체기준!$H$54:$H$63,MATCH($A29,계정대체기준!$A$54:$A$63,0)),0)))<=0,"당기손익","CSM "&TEXT(IF(계정대체기준!$C$67="전액 CSM",1,IF(계정대체기준!$C$67="전액 당기손익",0,IFERROR(INDEX(계정대체기준!$H$54:$H$63,MATCH($A29,계정대체기준!$A$54:$A$63,0)),0))),"0%")&" ("&C29&") · 나머지 손익"))))) | I29: =IF(AND(D29="신계약비",OR(C29="GMM",C29="VFA"),NOT((IFERROR(INDEX(계정대체기준!$I$54:$I$63,MATCH($A29,계정대체기준!$A$54:$A$63,0)),"N")="Y"))),G29*IF(계정대체기준!$C$67="전액 CSM",1,IF(계정대체기준!$C$67="전액 당기손익",0,IFERROR(INDEX(계정대체기준!$H$54:$H$63,MATCH($A29,계정대체기준!$A$54:$A$63,0)),0))),0) | J29: =IF(AND(D29="신계약비",C29="PAA",계정대체기준!$C$68="이연 후 상각"),0,G29-I29) | L29: =IF(변동분석!$A29="","",변동분석!$E29) | M29: =IF(L29="",0,SUMIFS(전표_원본!$Z$5:$Z$100000,전표_원본!$O$5:$O$100000,L29,전표_원본!$M$5:$M$100000,설정!$C$20)) | N29: =IF(L29="",0,SUMIFS(전표_원본!$Z$5:$Z$100000,전표_원본!$O$5:$O$100000,L29,전표_원본!$M$5:$M$100000,설정!$C$20-1)) | O29: =M29-N29 | P29: =IF(L29="","",O29+ROW()/1000000)
A30: PF04 | B30: =IFERROR(INDEX(계정대체기준!$B$54:$B$63,MATCH($A30,계정대체기준!$A$54:$A$63,0)),"") | C30: =IFERROR(INDEX(계정대체기준!$C$54:$C$63,MATCH($A30,계정대체기준!$A$54:$A$63,0)),"") | D30: 유지비 | E30: =$B$12*IFERROR(INDEX(계정대체기준!$E$54:$E$63,MATCH($A30,계정대체기준!$A$54:$A$63,0)),0) | F30: =SUMIFS(예정사업비!$K$5:$K$20000,예정사업비!$I$5:$I$20000,설정!$C$20,예정사업비!$C$5:$C$20000,$A30) | G30: =F30-E30 | H30: =IF(D30<>"신계약비","당기손익(보험서비스결과)",IF(C30="PAA",IF(계정대체기준!$C$68="이연 후 상각","잔여보장부채 이연(상각)","당기손익"),IF((IFERROR(INDEX(계정대체기준!$I$54:$I$63,MATCH($A30,계정대체기준!$A$54:$A$63,0)),"N")="Y"),"당기손익(손실요소)",IF(IF(계정대체기준!$C$67="전액 CSM",1,IF(계정대체기준!$C$67="전액 당기손익",0,IFERROR(INDEX(계정대체기준!$H$54:$H$63,MATCH($A30,계정대체기준!$A$54:$A$63,0)),0)))>=1,"CSM 조정 ("&C30&")",IF(IF(계정대체기준!$C$67="전액 CSM",1,IF(계정대체기준!$C$67="전액 당기손익",0,IFERROR(INDEX(계정대체기준!$H$54:$H$63,MATCH($A30,계정대체기준!$A$54:$A$63,0)),0)))<=0,"당기손익","CSM "&TEXT(IF(계정대체기준!$C$67="전액 CSM",1,IF(계정대체기준!$C$67="전액 당기손익",0,IFERROR(INDEX(계정대체기준!$H$54:$H$63,MATCH($A30,계정대체기준!$A$54:$A$63,0)),0))),"0%")&" ("&C30&") · 나머지 손익"))))) | I30: =IF(AND(D30="신계약비",OR(C30="GMM",C30="VFA"),NOT((IFERROR(INDEX(계정대체기준!$I$54:$I$63,MATCH($A30,계정대체기준!$A$54:$A$63,0)),"N")="Y"))),G30*IF(계정대체기준!$C$67="전액 CSM",1,IF(계정대체기준!$C$67="전액 당기손익",0,IFERROR(INDEX(계정대체기준!$H$54:$H$63,MATCH($A30,계정대체기준!$A$54:$A$63,0)),0))),0) | J30: =IF(AND(D30="신계약비",C30="PAA",계정대체기준!$C$68="이연 후 상각"),0,G30-I30) | L30: =IF(변동분석!$A30="","",변동분석!$E30) | M30: =IF(L30="",0,SUMIFS(전표_원본!$Z$5:$Z$100000,전표_원본!$O$5:$O$100000,L30,전표_원본!$M$5:$M$100000,설정!$C$20)) | N30: =IF(L30="",0,SUMIFS(전표_원본!$Z$5:$Z$100000,전표_원본!$O$5:$O$100000,L30,전표_원본!$M$5:$M$100000,설정!$C$20-1)) | O30: =M30-N30 | P30: =IF(L30="","",O30+ROW()/1000000)
A31: PF04 | B31: =IFERROR(INDEX(계정대체기준!$B$54:$B$63,MATCH($A31,계정대체기준!$A$54:$A$63,0)),"") | C31: =IFERROR(INDEX(계정대체기준!$C$54:$C$63,MATCH($A31,계정대체기준!$A$54:$A$63,0)),"") | D31: 수금비 | E31: =$B$13*IFERROR(INDEX(계정대체기준!$F$54:$F$63,MATCH($A31,계정대체기준!$A$54:$A$63,0)),0) | F31: =SUMIFS(예정사업비!$L$5:$L$20000,예정사업비!$I$5:$I$20000,설정!$C$20,예정사업비!$C$5:$C$20000,$A31) | G31: =F31-E31 | H31: =IF(D31<>"신계약비","당기손익(보험서비스결과)",IF(C31="PAA",IF(계정대체기준!$C$68="이연 후 상각","잔여보장부채 이연(상각)","당기손익"),IF((IFERROR(INDEX(계정대체기준!$I$54:$I$63,MATCH($A31,계정대체기준!$A$54:$A$63,0)),"N")="Y"),"당기손익(손실요소)",IF(IF(계정대체기준!$C$67="전액 CSM",1,IF(계정대체기준!$C$67="전액 당기손익",0,IFERROR(INDEX(계정대체기준!$H$54:$H$63,MATCH($A31,계정대체기준!$A$54:$A$63,0)),0)))>=1,"CSM 조정 ("&C31&")",IF(IF(계정대체기준!$C$67="전액 CSM",1,IF(계정대체기준!$C$67="전액 당기손익",0,IFERROR(INDEX(계정대체기준!$H$54:$H$63,MATCH($A31,계정대체기준!$A$54:$A$63,0)),0)))<=0,"당기손익","CSM "&TEXT(IF(계정대체기준!$C$67="전액 CSM",1,IF(계정대체기준!$C$67="전액 당기손익",0,IFERROR(INDEX(계정대체기준!$H$54:$H$63,MATCH($A31,계정대체기준!$A$54:$A$63,0)),0))),"0%")&" ("&C31&") · 나머지 손익"))))) | I31: =IF(AND(D31="신계약비",OR(C31="GMM",C31="VFA"),NOT((IFERROR(INDEX(계정대체기준!$I$54:$I$63,MATCH($A31,계정대체기준!$A$54:$A$63,0)),"N")="Y"))),G31*IF(계정대체기준!$C$67="전액 CSM",1,IF(계정대체기준!$C$67="전액 당기손익",0,IFERROR(INDEX(계정대체기준!$H$54:$H$63,MATCH($A31,계정대체기준!$A$54:$A$63,0)),0))),0) | J31: =IF(AND(D31="신계약비",C31="PAA",계정대체기준!$C$68="이연 후 상각"),0,G31-I31) | L31: =IF(변동분석!$A31="","",변동분석!$E31) | M31: =IF(L31="",0,SUMIFS(전표_원본!$Z$5:$Z$100000,전표_원본!$O$5:$O$100000,L31,전표_원본!$M$5:$M$100000,설정!$C$20)) | N31: =IF(L31="",0,SUMIFS(전표_원본!$Z$5:$Z$100000,전표_원본!$O$5:$O$100000,L31,전표_원본!$M$5:$M$100000,설정!$C$20-1)) | O31: =M31-N31 | P31: =IF(L31="","",O31+ROW()/1000000)
A32: CSM 조정 (GMM 취득현금흐름 예실차) | G32: =SUMIFS($I$20:$I$31,$C$20:$C$31,"GMM") | L32: =IF(변동분석!$A32="","",변동분석!$E32) | M32: =IF(L32="",0,SUMIFS(전표_원본!$Z$5:$Z$100000,전표_원본!$O$5:$O$100000,L32,전표_원본!$M$5:$M$100000,설정!$C$20)) | N32: =IF(L32="",0,SUMIFS(전표_원본!$Z$5:$Z$100000,전표_원본!$O$5:$O$100000,L32,전표_원본!$M$5:$M$100000,설정!$C$20-1)) | O32: =M32-N32 | P32: =IF(L32="","",O32+ROW()/1000000)
A33: CSM 조정 (VFA 취득현금흐름 예실차) | G33: =SUMIFS($I$20:$I$31,$C$20:$C$31,"VFA") | L33: =IF(변동분석!$A33="","",변동분석!$E33) | M33: =IF(L33="",0,SUMIFS(전표_원본!$Z$5:$Z$100000,전표_원본!$O$5:$O$100000,L33,전표_원본!$M$5:$M$100000,설정!$C$20)) | N33: =IF(L33="",0,SUMIFS(전표_원본!$Z$5:$Z$100000,전표_원본!$O$5:$O$100000,L33,전표_원본!$M$5:$M$100000,설정!$C$20-1)) | O33: =M33-N33 | P33: =IF(L33="","",O33+ROW()/1000000)
A34: 당기손익 (유지·수금, 연동 외 신계약비, PAA) | G34: =SUM($J$20:$J$31) | L34: =IF(변동분석!$A34="","",변동분석!$E34) | M34: =IF(L34="",0,SUMIFS(전표_원본!$Z$5:$Z$100000,전표_원본!$O$5:$O$100000,L34,전표_원본!$M$5:$M$100000,설정!$C$20)) | N34: =IF(L34="",0,SUMIFS(전표_원본!$Z$5:$Z$100000,전표_원본!$O$5:$O$100000,L34,전표_원본!$M$5:$M$100000,설정!$C$20-1)) | O34: =M34-N34 | P34: =IF(L34="","",O34+ROW()/1000000)
L35: =IF(변동분석!$A35="","",변동분석!$E35) | M35: =IF(L35="",0,SUMIFS(전표_원본!$Z$5:$Z$100000,전표_원본!$O$5:$O$100000,L35,전표_원본!$M$5:$M$100000,설정!$C$20)) | N35: =IF(L35="",0,SUMIFS(전표_원본!$Z$5:$Z$100000,전표_원본!$O$5:$O$100000,L35,전표_원본!$M$5:$M$100000,설정!$C$20-1)) | O35: =M35-N35 | P35: =IF(L35="","",O35+ROW()/1000000)
L36: =IF(변동분석!$A36="","",변동분석!$E36) | M36: =IF(L36="",0,SUMIFS(전표_원본!$Z$5:$Z$100000,전표_원본!$O$5:$O$100000,L36,전표_원본!$M$5:$M$100000,설정!$C$20)) | N36: =IF(L36="",0,SUMIFS(전표_원본!$Z$5:$Z$100000,전표_원본!$O$5:$O$100000,L36,전표_원본!$M$5:$M$100000,설정!$C$20-1)) | O36: =M36-N36 | P36: =IF(L36="","",O36+ROW()/1000000)
A37: 3. 변동표 대사 (계리 결과 '경험조정-취득현금흐름' CSM vs TRACE CSM 반영분) | L37: =IF(변동분석!$A37="","",변동분석!$E37) | M37: =IF(L37="",0,SUMIFS(전표_원본!$Z$5:$Z$100000,전표_원본!$O$5:$O$100000,L37,전표_원본!$M$5:$M$100000,설정!$C$20)) | N37: =IF(L37="",0,SUMIFS(전표_원본!$Z$5:$Z$100000,전표_원본!$O$5:$O$100000,L37,전표_원본!$M$5:$M$100000,설정!$C$20-1)) | O37: =M37-N37 | P37: =IF(L37="","",O37+ROW()/1000000)
A38: 포트폴리오 | B38: 측정모형 | C38: 계리 F31 (CSM) | D38: TRACE 추정 (CSM 반영분) | E38: 차이 | F38: 판정 | L38: =IF(변동분석!$A38="","",변동분석!$E38) | M38: =IF(L38="",0,SUMIFS(전표_원본!$Z$5:$Z$100000,전표_원본!$O$5:$O$100000,L38,전표_원본!$M$5:$M$100000,설정!$C$20)) | N38: =IF(L38="",0,SUMIFS(전표_원본!$Z$5:$Z$100000,전표_원본!$O$5:$O$100000,L38,전표_원본!$M$5:$M$100000,설정!$C$20-1)) | O38: =M38-N38 | P38: =IF(L38="","",O38+ROW()/1000000)
A39: PF01 | B39: =IFERROR(INDEX(계정대체기준!$C$54:$C$63,MATCH($A39,계정대체기준!$A$54:$A$63,0)),"") | C39: =SUMIFS(부채변동표!$O$5:$O$20000,부채변동표!$L$5:$L$20000,설정!$C$20,부채변동표!$C$5:$C$20000,$A39,부채변동표!$P$5:$P$20000,"F31") | D39: =IF(B39="PAA",0,SUMIFS($I$20:$I$31,$A$20:$A$31,$A39,$D$20:$D$31,"신계약비")) | E39: =C39-D39 | F39: =IF(B39="PAA","해당없음 (CSM 없음)",IF(ABS(E39)<0.5,"일치","차이 확인")) | L39: =IF(변동분석!$A39="","",변동분석!$E39) | M39: =IF(L39="",0,SUMIFS(전표_원본!$Z$5:$Z$100000,전표_원본!$O$5:$O$100000,L39,전표_원본!$M$5:$M$100000,설정!$C$20)) | N39: =IF(L39="",0,SUMIFS(전표_원본!$Z$5:$Z$100000,전표_원본!$O$5:$O$100000,L39,전표_원본!$M$5:$M$100000,설정!$C$20-1)) | O39: =M39-N39 | P39: =IF(L39="","",O39+ROW()/1000000)
A40: PF02 | B40: =IFERROR(INDEX(계정대체기준!$C$54:$C$63,MATCH($A40,계정대체기준!$A$54:$A$63,0)),"") | C40: =SUMIFS(부채변동표!$O$5:$O$20000,부채변동표!$L$5:$L$20000,설정!$C$20,부채변동표!$C$5:$C$20000,$A40,부채변동표!$P$5:$P$20000,"F31") | D40: =IF(B40="PAA",0,SUMIFS($I$20:$I$31,$A$20:$A$31,$A40,$D$20:$D$31,"신계약비")) | E40: =C40-D40 | F40: =IF(B40="PAA","해당없음 (CSM 없음)",IF(ABS(E40)<0.5,"일치","차이 확인")) | L40: =IF(변동분석!$A40="","",변동분석!$E40) | M40: =IF(L40="",0,SUMIFS(전표_원본!$Z$5:$Z$100000,전표_원본!$O$5:$O$100000,L40,전표_원본!$M$5:$M$100000,설정!$C$20)) | N40: =IF(L40="",0,SUMIFS(전표_원본!$Z$5:$Z$100000,전표_원본!$O$5:$O$100000,L40,전표_원본!$M$5:$M$100000,설정!$C$20-1)) | O40: =M40-N40 | P40: =IF(L40="","",O40+ROW()/1000000)
A41: PF03 | B41: =IFERROR(INDEX(계정대체기준!$C$54:$C$63,MATCH($A41,계정대체기준!$A$54:$A$63,0)),"") | C41: =SUMIFS(부채변동표!$O$5:$O$20000,부채변동표!$L$5:$L$20000,설정!$C$20,부채변동표!$C$5:$C$20000,$A41,부채변동표!$P$5:$P$20000,"F31") | D41: =IF(B41="PAA",0,SUMIFS($I$20:$I$31,$A$20:$A$31,$A41,$D$20:$D$31,"신계약비")) | E41: =C41-D41 | F41: =IF(B41="PAA","해당없음 (CSM 없음)",IF(ABS(E41)<0.5,"일치","차이 확인")) | L41: =IF(변동분석!$A41="","",변동분석!$E41) | M41: =IF(L41="",0,SUMIFS(전표_원본!$Z$5:$Z$100000,전표_원본!$O$5:$O$100000,L41,전표_원본!$M$5:$M$100000,설정!$C$20)) | N41: =IF(L41="",0,SUMIFS(전표_원본!$Z$5:$Z$100000,전표_원본!$O$5:$O$100000,L41,전표_원본!$M$5:$M$100000,설정!$C$20-1)) | O41: =M41-N41 | P41: =IF(L41="","",O41+ROW()/1000000)
A42: PF04 | B42: =IFERROR(INDEX(계정대체기준!$C$54:$C$63,MATCH($A42,계정대체기준!$A$54:$A$63,0)),"") | C42: =SUMIFS(부채변동표!$O$5:$O$20000,부채변동표!$L$5:$L$20000,설정!$C$20,부채변동표!$C$5:$C$20000,$A42,부채변동표!$P$5:$P$20000,"F31") | D42: =IF(B42="PAA",0,SUMIFS($I$20:$I$31,$A$20:$A$31,$A42,$D$20:$D$31,"신계약비")) | E42: =C42-D42 | F42: =IF(B42="PAA","해당없음 (CSM 없음)",IF(ABS(E42)<0.5,"일치","차이 확인")) | L42: =IF(변동분석!$A42="","",변동분석!$E42) | M42: =IF(L42="",0,SUMIFS(전표_원본!$Z$5:$Z$100000,전표_원본!$O$5:$O$100000,L42,전표_원본!$M$5:$M$100000,설정!$C$20)) | N42: =IF(L42="",0,SUMIFS(전표_원본!$Z$5:$Z$100000,전표_원본!$O$5:$O$100000,L42,전표_원본!$M$5:$M$100000,설정!$C$20-1)) | O42: =M42-N42 | P42: =IF(L42="","",O42+ROW()/1000000)
L43: =IF(변동분석!$A43="","",변동분석!$E43) | M43: =IF(L43="",0,SUMIFS(전표_원본!$Z$5:$Z$100000,전표_원본!$O$5:$O$100000,L43,전표_원본!$M$5:$M$100000,설정!$C$20)) | N43: =IF(L43="",0,SUMIFS(전표_원본!$Z$5:$Z$100000,전표_원본!$O$5:$O$100000,L43,전표_원본!$M$5:$M$100000,설정!$C$20-1)) | O43: =M43-N43 | P43: =IF(L43="","",O43+ROW()/1000000)
A44: 4. GMM 변동 브리지 (보장성 + 저축성, 당월) | L44: =IF(변동분석!$A44="","",변동분석!$E44) | M44: =IF(L44="",0,SUMIFS(전표_원본!$Z$5:$Z$100000,전표_원본!$O$5:$O$100000,L44,전표_원본!$M$5:$M$100000,설정!$C$20)) | N44: =IF(L44="",0,SUMIFS(전표_원본!$Z$5:$Z$100000,전표_원본!$O$5:$O$100000,L44,전표_원본!$M$5:$M$100000,설정!$C$20-1)) | O44: =M44-N44 | P44: =IF(L44="","",O44+ROW()/1000000)
A45: 요인코드 | B45: 변동요인 | C45: BEL | D45: RA | E45: CSM | F45: 사업비 관련 | L45: =IF(변동분석!$A45="","",변동분석!$E45) | M45: =IF(L45="",0,SUMIFS(전표_원본!$Z$5:$Z$100000,전표_원본!$O$5:$O$100000,L45,전표_원본!$M$5:$M$100000,설정!$C$20)) | N45: =IF(L45="",0,SUMIFS(전표_원본!$Z$5:$Z$100000,전표_원본!$O$5:$O$100000,L45,전표_원본!$M$5:$M$100000,설정!$C$20-1)) | O45: =M45-N45 | P45: =IF(L45="","",O45+ROW()/1000000)
A46: F00 | B46: 기초잔액 | C46: =SUMIFS(부채변동표!$M$5:$M$20000,부채변동표!$L$5:$L$20000,설정!$C$20,부채변동표!$P$5:$P$20000,$A46,부채변동표!$E$5:$E$20000,"GMM") | D46: =SUMIFS(부채변동표!$N$5:$N$20000,부채변동표!$L$5:$L$20000,설정!$C$20,부채변동표!$P$5:$P$20000,$A46,부채변동표!$E$5:$E$20000,"GMM") | E46: =SUMIFS(부채변동표!$O$5:$O$20000,부채변동표!$L$5:$L$20000,설정!$C$20,부채변동표!$P$5:$P$20000,$A46,부채변동표!$E$5:$E$20000,"GMM") | L46: =IF(변동분석!$A46="","",변동분석!$E46) | M46: =IF(L46="",0,SUMIFS(전표_원본!$Z$5:$Z$100000,전표_원본!$O$5:$O$100000,L46,전표_원본!$M$5:$M$100000,설정!$C$20)) | N46: =IF(L46="",0,SUMIFS(전표_원본!$Z$5:$Z$100000,전표_원본!$O$5:$O$100000,L46,전표_원본!$M$5:$M$100000,설정!$C$20-1)) | O46: =M46-N46 | P46: =IF(L46="","",O46+ROW()/1000000)
A47: F10 | B47: 신계약 효과 | C47: =SUMIFS(부채변동표!$M$5:$M$20000,부채변동표!$L$5:$L$20000,설정!$C$20,부채변동표!$P$5:$P$20000,$A47,부채변동표!$E$5:$E$20000,"GMM") | D47: =SUMIFS(부채변동표!$N$5:$N$20000,부채변동표!$L$5:$L$20000,설정!$C$20,부채변동표!$P$5:$P$20000,$A47,부채변동표!$E$5:$E$20000,"GMM") | E47: =SUMIFS(부채변동표!$O$5:$O$20000,부채변동표!$L$5:$L$20000,설정!$C$20,부채변동표!$P$5:$P$20000,$A47,부채변동표!$E$5:$E$20000,"GMM") | L47: =IF(변동분석!$A47="","",변동분석!$E47) | M47: =IF(L47="",0,SUMIFS(전표_원본!$Z$5:$Z$100000,전표_원본!$O$5:$O$100000,L47,전표_원본!$M$5:$M$100000,설정!$C$20)) | N47: =IF(L47="",0,SUMIFS(전표_원본!$Z$5:$Z$100000,전표_원본!$O$5:$O$100000,L47,전표_원본!$M$5:$M$100000,설정!$C$20-1)) | O47: =M47-N47 | P47: =IF(L47="","",O47+ROW()/1000000)
A48: F21 | B48: 가정변경-사업비 | C48: =SUMIFS(부채변동표!$M$5:$M$20000,부채변동표!$L$5:$L$20000,설정!$C$20,부채변동표!$P$5:$P$20000,$A48,부채변동표!$E$5:$E$20000,"GMM") | D48: =SUMIFS(부채변동표!$N$5:$N$20000,부채변동표!$L$5:$L$20000,설정!$C$20,부채변동표!$P$5:$P$20000,$A48,부채변동표!$E$5:$E$20000,"GMM") | E48: =SUMIFS(부채변동표!$O$5:$O$20000,부채변동표!$L$5:$L$20000,설정!$C$20,부채변동표!$P$5:$P$20000,$A48,부채변동표!$E$5:$E$20000,"GMM") | F48: 사업비 | L48: =IF(변동분석!$A48="","",변동분석!$E48) | M48: =IF(L48="",0,SUMIFS(전표_원본!$Z$5:$Z$100000,전표_원본!$O$5:$O$100000,L48,전표_원본!$M$5:$M$100000,설정!$C$20)) | N48: =IF(L48="",0,SUMIFS(전표_원본!$Z$5:$Z$100000,전표_원본!$O$5:$O$100000,L48,전표_원본!$M$5:$M$100000,설정!$C$20-1)) | O48: =M48-N48 | P48: =IF(L48="","",O48+ROW()/1000000)
A49: F22 | B49: 가정변경-기타 | C49: =SUMIFS(부채변동표!$M$5:$M$20000,부채변동표!$L$5:$L$20000,설정!$C$20,부채변동표!$P$5:$P$20000,$A49,부채변동표!$E$5:$E$20000,"GMM") | D49: =SUMIFS(부채변동표!$N$5:$N$20000,부채변동표!$L$5:$L$20000,설정!$C$20,부채변동표!$P$5:$P$20000,$A49,부채변동표!$E$5:$E$20000,"GMM") | E49: =SUMIFS(부채변동표!$O$5:$O$20000,부채변동표!$L$5:$L$20000,설정!$C$20,부채변동표!$P$5:$P$20000,$A49,부채변동표!$E$5:$E$20000,"GMM") | L49: =IF(변동분석!$A49="","",변동분석!$E49) | M49: =IF(L49="",0,SUMIFS(전표_원본!$Z$5:$Z$100000,전표_원본!$O$5:$O$100000,L49,전표_원본!$M$5:$M$100000,설정!$C$20)) | N49: =IF(L49="",0,SUMIFS(전표_원본!$Z$5:$Z$100000,전표_원본!$O$5:$O$100000,L49,전표_원본!$M$5:$M$100000,설정!$C$20-1)) | O49: =M49-N49 | P49: =IF(L49="","",O49+ROW()/1000000)
A50: F31 | B50: 경험조정-취득현금흐름 | C50: =SUMIFS(부채변동표!$M$5:$M$20000,부채변동표!$L$5:$L$20000,설정!$C$20,부채변동표!$P$5:$P$20000,$A50,부채변동표!$E$5:$E$20000,"GMM") | D50: =SUMIFS(부채변동표!$N$5:$N$20000,부채변동표!$L$5:$L$20000,설정!$C$20,부채변동표!$P$5:$P$20000,$A50,부채변동표!$E$5:$E$20000,"GMM") | E50: =SUMIFS(부채변동표!$O$5:$O$20000,부채변동표!$L$5:$L$20000,설정!$C$20,부채변동표!$P$5:$P$20000,$A50,부채변동표!$E$5:$E$20000,"GMM") | F50: 사업비 | L50: =IF(변동분석!$A50="","",변동분석!$E50) | M50: =IF(L50="",0,SUMIFS(전표_원본!$Z$5:$Z$100000,전표_원본!$O$5:$O$100000,L50,전표_원본!$M$5:$M$100000,설정!$C$20)) | N50: =IF(L50="",0,SUMIFS(전표_원본!$Z$5:$Z$100000,전표_원본!$O$5:$O$100000,L50,전표_원본!$M$5:$M$100000,설정!$C$20-1)) | O50: =M50-N50 | P50: =IF(L50="","",O50+ROW()/1000000)
A51: F32 | B51: 경험조정-보험료 등 | C51: =SUMIFS(부채변동표!$M$5:$M$20000,부채변동표!$L$5:$L$20000,설정!$C$20,부채변동표!$P$5:$P$20000,$A51,부채변동표!$E$5:$E$20000,"GMM") | D51: =SUMIFS(부채변동표!$N$5:$N$20000,부채변동표!$L$5:$L$20000,설정!$C$20,부채변동표!$P$5:$P$20000,$A51,부채변동표!$E$5:$E$20000,"GMM") | E51: =SUMIFS(부채변동표!$O$5:$O$20000,부채변동표!$L$5:$L$20000,설정!$C$20,부채변동표!$P$5:$P$20000,$A51,부채변동표!$E$5:$E$20000,"GMM") | L51: =IF(변동분석!$A51="","",변동분석!$E51) | M51: =IF(L51="",0,SUMIFS(전표_원본!$Z$5:$Z$100000,전표_원본!$O$5:$O$100000,L51,전표_원본!$M$5:$M$100000,설정!$C$20)) | N51: =IF(L51="",0,SUMIFS(전표_원본!$Z$5:$Z$100000,전표_원본!$O$5:$O$100000,L51,전표_원본!$M$5:$M$100000,설정!$C$20-1)) | O51: =M51-N51 | P51: =IF(L51="","",O51+ROW()/1000000)
A52: F40 | B52: 보험금융비용(이자부리) | C52: =SUMIFS(부채변동표!$M$5:$M$20000,부채변동표!$L$5:$L$20000,설정!$C$20,부채변동표!$P$5:$P$20000,$A52,부채변동표!$E$5:$E$20000,"GMM") | D52: =SUMIFS(부채변동표!$N$5:$N$20000,부채변동표!$L$5:$L$20000,설정!$C$20,부채변동표!$P$5:$P$20000,$A52,부채변동표!$E$5:$E$20000,"GMM") | E52: =SUMIFS(부채변동표!$O$5:$O$20000,부채변동표!$L$5:$L$20000,설정!$C$20,부채변동표!$P$5:$P$20000,$A52,부채변동표!$E$5:$E$20000,"GMM") | L52: =IF(변동분석!$A52="","",변동분석!$E52) | M52: =IF(L52="",0,SUMIFS(전표_원본!$Z$5:$Z$100000,전표_원본!$O$5:$O$100000,L52,전표_원본!$M$5:$M$100000,설정!$C$20)) | N52: =IF(L52="",0,SUMIFS(전표_원본!$Z$5:$Z$100000,전표_원본!$O$5:$O$100000,L52,전표_원본!$M$5:$M$100000,설정!$C$20-1)) | O52: =M52-N52 | P52: =IF(L52="","",O52+ROW()/1000000)
A53: F51 | B53: CSM 상각 | C53: =SUMIFS(부채변동표!$M$5:$M$20000,부채변동표!$L$5:$L$20000,설정!$C$20,부채변동표!$P$5:$P$20000,$A53,부채변동표!$E$5:$E$20000,"GMM") | D53: =SUMIFS(부채변동표!$N$5:$N$20000,부채변동표!$L$5:$L$20000,설정!$C$20,부채변동표!$P$5:$P$20000,$A53,부채변동표!$E$5:$E$20000,"GMM") | E53: =SUMIFS(부채변동표!$O$5:$O$20000,부채변동표!$L$5:$L$20000,설정!$C$20,부채변동표!$P$5:$P$20000,$A53,부채변동표!$E$5:$E$20000,"GMM") | L53: =IF(변동분석!$A53="","",변동분석!$E53) | M53: =IF(L53="",0,SUMIFS(전표_원본!$Z$5:$Z$100000,전표_원본!$O$5:$O$100000,L53,전표_원본!$M$5:$M$100000,설정!$C$20)) | N53: =IF(L53="",0,SUMIFS(전표_원본!$Z$5:$Z$100000,전표_원본!$O$5:$O$100000,L53,전표_원본!$M$5:$M$100000,설정!$C$20-1)) | O53: =M53-N53 | P53: =IF(L53="","",O53+ROW()/1000000)
A54: F52 | B54: RA 해제 | C54: =SUMIFS(부채변동표!$M$5:$M$20000,부채변동표!$L$5:$L$20000,설정!$C$20,부채변동표!$P$5:$P$20000,$A54,부채변동표!$E$5:$E$20000,"GMM") | D54: =SUMIFS(부채변동표!$N$5:$N$20000,부채변동표!$L$5:$L$20000,설정!$C$20,부채변동표!$P$5:$P$20000,$A54,부채변동표!$E$5:$E$20000,"GMM") | E54: =SUMIFS(부채변동표!$O$5:$O$20000,부채변동표!$L$5:$L$20000,설정!$C$20,부채변동표!$P$5:$P$20000,$A54,부채변동표!$E$5:$E$20000,"GMM") | L54: =IF(변동분석!$A54="","",변동분석!$E54) | M54: =IF(L54="",0,SUMIFS(전표_원본!$Z$5:$Z$100000,전표_원본!$O$5:$O$100000,L54,전표_원본!$M$5:$M$100000,설정!$C$20)) | N54: =IF(L54="",0,SUMIFS(전표_원본!$Z$5:$Z$100000,전표_원본!$O$5:$O$100000,L54,전표_원본!$M$5:$M$100000,설정!$C$20-1)) | O54: =M54-N54 | P54: =IF(L54="","",O54+ROW()/1000000)
A55: F60 | B55: 현금흐름 및 기타 | C55: =SUMIFS(부채변동표!$M$5:$M$20000,부채변동표!$L$5:$L$20000,설정!$C$20,부채변동표!$P$5:$P$20000,$A55,부채변동표!$E$5:$E$20000,"GMM") | D55: =SUMIFS(부채변동표!$N$5:$N$20000,부채변동표!$L$5:$L$20000,설정!$C$20,부채변동표!$P$5:$P$20000,$A55,부채변동표!$E$5:$E$20000,"GMM") | E55: =SUMIFS(부채변동표!$O$5:$O$20000,부채변동표!$L$5:$L$20000,설정!$C$20,부채변동표!$P$5:$P$20000,$A55,부채변동표!$E$5:$E$20000,"GMM") | L55: =IF(변동분석!$A55="","",변동분석!$E55) | M55: =IF(L55="",0,SUMIFS(전표_원본!$Z$5:$Z$100000,전표_원본!$O$5:$O$100000,L55,전표_원본!$M$5:$M$100000,설정!$C$20)) | N55: =IF(L55="",0,SUMIFS(전표_원본!$Z$5:$Z$100000,전표_원본!$O$5:$O$100000,L55,전표_원본!$M$5:$M$100000,설정!$C$20-1)) | O55: =M55-N55 | P55: =IF(L55="","",O55+ROW()/1000000)
A56: F99 | B56: 기말잔액 | C56: =SUMIFS(부채변동표!$M$5:$M$20000,부채변동표!$L$5:$L$20000,설정!$C$20,부채변동표!$P$5:$P$20000,$A56,부채변동표!$E$5:$E$20000,"GMM") | D56: =SUMIFS(부채변동표!$N$5:$N$20000,부채변동표!$L$5:$L$20000,설정!$C$20,부채변동표!$P$5:$P$20000,$A56,부채변동표!$E$5:$E$20000,"GMM") | E56: =SUMIFS(부채변동표!$O$5:$O$20000,부채변동표!$L$5:$L$20000,설정!$C$20,부채변동표!$P$5:$P$20000,$A56,부채변동표!$E$5:$E$20000,"GMM") | L56: =IF(변동분석!$A56="","",변동분석!$E56) | M56: =IF(L56="",0,SUMIFS(전표_원본!$Z$5:$Z$100000,전표_원본!$O$5:$O$100000,L56,전표_원본!$M$5:$M$100000,설정!$C$20)) | N56: =IF(L56="",0,SUMIFS(전표_원본!$Z$5:$Z$100000,전표_원본!$O$5:$O$100000,L56,전표_원본!$M$5:$M$100000,설정!$C$20-1)) | O56: =M56-N56 | P56: =IF(L56="","",O56+ROW()/1000000)
B57: CSM 당월 변동 (기말 − 기초) | E57: =E56-E46 | L57: =IF(변동분석!$A57="","",변동분석!$E57) | M57: =IF(L57="",0,SUMIFS(전표_원본!$Z$5:$Z$100000,전표_원본!$O$5:$O$100000,L57,전표_원본!$M$5:$M$100000,설정!$C$20)) | N57: =IF(L57="",0,SUMIFS(전표_원본!$Z$5:$Z$100000,전표_원본!$O$5:$O$100000,L57,전표_원본!$M$5:$M$100000,설정!$C$20-1)) | O57: =M57-N57 | P57: =IF(L57="","",O57+ROW()/1000000)
B58: 그중 사업비 관련 (F21 + F31) | E58: =E48+E50 | L58: =IF(변동분석!$A58="","",변동분석!$E58) | M58: =IF(L58="",0,SUMIFS(전표_원본!$Z$5:$Z$100000,전표_원본!$O$5:$O$100000,L58,전표_원본!$M$5:$M$100000,설정!$C$20)) | N58: =IF(L58="",0,SUMIFS(전표_원본!$Z$5:$Z$100000,전표_원본!$O$5:$O$100000,L58,전표_원본!$M$5:$M$100000,설정!$C$20-1)) | O58: =M58-N58 | P58: =IF(L58="","",O58+ROW()/1000000)
L59: =IF(변동분석!$A59="","",변동분석!$E59) | M59: =IF(L59="",0,SUMIFS(전표_원본!$Z$5:$Z$100000,전표_원본!$O$5:$O$100000,L59,전표_원본!$M$5:$M$100000,설정!$C$20)) | N59: =IF(L59="",0,SUMIFS(전표_원본!$Z$5:$Z$100000,전표_원본!$O$5:$O$100000,L59,전표_원본!$M$5:$M$100000,설정!$C$20-1)) | O59: =M59-N59 | P59: =IF(L59="","",O59+ROW()/1000000)
L60: =IF(변동분석!$A60="","",변동분석!$E60) | M60: =IF(L60="",0,SUMIFS(전표_원본!$Z$5:$Z$100000,전표_원본!$O$5:$O$100000,L60,전표_원본!$M$5:$M$100000,설정!$C$20)) | N60: =IF(L60="",0,SUMIFS(전표_원본!$Z$5:$Z$100000,전표_원본!$O$5:$O$100000,L60,전표_원본!$M$5:$M$100000,설정!$C$20-1)) | O60: =M60-N60 | P60: =IF(L60="","",O60+ROW()/1000000)
A61: 4-2. VFA 변동 브리지 (변액, 당월) | L61: =IF(변동분석!$A61="","",변동분석!$E61) | M61: =IF(L61="",0,SUMIFS(전표_원본!$Z$5:$Z$100000,전표_원본!$O$5:$O$100000,L61,전표_원본!$M$5:$M$100000,설정!$C$20)) | N61: =IF(L61="",0,SUMIFS(전표_원본!$Z$5:$Z$100000,전표_원본!$O$5:$O$100000,L61,전표_원본!$M$5:$M$100000,설정!$C$20-1)) | O61: =M61-N61 | P61: =IF(L61="","",O61+ROW()/1000000)
A62: 요인코드 | B62: 변동요인 | C62: BEL | D62: RA | E62: CSM | F62: 사업비 관련 | L62: =IF(변동분석!$A62="","",변동분석!$E62) | M62: =IF(L62="",0,SUMIFS(전표_원본!$Z$5:$Z$100000,전표_원본!$O$5:$O$100000,L62,전표_원본!$M$5:$M$100000,설정!$C$20)) | N62: =IF(L62="",0,SUMIFS(전표_원본!$Z$5:$Z$100000,전표_원본!$O$5:$O$100000,L62,전표_원본!$M$5:$M$100000,설정!$C$20-1)) | O62: =M62-N62 | P62: =IF(L62="","",O62+ROW()/1000000)
A63: F00 | B63: 기초잔액 | C63: =SUMIFS(부채변동표!$M$5:$M$20000,부채변동표!$L$5:$L$20000,설정!$C$20,부채변동표!$P$5:$P$20000,$A63,부채변동표!$E$5:$E$20000,"VFA") | D63: =SUMIFS(부채변동표!$N$5:$N$20000,부채변동표!$L$5:$L$20000,설정!$C$20,부채변동표!$P$5:$P$20000,$A63,부채변동표!$E$5:$E$20000,"VFA") | E63: =SUMIFS(부채변동표!$O$5:$O$20000,부채변동표!$L$5:$L$20000,설정!$C$20,부채변동표!$P$5:$P$20000,$A63,부채변동표!$E$5:$E$20000,"VFA") | L63: =IF(변동분석!$A63="","",변동분석!$E63) | M63: =IF(L63="",0,SUMIFS(전표_원본!$Z$5:$Z$100000,전표_원본!$O$5:$O$100000,L63,전표_원본!$M$5:$M$100000,설정!$C$20)) | N63: =IF(L63="",0,SUMIFS(전표_원본!$Z$5:$Z$100000,전표_원본!$O$5:$O$100000,L63,전표_원본!$M$5:$M$100000,설정!$C$20-1)) | O63: =M63-N63 | P63: =IF(L63="","",O63+ROW()/1000000)
A64: F10 | B64: 신계약 효과 | C64: =SUMIFS(부채변동표!$M$5:$M$20000,부채변동표!$L$5:$L$20000,설정!$C$20,부채변동표!$P$5:$P$20000,$A64,부채변동표!$E$5:$E$20000,"VFA") | D64: =SUMIFS(부채변동표!$N$5:$N$20000,부채변동표!$L$5:$L$20000,설정!$C$20,부채변동표!$P$5:$P$20000,$A64,부채변동표!$E$5:$E$20000,"VFA") | E64: =SUMIFS(부채변동표!$O$5:$O$20000,부채변동표!$L$5:$L$20000,설정!$C$20,부채변동표!$P$5:$P$20000,$A64,부채변동표!$E$5:$E$20000,"VFA") | L64: =IF(변동분석!$A64="","",변동분석!$E64) | M64: =IF(L64="",0,SUMIFS(전표_원본!$Z$5:$Z$100000,전표_원본!$O$5:$O$100000,L64,전표_원본!$M$5:$M$100000,설정!$C$20)) | N64: =IF(L64="",0,SUMIFS(전표_원본!$Z$5:$Z$100000,전표_원본!$O$5:$O$100000,L64,전표_원본!$M$5:$M$100000,설정!$C$20-1)) | O64: =M64-N64 | P64: =IF(L64="","",O64+ROW()/1000000)
A65: F21 | B65: 가정변경-사업비 | C65: =SUMIFS(부채변동표!$M$5:$M$20000,부채변동표!$L$5:$L$20000,설정!$C$20,부채변동표!$P$5:$P$20000,$A65,부채변동표!$E$5:$E$20000,"VFA") | D65: =SUMIFS(부채변동표!$N$5:$N$20000,부채변동표!$L$5:$L$20000,설정!$C$20,부채변동표!$P$5:$P$20000,$A65,부채변동표!$E$5:$E$20000,"VFA") | E65: =SUMIFS(부채변동표!$O$5:$O$20000,부채변동표!$L$5:$L$20000,설정!$C$20,부채변동표!$P$5:$P$20000,$A65,부채변동표!$E$5:$E$20000,"VFA") | F65: 사업비 | L65: =IF(변동분석!$A65="","",변동분석!$E65) | M65: =IF(L65="",0,SUMIFS(전표_원본!$Z$5:$Z$100000,전표_원본!$O$5:$O$100000,L65,전표_원본!$M$5:$M$100000,설정!$C$20)) | N65: =IF(L65="",0,SUMIFS(전표_원본!$Z$5:$Z$100000,전표_원본!$O$5:$O$100000,L65,전표_원본!$M$5:$M$100000,설정!$C$20-1)) | O65: =M65-N65 | P65: =IF(L65="","",O65+ROW()/1000000)
A66: F22 | B66: 가정변경-기타 | C66: =SUMIFS(부채변동표!$M$5:$M$20000,부채변동표!$L$5:$L$20000,설정!$C$20,부채변동표!$P$5:$P$20000,$A66,부채변동표!$E$5:$E$20000,"VFA") | D66: =SUMIFS(부채변동표!$N$5:$N$20000,부채변동표!$L$5:$L$20000,설정!$C$20,부채변동표!$P$5:$P$20000,$A66,부채변동표!$E$5:$E$20000,"VFA") | E66: =SUMIFS(부채변동표!$O$5:$O$20000,부채변동표!$L$5:$L$20000,설정!$C$20,부채변동표!$P$5:$P$20000,$A66,부채변동표!$E$5:$E$20000,"VFA") | L66: =IF(변동분석!$A66="","",변동분석!$E66) | M66: =IF(L66="",0,SUMIFS(전표_원본!$Z$5:$Z$100000,전표_원본!$O$5:$O$100000,L66,전표_원본!$M$5:$M$100000,설정!$C$20)) | N66: =IF(L66="",0,SUMIFS(전표_원본!$Z$5:$Z$100000,전표_원본!$O$5:$O$100000,L66,전표_원본!$M$5:$M$100000,설정!$C$20-1)) | O66: =M66-N66 | P66: =IF(L66="","",O66+ROW()/1000000)
A67: F31 | B67: 경험조정-취득현금흐름 | C67: =SUMIFS(부채변동표!$M$5:$M$20000,부채변동표!$L$5:$L$20000,설정!$C$20,부채변동표!$P$5:$P$20000,$A67,부채변동표!$E$5:$E$20000,"VFA") | D67: =SUMIFS(부채변동표!$N$5:$N$20000,부채변동표!$L$5:$L$20000,설정!$C$20,부채변동표!$P$5:$P$20000,$A67,부채변동표!$E$5:$E$20000,"VFA") | E67: =SUMIFS(부채변동표!$O$5:$O$20000,부채변동표!$L$5:$L$20000,설정!$C$20,부채변동표!$P$5:$P$20000,$A67,부채변동표!$E$5:$E$20000,"VFA") | F67: 사업비 | L67: =IF(변동분석!$A67="","",변동분석!$E67) | M67: =IF(L67="",0,SUMIFS(전표_원본!$Z$5:$Z$100000,전표_원본!$O$5:$O$100000,L67,전표_원본!$M$5:$M$100000,설정!$C$20)) | N67: =IF(L67="",0,SUMIFS(전표_원본!$Z$5:$Z$100000,전표_원본!$O$5:$O$100000,L67,전표_원본!$M$5:$M$100000,설정!$C$20-1)) | O67: =M67-N67 | P67: =IF(L67="","",O67+ROW()/1000000)
A68: F32 | B68: 경험조정-보험료 등 | C68: =SUMIFS(부채변동표!$M$5:$M$20000,부채변동표!$L$5:$L$20000,설정!$C$20,부채변동표!$P$5:$P$20000,$A68,부채변동표!$E$5:$E$20000,"VFA") | D68: =SUMIFS(부채변동표!$N$5:$N$20000,부채변동표!$L$5:$L$20000,설정!$C$20,부채변동표!$P$5:$P$20000,$A68,부채변동표!$E$5:$E$20000,"VFA") | E68: =SUMIFS(부채변동표!$O$5:$O$20000,부채변동표!$L$5:$L$20000,설정!$C$20,부채변동표!$P$5:$P$20000,$A68,부채변동표!$E$5:$E$20000,"VFA") | L68: =IF(변동분석!$A68="","",변동분석!$E68) | M68: =IF(L68="",0,SUMIFS(전표_원본!$Z$5:$Z$100000,전표_원본!$O$5:$O$100000,L68,전표_원본!$M$5:$M$100000,설정!$C$20)) | N68: =IF(L68="",0,SUMIFS(전표_원본!$Z$5:$Z$100000,전표_원본!$O$5:$O$100000,L68,전표_원본!$M$5:$M$100000,설정!$C$20-1)) | O68: =M68-N68 | P68: =IF(L68="","",O68+ROW()/1000000)
A69: F40 | B69: 보험금융비용(이자부리) | C69: =SUMIFS(부채변동표!$M$5:$M$20000,부채변동표!$L$5:$L$20000,설정!$C$20,부채변동표!$P$5:$P$20000,$A69,부채변동표!$E$5:$E$20000,"VFA") | D69: =SUMIFS(부채변동표!$N$5:$N$20000,부채변동표!$L$5:$L$20000,설정!$C$20,부채변동표!$P$5:$P$20000,$A69,부채변동표!$E$5:$E$20000,"VFA") | E69: =SUMIFS(부채변동표!$O$5:$O$20000,부채변동표!$L$5:$L$20000,설정!$C$20,부채변동표!$P$5:$P$20000,$A69,부채변동표!$E$5:$E$20000,"VFA") | L69: =IF(변동분석!$A69="","",변동분석!$E69) | M69: =IF(L69="",0,SUMIFS(전표_원본!$Z$5:$Z$100000,전표_원본!$O$5:$O$100000,L69,전표_원본!$M$5:$M$100000,설정!$C$20)) | N69: =IF(L69="",0,SUMIFS(전표_원본!$Z$5:$Z$100000,전표_원본!$O$5:$O$100000,L69,전표_원본!$M$5:$M$100000,설정!$C$20-1)) | O69: =M69-N69 | P69: =IF(L69="","",O69+ROW()/1000000)
A70: F51 | B70: CSM 상각 | C70: =SUMIFS(부채변동표!$M$5:$M$20000,부채변동표!$L$5:$L$20000,설정!$C$20,부채변동표!$P$5:$P$20000,$A70,부채변동표!$E$5:$E$20000,"VFA") | D70: =SUMIFS(부채변동표!$N$5:$N$20000,부채변동표!$L$5:$L$20000,설정!$C$20,부채변동표!$P$5:$P$20000,$A70,부채변동표!$E$5:$E$20000,"VFA") | E70: =SUMIFS(부채변동표!$O$5:$O$20000,부채변동표!$L$5:$L$20000,설정!$C$20,부채변동표!$P$5:$P$20000,$A70,부채변동표!$E$5:$E$20000,"VFA") | L70: =IF(변동분석!$A70="","",변동분석!$E70) | M70: =IF(L70="",0,SUMIFS(전표_원본!$Z$5:$Z$100000,전표_원본!$O$5:$O$100000,L70,전표_원본!$M$5:$M$100000,설정!$C$20)) | N70: =IF(L70="",0,SUMIFS(전표_원본!$Z$5:$Z$100000,전표_원본!$O$5:$O$100000,L70,전표_원본!$M$5:$M$100000,설정!$C$20-1)) | O70: =M70-N70 | P70: =IF(L70="","",O70+ROW()/1000000)
A71: F52 | B71: RA 해제 | C71: =SUMIFS(부채변동표!$M$5:$M$20000,부채변동표!$L$5:$L$20000,설정!$C$20,부채변동표!$P$5:$P$20000,$A71,부채변동표!$E$5:$E$20000,"VFA") | D71: =SUMIFS(부채변동표!$N$5:$N$20000,부채변동표!$L$5:$L$20000,설정!$C$20,부채변동표!$P$5:$P$20000,$A71,부채변동표!$E$5:$E$20000,"VFA") | E71: =SUMIFS(부채변동표!$O$5:$O$20000,부채변동표!$L$5:$L$20000,설정!$C$20,부채변동표!$P$5:$P$20000,$A71,부채변동표!$E$5:$E$20000,"VFA") | L71: =IF(변동분석!$A71="","",변동분석!$E71) | M71: =IF(L71="",0,SUMIFS(전표_원본!$Z$5:$Z$100000,전표_원본!$O$5:$O$100000,L71,전표_원본!$M$5:$M$100000,설정!$C$20)) | N71: =IF(L71="",0,SUMIFS(전표_원본!$Z$5:$Z$100000,전표_원본!$O$5:$O$100000,L71,전표_원본!$M$5:$M$100000,설정!$C$20-1)) | O71: =M71-N71 | P71: =IF(L71="","",O71+ROW()/1000000)
A72: F60 | B72: 현금흐름 및 기타 | C72: =SUMIFS(부채변동표!$M$5:$M$20000,부채변동표!$L$5:$L$20000,설정!$C$20,부채변동표!$P$5:$P$20000,$A72,부채변동표!$E$5:$E$20000,"VFA") | D72: =SUMIFS(부채변동표!$N$5:$N$20000,부채변동표!$L$5:$L$20000,설정!$C$20,부채변동표!$P$5:$P$20000,$A72,부채변동표!$E$5:$E$20000,"VFA") | E72: =SUMIFS(부채변동표!$O$5:$O$20000,부채변동표!$L$5:$L$20000,설정!$C$20,부채변동표!$P$5:$P$20000,$A72,부채변동표!$E$5:$E$20000,"VFA") | L72: =IF(변동분석!$A72="","",변동분석!$E72) | M72: =IF(L72="",0,SUMIFS(전표_원본!$Z$5:$Z$100000,전표_원본!$O$5:$O$100000,L72,전표_원본!$M$5:$M$100000,설정!$C$20)) | N72: =IF(L72="",0,SUMIFS(전표_원본!$Z$5:$Z$100000,전표_원본!$O$5:$O$100000,L72,전표_원본!$M$5:$M$100000,설정!$C$20-1)) | O72: =M72-N72 | P72: =IF(L72="","",O72+ROW()/1000000)
A73: F99 | B73: 기말잔액 | C73: =SUMIFS(부채변동표!$M$5:$M$20000,부채변동표!$L$5:$L$20000,설정!$C$20,부채변동표!$P$5:$P$20000,$A73,부채변동표!$E$5:$E$20000,"VFA") | D73: =SUMIFS(부채변동표!$N$5:$N$20000,부채변동표!$L$5:$L$20000,설정!$C$20,부채변동표!$P$5:$P$20000,$A73,부채변동표!$E$5:$E$20000,"VFA") | E73: =SUMIFS(부채변동표!$O$5:$O$20000,부채변동표!$L$5:$L$20000,설정!$C$20,부채변동표!$P$5:$P$20000,$A73,부채변동표!$E$5:$E$20000,"VFA") | L73: =IF(변동분석!$A73="","",변동분석!$E73) | M73: =IF(L73="",0,SUMIFS(전표_원본!$Z$5:$Z$100000,전표_원본!$O$5:$O$100000,L73,전표_원본!$M$5:$M$100000,설정!$C$20)) | N73: =IF(L73="",0,SUMIFS(전표_원본!$Z$5:$Z$100000,전표_원본!$O$5:$O$100000,L73,전표_원본!$M$5:$M$100000,설정!$C$20-1)) | O73: =M73-N73 | P73: =IF(L73="","",O73+ROW()/1000000)
B74: CSM 당월 변동 (기말 − 기초) | E74: =E73-E63 | L74: =IF(변동분석!$A74="","",변동분석!$E74) | M74: =IF(L74="",0,SUMIFS(전표_원본!$Z$5:$Z$100000,전표_원본!$O$5:$O$100000,L74,전표_원본!$M$5:$M$100000,설정!$C$20)) | N74: =IF(L74="",0,SUMIFS(전표_원본!$Z$5:$Z$100000,전표_원본!$O$5:$O$100000,L74,전표_원본!$M$5:$M$100000,설정!$C$20-1)) | O74: =M74-N74 | P74: =IF(L74="","",O74+ROW()/1000000)
B75: 그중 사업비 관련 (F21 + F31) | E75: =E65+E67 | L75: =IF(변동분석!$A75="","",변동분석!$E75) | M75: =IF(L75="",0,SUMIFS(전표_원본!$Z$5:$Z$100000,전표_원본!$O$5:$O$100000,L75,전표_원본!$M$5:$M$100000,설정!$C$20)) | N75: =IF(L75="",0,SUMIFS(전표_원본!$Z$5:$Z$100000,전표_원본!$O$5:$O$100000,L75,전표_원본!$M$5:$M$100000,설정!$C$20-1)) | O75: =M75-N75 | P75: =IF(L75="","",O75+ROW()/1000000)
L76: =IF(변동분석!$A76="","",변동분석!$E76) | M76: =IF(L76="",0,SUMIFS(전표_원본!$Z$5:$Z$100000,전표_원본!$O$5:$O$100000,L76,전표_원본!$M$5:$M$100000,설정!$C$20)) | N76: =IF(L76="",0,SUMIFS(전표_원본!$Z$5:$Z$100000,전표_원본!$O$5:$O$100000,L76,전표_원본!$M$5:$M$100000,설정!$C$20-1)) | O76: =M76-N76 | P76: =IF(L76="","",O76+ROW()/1000000)
A77: 5. 신계약비 증가 기여 (부서 × 계정, 당월 − 전월, 귀속 신계약비 기준) | L77: =IF(변동분석!$A77="","",변동분석!$E77) | M77: =IF(L77="",0,SUMIFS(전표_원본!$Z$5:$Z$100000,전표_원본!$O$5:$O$100000,L77,전표_원본!$M$5:$M$100000,설정!$C$20)) | N77: =IF(L77="",0,SUMIFS(전표_원본!$Z$5:$Z$100000,전표_원본!$O$5:$O$100000,L77,전표_원본!$M$5:$M$100000,설정!$C$20-1)) | O77: =M77-N77 | P77: =IF(L77="","",O77+ROW()/1000000)
A78: 순위 | B78: 부서 | C78: 계정 | D78: 당월 | E78: 전월 | F78: 증감 | L78: =IF(변동분석!$A78="","",변동분석!$E78) | M78: =IF(L78="",0,SUMIFS(전표_원본!$Z$5:$Z$100000,전표_원본!$O$5:$O$100000,L78,전표_원본!$M$5:$M$100000,설정!$C$20)) | N78: =IF(L78="",0,SUMIFS(전표_원본!$Z$5:$Z$100000,전표_원본!$O$5:$O$100000,L78,전표_원본!$M$5:$M$100000,설정!$C$20-1)) | O78: =M78-N78 | P78: =IF(L78="","",O78+ROW()/1000000)
A79: 1 | B79: =IF($K79="","",INDEX(변동분석!$B$7:$B$119,$K79)) | C79: =IF($K79="","",INDEX(변동분석!$D$7:$D$119,$K79)) | D79: =IF($K79="","",INDEX($M$7:$M$119,$K79)) | E79: =IF($K79="","",INDEX($N$7:$N$119,$K79)) | F79: =IF($K79="","",INDEX($O$7:$O$119,$K79)) | K79: =IFERROR(MATCH(LARGE($P$7:$P$119,1),$P$7:$P$119,0),"") | L79: =IF(변동분석!$A79="","",변동분석!$E79) | M79: =IF(L79="",0,SUMIFS(전표_원본!$Z$5:$Z$100000,전표_원본!$O$5:$O$100000,L79,전표_원본!$M$5:$M$100000,설정!$C$20)) | N79: =IF(L79="",0,SUMIFS(전표_원본!$Z$5:$Z$100000,전표_원본!$O$5:$O$100000,L79,전표_원본!$M$5:$M$100000,설정!$C$20-1)) | O79: =M79-N79 | P79: =IF(L79="","",O79+ROW()/1000000)
A80: 2 | B80: =IF($K80="","",INDEX(변동분석!$B$7:$B$119,$K80)) | C80: =IF($K80="","",INDEX(변동분석!$D$7:$D$119,$K80)) | D80: =IF($K80="","",INDEX($M$7:$M$119,$K80)) | E80: =IF($K80="","",INDEX($N$7:$N$119,$K80)) | F80: =IF($K80="","",INDEX($O$7:$O$119,$K80)) | K80: =IFERROR(MATCH(LARGE($P$7:$P$119,2),$P$7:$P$119,0),"") | L80: =IF(변동분석!$A80="","",변동분석!$E80) | M80: =IF(L80="",0,SUMIFS(전표_원본!$Z$5:$Z$100000,전표_원본!$O$5:$O$100000,L80,전표_원본!$M$5:$M$100000,설정!$C$20)) | N80: =IF(L80="",0,SUMIFS(전표_원본!$Z$5:$Z$100000,전표_원본!$O$5:$O$100000,L80,전표_원본!$M$5:$M$100000,설정!$C$20-1)) | O80: =M80-N80 | P80: =IF(L80="","",O80+ROW()/1000000)
A81: 3 | B81: =IF($K81="","",INDEX(변동분석!$B$7:$B$119,$K81)) | C81: =IF($K81="","",INDEX(변동분석!$D$7:$D$119,$K81)) | D81: =IF($K81="","",INDEX($M$7:$M$119,$K81)) | E81: =IF($K81="","",INDEX($N$7:$N$119,$K81)) | F81: =IF($K81="","",INDEX($O$7:$O$119,$K81)) | K81: =IFERROR(MATCH(LARGE($P$7:$P$119,3),$P$7:$P$119,0),"") | L81: =IF(변동분석!$A81="","",변동분석!$E81) | M81: =IF(L81="",0,SUMIFS(전표_원본!$Z$5:$Z$100000,전표_원본!$O$5:$O$100000,L81,전표_원본!$M$5:$M$100000,설정!$C$20)) | N81: =IF(L81="",0,SUMIFS(전표_원본!$Z$5:$Z$100000,전표_원본!$O$5:$O$100000,L81,전표_원본!$M$5:$M$100000,설정!$C$20-1)) | O81: =M81-N81 | P81: =IF(L81="","",O81+ROW()/1000000)
A82: 4 | B82: =IF($K82="","",INDEX(변동분석!$B$7:$B$119,$K82)) | C82: =IF($K82="","",INDEX(변동분석!$D$7:$D$119,$K82)) | D82: =IF($K82="","",INDEX($M$7:$M$119,$K82)) | E82: =IF($K82="","",INDEX($N$7:$N$119,$K82)) | F82: =IF($K82="","",INDEX($O$7:$O$119,$K82)) | K82: =IFERROR(MATCH(LARGE($P$7:$P$119,4),$P$7:$P$119,0),"") | L82: =IF(변동분석!$A82="","",변동분석!$E82) | M82: =IF(L82="",0,SUMIFS(전표_원본!$Z$5:$Z$100000,전표_원본!$O$5:$O$100000,L82,전표_원본!$M$5:$M$100000,설정!$C$20)) | N82: =IF(L82="",0,SUMIFS(전표_원본!$Z$5:$Z$100000,전표_원본!$O$5:$O$100000,L82,전표_원본!$M$5:$M$100000,설정!$C$20-1)) | O82: =M82-N82 | P82: =IF(L82="","",O82+ROW()/1000000)
A83: 5 | B83: =IF($K83="","",INDEX(변동분석!$B$7:$B$119,$K83)) | C83: =IF($K83="","",INDEX(변동분석!$D$7:$D$119,$K83)) | D83: =IF($K83="","",INDEX($M$7:$M$119,$K83)) | E83: =IF($K83="","",INDEX($N$7:$N$119,$K83)) | F83: =IF($K83="","",INDEX($O$7:$O$119,$K83)) | K83: =IFERROR(MATCH(LARGE($P$7:$P$119,5),$P$7:$P$119,0),"") | L83: =IF(변동분석!$A83="","",변동분석!$E83) | M83: =IF(L83="",0,SUMIFS(전표_원본!$Z$5:$Z$100000,전표_원본!$O$5:$O$100000,L83,전표_원본!$M$5:$M$100000,설정!$C$20)) | N83: =IF(L83="",0,SUMIFS(전표_원본!$Z$5:$Z$100000,전표_원본!$O$5:$O$100000,L83,전표_원본!$M$5:$M$100000,설정!$C$20-1)) | O83: =M83-N83 | P83: =IF(L83="","",O83+ROW()/1000000)
L84: =IF(변동분석!$A84="","",변동분석!$E84) | M84: =IF(L84="",0,SUMIFS(전표_원본!$Z$5:$Z$100000,전표_원본!$O$5:$O$100000,L84,전표_원본!$M$5:$M$100000,설정!$C$20)) | N84: =IF(L84="",0,SUMIFS(전표_원본!$Z$5:$Z$100000,전표_원본!$O$5:$O$100000,L84,전표_원본!$M$5:$M$100000,설정!$C$20-1)) | O84: =M84-N84 | P84: =IF(L84="","",O84+ROW()/1000000)
A85: 6. 근거 전표 (당월, 귀속 신계약비 큰 순) | L85: =IF(변동분석!$A85="","",변동분석!$E85) | M85: =IF(L85="",0,SUMIFS(전표_원본!$Z$5:$Z$100000,전표_원본!$O$5:$O$100000,L85,전표_원본!$M$5:$M$100000,설정!$C$20)) | N85: =IF(L85="",0,SUMIFS(전표_원본!$Z$5:$Z$100000,전표_원본!$O$5:$O$100000,L85,전표_원본!$M$5:$M$100000,설정!$C$20-1)) | O85: =M85-N85 | P85: =IF(L85="","",O85+ROW()/1000000)
A86: 전기일 | B86: 전표번호 | C86: 코스트센터 | D86: G/L 계정 | E86: 거래처 | F86: 적요 | G86: 금액 | H86: 신계약 귀속 | L86: =IF(변동분석!$A86="","",변동분석!$E86) | M86: =IF(L86="",0,SUMIFS(전표_원본!$Z$5:$Z$100000,전표_원본!$O$5:$O$100000,L86,전표_원본!$M$5:$M$100000,설정!$C$20)) | N86: =IF(L86="",0,SUMIFS(전표_원본!$Z$5:$Z$100000,전표_원본!$O$5:$O$100000,L86,전표_원본!$M$5:$M$100000,설정!$C$20-1)) | O86: =M86-N86 | P86: =IF(L86="","",O86+ROW()/1000000)
A87: =IF($K87="","",INDEX(전표_원본!$D$5:$D$100000,$K87)) | B87: =IF($K87="","",INDEX(전표_원본!$C$5:$C$100000,$K87)) | C87: =IF($K87="","",INDEX(전표_원본!$G$5:$G$100000,$K87)) | D87: =IF($K87="","",INDEX(전표_원본!$F$5:$F$100000,$K87)) | E87: =IF($K87="","",INDEX(전표_원본!$K$5:$K$100000,$K87)) | F87: =IF($K87="","",INDEX(전표_원본!$I$5:$I$100000,$K87)) | G87: =IF($K87="","",INDEX(전표_원본!$P$5:$P$100000,$K87)) | H87: =IF($K87="","",INDEX(전표_원본!$Z$5:$Z$100000,$K87)) | K87: =IFERROR(MATCH(LARGE(전표_원본!$AC$5:$AC$100000,1),전표_원본!$AC$5:$AC$100000,0),"") | L87: =IF(변동분석!$A87="","",변동분석!$E87) | M87: =IF(L87="",0,SUMIFS(전표_원본!$Z$5:$Z$100000,전표_원본!$O$5:$O$100000,L87,전표_원본!$M$5:$M$100000,설정!$C$20)) | N87: =IF(L87="",0,SUMIFS(전표_원본!$Z$5:$Z$100000,전표_원본!$O$5:$O$100000,L87,전표_원본!$M$5:$M$100000,설정!$C$20-1)) | O87: =M87-N87 | P87: =IF(L87="","",O87+ROW()/1000000)
A88: =IF($K88="","",INDEX(전표_원본!$D$5:$D$100000,$K88)) | B88: =IF($K88="","",INDEX(전표_원본!$C$5:$C$100000,$K88)) | C88: =IF($K88="","",INDEX(전표_원본!$G$5:$G$100000,$K88)) | D88: =IF($K88="","",INDEX(전표_원본!$F$5:$F$100000,$K88)) | E88: =IF($K88="","",INDEX(전표_원본!$K$5:$K$100000,$K88)) | F88: =IF($K88="","",INDEX(전표_원본!$I$5:$I$100000,$K88)) | G88: =IF($K88="","",INDEX(전표_원본!$P$5:$P$100000,$K88)) | H88: =IF($K88="","",INDEX(전표_원본!$Z$5:$Z$100000,$K88)) | K88: =IFERROR(MATCH(LARGE(전표_원본!$AC$5:$AC$100000,2),전표_원본!$AC$5:$AC$100000,0),"") | L88: =IF(변동분석!$A88="","",변동분석!$E88) | M88: =IF(L88="",0,SUMIFS(전표_원본!$Z$5:$Z$100000,전표_원본!$O$5:$O$100000,L88,전표_원본!$M$5:$M$100000,설정!$C$20)) | N88: =IF(L88="",0,SUMIFS(전표_원본!$Z$5:$Z$100000,전표_원본!$O$5:$O$100000,L88,전표_원본!$M$5:$M$100000,설정!$C$20-1)) | O88: =M88-N88 | P88: =IF(L88="","",O88+ROW()/1000000)
A89: =IF($K89="","",INDEX(전표_원본!$D$5:$D$100000,$K89)) | B89: =IF($K89="","",INDEX(전표_원본!$C$5:$C$100000,$K89)) | C89: =IF($K89="","",INDEX(전표_원본!$G$5:$G$100000,$K89)) | D89: =IF($K89="","",INDEX(전표_원본!$F$5:$F$100000,$K89)) | E89: =IF($K89="","",INDEX(전표_원본!$K$5:$K$100000,$K89)) | F89: =IF($K89="","",INDEX(전표_원본!$I$5:$I$100000,$K89)) | G89: =IF($K89="","",INDEX(전표_원본!$P$5:$P$100000,$K89)) | H89: =IF($K89="","",INDEX(전표_원본!$Z$5:$Z$100000,$K89)) | K89: =IFERROR(MATCH(LARGE(전표_원본!$AC$5:$AC$100000,3),전표_원본!$AC$5:$AC$100000,0),"") | L89: =IF(변동분석!$A89="","",변동분석!$E89) | M89: =IF(L89="",0,SUMIFS(전표_원본!$Z$5:$Z$100000,전표_원본!$O$5:$O$100000,L89,전표_원본!$M$5:$M$100000,설정!$C$20)) | N89: =IF(L89="",0,SUMIFS(전표_원본!$Z$5:$Z$100000,전표_원본!$O$5:$O$100000,L89,전표_원본!$M$5:$M$100000,설정!$C$20-1)) | O89: =M89-N89 | P89: =IF(L89="","",O89+ROW()/1000000)
A90: =IF($K90="","",INDEX(전표_원본!$D$5:$D$100000,$K90)) | B90: =IF($K90="","",INDEX(전표_원본!$C$5:$C$100000,$K90)) | C90: =IF($K90="","",INDEX(전표_원본!$G$5:$G$100000,$K90)) | D90: =IF($K90="","",INDEX(전표_원본!$F$5:$F$100000,$K90)) | E90: =IF($K90="","",INDEX(전표_원본!$K$5:$K$100000,$K90)) | F90: =IF($K90="","",INDEX(전표_원본!$I$5:$I$100000,$K90)) | G90: =IF($K90="","",INDEX(전표_원본!$P$5:$P$100000,$K90)) | H90: =IF($K90="","",INDEX(전표_원본!$Z$5:$Z$100000,$K90)) | K90: =IFERROR(MATCH(LARGE(전표_원본!$AC$5:$AC$100000,4),전표_원본!$AC$5:$AC$100000,0),"") | L90: =IF(변동분석!$A90="","",변동분석!$E90) | M90: =IF(L90="",0,SUMIFS(전표_원본!$Z$5:$Z$100000,전표_원본!$O$5:$O$100000,L90,전표_원본!$M$5:$M$100000,설정!$C$20)) | N90: =IF(L90="",0,SUMIFS(전표_원본!$Z$5:$Z$100000,전표_원본!$O$5:$O$100000,L90,전표_원본!$M$5:$M$100000,설정!$C$20-1)) | O90: =M90-N90 | P90: =IF(L90="","",O90+ROW()/1000000)
A91: =IF($K91="","",INDEX(전표_원본!$D$5:$D$100000,$K91)) | B91: =IF($K91="","",INDEX(전표_원본!$C$5:$C$100000,$K91)) | C91: =IF($K91="","",INDEX(전표_원본!$G$5:$G$100000,$K91)) | D91: =IF($K91="","",INDEX(전표_원본!$F$5:$F$100000,$K91)) | E91: =IF($K91="","",INDEX(전표_원본!$K$5:$K$100000,$K91)) | F91: =IF($K91="","",INDEX(전표_원본!$I$5:$I$100000,$K91)) | G91: =IF($K91="","",INDEX(전표_원본!$P$5:$P$100000,$K91)) | H91: =IF($K91="","",INDEX(전표_원본!$Z$5:$Z$100000,$K91)) | K91: =IFERROR(MATCH(LARGE(전표_원본!$AC$5:$AC$100000,5),전표_원본!$AC$5:$AC$100000,0),"") | L91: =IF(변동분석!$A91="","",변동분석!$E91) | M91: =IF(L91="",0,SUMIFS(전표_원본!$Z$5:$Z$100000,전표_원본!$O$5:$O$100000,L91,전표_원본!$M$5:$M$100000,설정!$C$20)) | N91: =IF(L91="",0,SUMIFS(전표_원본!$Z$5:$Z$100000,전표_원본!$O$5:$O$100000,L91,전표_원본!$M$5:$M$100000,설정!$C$20-1)) | O91: =M91-N91 | P91: =IF(L91="","",O91+ROW()/1000000)
A92: =IF($K92="","",INDEX(전표_원본!$D$5:$D$100000,$K92)) | B92: =IF($K92="","",INDEX(전표_원본!$C$5:$C$100000,$K92)) | C92: =IF($K92="","",INDEX(전표_원본!$G$5:$G$100000,$K92)) | D92: =IF($K92="","",INDEX(전표_원본!$F$5:$F$100000,$K92)) | E92: =IF($K92="","",INDEX(전표_원본!$K$5:$K$100000,$K92)) | F92: =IF($K92="","",INDEX(전표_원본!$I$5:$I$100000,$K92)) | G92: =IF($K92="","",INDEX(전표_원본!$P$5:$P$100000,$K92)) | H92: =IF($K92="","",INDEX(전표_원본!$Z$5:$Z$100000,$K92)) | K92: =IFERROR(MATCH(LARGE(전표_원본!$AC$5:$AC$100000,6),전표_원본!$AC$5:$AC$100000,0),"") | L92: =IF(변동분석!$A92="","",변동분석!$E92) | M92: =IF(L92="",0,SUMIFS(전표_원본!$Z$5:$Z$100000,전표_원본!$O$5:$O$100000,L92,전표_원본!$M$5:$M$100000,설정!$C$20)) | N92: =IF(L92="",0,SUMIFS(전표_원본!$Z$5:$Z$100000,전표_원본!$O$5:$O$100000,L92,전표_원본!$M$5:$M$100000,설정!$C$20-1)) | O92: =M92-N92 | P92: =IF(L92="","",O92+ROW()/1000000)
A93: =IF($K93="","",INDEX(전표_원본!$D$5:$D$100000,$K93)) | B93: =IF($K93="","",INDEX(전표_원본!$C$5:$C$100000,$K93)) | C93: =IF($K93="","",INDEX(전표_원본!$G$5:$G$100000,$K93)) | D93: =IF($K93="","",INDEX(전표_원본!$F$5:$F$100000,$K93)) | E93: =IF($K93="","",INDEX(전표_원본!$K$5:$K$100000,$K93)) | F93: =IF($K93="","",INDEX(전표_원본!$I$5:$I$100000,$K93)) | G93: =IF($K93="","",INDEX(전표_원본!$P$5:$P$100000,$K93)) | H93: =IF($K93="","",INDEX(전표_원본!$Z$5:$Z$100000,$K93)) | K93: =IFERROR(MATCH(LARGE(전표_원본!$AC$5:$AC$100000,7),전표_원본!$AC$5:$AC$100000,0),"") | L93: =IF(변동분석!$A93="","",변동분석!$E93) | M93: =IF(L93="",0,SUMIFS(전표_원본!$Z$5:$Z$100000,전표_원본!$O$5:$O$100000,L93,전표_원본!$M$5:$M$100000,설정!$C$20)) | N93: =IF(L93="",0,SUMIFS(전표_원본!$Z$5:$Z$100000,전표_원본!$O$5:$O$100000,L93,전표_원본!$M$5:$M$100000,설정!$C$20-1)) | O93: =M93-N93 | P93: =IF(L93="","",O93+ROW()/1000000)
A94: =IF($K94="","",INDEX(전표_원본!$D$5:$D$100000,$K94)) | B94: =IF($K94="","",INDEX(전표_원본!$C$5:$C$100000,$K94)) | C94: =IF($K94="","",INDEX(전표_원본!$G$5:$G$100000,$K94)) | D94: =IF($K94="","",INDEX(전표_원본!$F$5:$F$100000,$K94)) | E94: =IF($K94="","",INDEX(전표_원본!$K$5:$K$100000,$K94)) | F94: =IF($K94="","",INDEX(전표_원본!$I$5:$I$100000,$K94)) | G94: =IF($K94="","",INDEX(전표_원본!$P$5:$P$100000,$K94)) | H94: =IF($K94="","",INDEX(전표_원본!$Z$5:$Z$100000,$K94)) | K94: =IFERROR(MATCH(LARGE(전표_원본!$AC$5:$AC$100000,8),전표_원본!$AC$5:$AC$100000,0),"") | L94: =IF(변동분석!$A94="","",변동분석!$E94) | M94: =IF(L94="",0,SUMIFS(전표_원본!$Z$5:$Z$100000,전표_원본!$O$5:$O$100000,L94,전표_원본!$M$5:$M$100000,설정!$C$20)) | N94: =IF(L94="",0,SUMIFS(전표_원본!$Z$5:$Z$100000,전표_원본!$O$5:$O$100000,L94,전표_원본!$M$5:$M$100000,설정!$C$20-1)) | O94: =M94-N94 | P94: =IF(L94="","",O94+ROW()/1000000)
A95: =IF($K95="","",INDEX(전표_원본!$D$5:$D$100000,$K95)) | B95: =IF($K95="","",INDEX(전표_원본!$C$5:$C$100000,$K95)) | C95: =IF($K95="","",INDEX(전표_원본!$G$5:$G$100000,$K95)) | D95: =IF($K95="","",INDEX(전표_원본!$F$5:$F$100000,$K95)) | E95: =IF($K95="","",INDEX(전표_원본!$K$5:$K$100000,$K95)) | F95: =IF($K95="","",INDEX(전표_원본!$I$5:$I$100000,$K95)) | G95: =IF($K95="","",INDEX(전표_원본!$P$5:$P$100000,$K95)) | H95: =IF($K95="","",INDEX(전표_원본!$Z$5:$Z$100000,$K95)) | K95: =IFERROR(MATCH(LARGE(전표_원본!$AC$5:$AC$100000,9),전표_원본!$AC$5:$AC$100000,0),"") | L95: =IF(변동분석!$A95="","",변동분석!$E95) | M95: =IF(L95="",0,SUMIFS(전표_원본!$Z$5:$Z$100000,전표_원본!$O$5:$O$100000,L95,전표_원본!$M$5:$M$100000,설정!$C$20)) | N95: =IF(L95="",0,SUMIFS(전표_원본!$Z$5:$Z$100000,전표_원본!$O$5:$O$100000,L95,전표_원본!$M$5:$M$100000,설정!$C$20-1)) | O95: =M95-N95 | P95: =IF(L95="","",O95+ROW()/1000000)
A96: =IF($K96="","",INDEX(전표_원본!$D$5:$D$100000,$K96)) | B96: =IF($K96="","",INDEX(전표_원본!$C$5:$C$100000,$K96)) | C96: =IF($K96="","",INDEX(전표_원본!$G$5:$G$100000,$K96)) | D96: =IF($K96="","",INDEX(전표_원본!$F$5:$F$100000,$K96)) | E96: =IF($K96="","",INDEX(전표_원본!$K$5:$K$100000,$K96)) | F96: =IF($K96="","",INDEX(전표_원본!$I$5:$I$100000,$K96)) | G96: =IF($K96="","",INDEX(전표_원본!$P$5:$P$100000,$K96)) | H96: =IF($K96="","",INDEX(전표_원본!$Z$5:$Z$100000,$K96)) | K96: =IFERROR(MATCH(LARGE(전표_원본!$AC$5:$AC$100000,10),전표_원본!$AC$5:$AC$100000,0),"") | L96: =IF(변동분석!$A96="","",변동분석!$E96) | M96: =IF(L96="",0,SUMIFS(전표_원본!$Z$5:$Z$100000,전표_원본!$O$5:$O$100000,L96,전표_원본!$M$5:$M$100000,설정!$C$20)) | N96: =IF(L96="",0,SUMIFS(전표_원본!$Z$5:$Z$100000,전표_원본!$O$5:$O$100000,L96,전표_원본!$M$5:$M$100000,설정!$C$20-1)) | O96: =M96-N96 | P96: =IF(L96="","",O96+ROW()/1000000)
L97: =IF(변동분석!$A97="","",변동분석!$E97) | M97: =IF(L97="",0,SUMIFS(전표_원본!$Z$5:$Z$100000,전표_원본!$O$5:$O$100000,L97,전표_원본!$M$5:$M$100000,설정!$C$20)) | N97: =IF(L97="",0,SUMIFS(전표_원본!$Z$5:$Z$100000,전표_원본!$O$5:$O$100000,L97,전표_원본!$M$5:$M$100000,설정!$C$20-1)) | O97: =M97-N97 | P97: =IF(L97="","",O97+ROW()/1000000)
L98: =IF(변동분석!$A98="","",변동분석!$E98) | M98: =IF(L98="",0,SUMIFS(전표_원본!$Z$5:$Z$100000,전표_원본!$O$5:$O$100000,L98,전표_원본!$M$5:$M$100000,설정!$C$20)) | N98: =IF(L98="",0,SUMIFS(전표_원본!$Z$5:$Z$100000,전표_원본!$O$5:$O$100000,L98,전표_원본!$M$5:$M$100000,설정!$C$20-1)) | O98: =M98-N98 | P98: =IF(L98="","",O98+ROW()/1000000)
L99: =IF(변동분석!$A99="","",변동분석!$E99) | M99: =IF(L99="",0,SUMIFS(전표_원본!$Z$5:$Z$100000,전표_원본!$O$5:$O$100000,L99,전표_원본!$M$5:$M$100000,설정!$C$20)) | N99: =IF(L99="",0,SUMIFS(전표_원본!$Z$5:$Z$100000,전표_원본!$O$5:$O$100000,L99,전표_원본!$M$5:$M$100000,설정!$C$20-1)) | O99: =M99-N99 | P99: =IF(L99="","",O99+ROW()/1000000)
L100: =IF(변동분석!$A100="","",변동분석!$E100) | M100: =IF(L100="",0,SUMIFS(전표_원본!$Z$5:$Z$100000,전표_원본!$O$5:$O$100000,L100,전표_원본!$M$5:$M$100000,설정!$C$20)) | N100: =IF(L100="",0,SUMIFS(전표_원본!$Z$5:$Z$100000,전표_원본!$O$5:$O$100000,L100,전표_원본!$M$5:$M$100000,설정!$C$20-1)) | O100: =M100-N100 | P100: =IF(L100="","",O100+ROW()/1000000)
L101: =IF(변동분석!$A101="","",변동분석!$E101) | M101: =IF(L101="",0,SUMIFS(전표_원본!$Z$5:$Z$100000,전표_원본!$O$5:$O$100000,L101,전표_원본!$M$5:$M$100000,설정!$C$20)) | N101: =IF(L101="",0,SUMIFS(전표_원본!$Z$5:$Z$100000,전표_원본!$O$5:$O$100000,L101,전표_원본!$M$5:$M$100000,설정!$C$20-1)) | O101: =M101-N101 | P101: =IF(L101="","",O101+ROW()/1000000)
...

Sheet 리포트
A1: =설정!$C$5&" TRACE 사업비 변동 점검 ("&INT((설정!$C$20-1)/12)&"-"&TEXT(MOD(설정!$C$20-1,12)+1,"00")&")"
A2: ="단위: "&설정!$C$9&" · 전표·TB·예산판 대사: "&계정변동!$P$25&" · 자가진단: "&자가진단!$B$4
A4: 사업비 당월 | B4: 전월 대비 | C4: 전년동월 대비 | D4: 분기 한도 초과(예상) | E4: 분기 한도 주의 | F4: 무예산 집행
A5: =월별집계!Z6 | B5: =IF(월별집계!Y6<=0,0,월별집계!Z6/월별집계!Y6-1) | C5: =IF(월별집계!N6<=0,0,월별집계!Z6/월별집계!N6-1) | D5: =COUNTIF(변동분석!$AO$7:$AO$506,"한도 초과")+COUNTIF(변동분석!$AO$7:$AO$506,"초과 예상") | E5: =COUNTIF(변동분석!$AO$7:$AO$506,"주의") | F5: =COUNTIF(변동분석!$AO$7:$AO$506,"무예산")
A7: 1. 주의 대상 TOP 10
A8: 순위 | B8: 부서 | C8: 계정 | D8: 당월 | E8: 전월대비 | F8: 예산 | G8: 빠른 신호 | H8: 확인된 원인
A9: =주의대상!A6 | B9: =주의대상!B6 | C9: =주의대상!C6 | D9: =주의대상!D6 | E9: =주의대상!E6 | F9: =주의대상!G6 | G9: =주의대상!J6 | H9: =주의대상!M6
A10: =주의대상!A7 | B10: =주의대상!B7 | C10: =주의대상!C7 | D10: =주의대상!D7 | E10: =주의대상!E7 | F10: =주의대상!G7 | G10: =주의대상!J7 | H10: =주의대상!M7
A11: =주의대상!A8 | B11: =주의대상!B8 | C11: =주의대상!C8 | D11: =주의대상!D8 | E11: =주의대상!E8 | F11: =주의대상!G8 | G11: =주의대상!J8 | H11: =주의대상!M8
A12: =주의대상!A9 | B12: =주의대상!B9 | C12: =주의대상!C9 | D12: =주의대상!D9 | E12: =주의대상!E9 | F12: =주의대상!G9 | G12: =주의대상!J9 | H12: =주의대상!M9
A13: =주의대상!A10 | B13: =주의대상!B10 | C13: =주의대상!C10 | D13: =주의대상!D10 | E13: =주의대상!E10 | F13: =주의대상!G10 | G13: =주의대상!J10 | H13: =주의대상!M10
A14: =주의대상!A11 | B14: =주의대상!B11 | C14: =주의대상!C11 | D14: =주의대상!D11 | E14: =주의대상!E11 | F14: =주의대상!G11 | G14: =주의대상!J11 | H14: =주의대상!M11
A15: =주의대상!A12 | B15: =주의대상!B12 | C15: =주의대상!C12 | D15: =주의대상!D12 | E15: =주의대상!E12 | F15: =주의대상!G12 | G15: =주의대상!J12 | H15: =주의대상!M12
A16: =주의대상!A13 | B16: =주의대상!B13 | C16: =주의대상!C13 | D16: =주의대상!D13 | E16: =주의대상!E13 | F16: =주의대상!G13 | G16: =주의대상!J13 | H16: =주의대상!M13
A17: =주의대상!A14 | B17: =주의대상!B14 | C17: =주의대상!C14 | D17: =주의대상!D14 | E17: =주의대상!E14 | F17: =주의대상!G14 | G17: =주의대상!J14 | H17: =주의대상!M14
A18: =주의대상!A15 | B18: =주의대상!B15 | C18: =주의대상!C15 | D18: =주의대상!D15 | E18: =주의대상!E15 | F18: =주의대상!G15 | G18: =주의대상!J15 | H18: =주의대상!M15
A20: 2. 원인 분석 (원인분석 시트에서 선택한 항목)
A21: =원인분석!A18
A22: 순위 | B22: 패턴 | C22: 근거 강도 | D22: 설명
A23: =원인분석!A21 | B23: =원인분석!B21 | C23: =원인분석!C21 | D23: =원인분석!D21
A24: =원인분석!A22 | B24: =원인분석!B22 | C24: =원인분석!C22 | D24: =원인분석!D22
A25: =원인분석!A23 | B25: =원인분석!B23 | C25: =원인분석!C23 | D25: =원인분석!D23
A26: =원인분석!A24 | B26: =원인분석!B24 | C26: =원인분석!C24 | D26: =원인분석!D24
A28: 3. 월별 사업비 (전사, 당해 vs 전년)
K29: 월 | L29: =설정!$C$6&"년" | M29: =설정!$C$6-1&"년"
K30: 1월 | L30: =IF(1>설정!$C$7,0,SUMIFS(전표_원본!$P$5:$P$100000,전표_원본!$M$5:$M$100000,설정!$C$6*12+1)) | M30: =SUMIFS(전표_원본!$P$5:$P$100000,전표_원본!$M$5:$M$100000,(설정!$C$6-1)*12+1)
K31: 2월 | L31: =IF(2>설정!$C$7,0,SUMIFS(전표_원본!$P$5:$P$100000,전표_원본!$M$5:$M$100000,설정!$C$6*12+2)) | M31: =SUMIFS(전표_원본!$P$5:$P$100000,전표_원본!$M$5:$M$100000,(설정!$C$6-1)*12+2)
K32: 3월 | L32: =IF(3>설정!$C$7,0,SUMIFS(전표_원본!$P$5:$P$100000,전표_원본!$M$5:$M$100000,설정!$C$6*12+3)) | M32: =SUMIFS(전표_원본!$P$5:$P$100000,전표_원본!$M$5:$M$100000,(설정!$C$6-1)*12+3)
K33: 4월 | L33: =IF(4>설정!$C$7,0,SUMIFS(전표_원본!$P$5:$P$100000,전표_원본!$M$5:$M$100000,설정!$C$6*12+4)) | M33: =SUMIFS(전표_원본!$P$5:$P$100000,전표_원본!$M$5:$M$100000,(설정!$C$6-1)*12+4)
K34: 5월 | L34: =IF(5>설정!$C$7,0,SUMIFS(전표_원본!$P$5:$P$100000,전표_원본!$M$5:$M$100000,설정!$C$6*12+5)) | M34: =SUMIFS(전표_원본!$P$5:$P$100000,전표_원본!$M$5:$M$100000,(설정!$C$6-1)*12+5)
K35: 6월 | L35: =IF(6>설정!$C$7,0,SUMIFS(전표_원본!$P$5:$P$100000,전표_원본!$M$5:$M$100000,설정!$C$6*12+6)) | M35: =SUMIFS(전표_원본!$P$5:$P$100000,전표_원본!$M$5:$M$100000,(설정!$C$6-1)*12+6)
K36: 7월 | L36: =IF(7>설정!$C$7,0,SUMIFS(전표_원본!$P$5:$P$100000,전표_원본!$M$5:$M$100000,설정!$C$6*12+7)) | M36: =SUMIFS(전표_원본!$P$5:$P$100000,전표_원본!$M$5:$M$100000,(설정!$C$6-1)*12+7)
K37: 8월 | L37: =IF(8>설정!$C$7,0,SUMIFS(전표_원본!$P$5:$P$100000,전표_원본!$M$5:$M$100000,설정!$C$6*12+8)) | M37: =SUMIFS(전표_원본!$P$5:$P$100000,전표_원본!$M$5:$M$100000,(설정!$C$6-1)*12+8)
K38: 9월 | L38: =IF(9>설정!$C$7,0,SUMIFS(전표_원본!$P$5:$P$100000,전표_원본!$M$5:$M$100000,설정!$C$6*12+9)) | M38: =SUMIFS(전표_원본!$P$5:$P$100000,전표_원본!$M$5:$M$100000,(설정!$C$6-1)*12+9)
K39: 10월 | L39: =IF(10>설정!$C$7,0,SUMIFS(전표_원본!$P$5:$P$100000,전표_원본!$M$5:$M$100000,설정!$C$6*12+10)) | M39: =SUMIFS(전표_원본!$P$5:$P$100000,전표_원본!$M$5:$M$100000,(설정!$C$6-1)*12+10)
K40: 11월 | L40: =IF(11>설정!$C$7,0,SUMIFS(전표_원본!$P$5:$P$100000,전표_원본!$M$5:$M$100000,설정!$C$6*12+11)) | M40: =SUMIFS(전표_원본!$P$5:$P$100000,전표_원본!$M$5:$M$100000,(설정!$C$6-1)*12+11)
K41: 12월 | L41: =IF(12>설정!$C$7,0,SUMIFS(전표_원본!$P$5:$P$100000,전표_원본!$M$5:$M$100000,설정!$C$6*12+12)) | M41: =SUMIFS(전표_원본!$P$5:$P$100000,전표_원본!$M$5:$M$100000,(설정!$C$6-1)*12+12)

Sheet 주의대상
A1: TRACE · 주의 대상 TOP 10
A2: 점수 = 증가액(30) + 증가율(20) + 이상치(25) + 예산(25), 작은 금액은 30%로 낮춤 · 원인은 원인분석 시트 C5에 순위 입력
A3: ="기준: "&INT((설정!$C$20-1)/12)&"-"&TEXT(MOD(설정!$C$20-1,12)+1,"00")&" · 단위: "&설정!$C$9&" · 분기 한도 초과 "&COUNTIF(변동분석!$AO$7:$AO$506,"한도 초과")&"건 · 초과 예상 "&COUNTIF(변동분석!$AO$7:$AO$506,"초과 예상")&"건 · 주의 "&COUNTIF(변동분석!$AO$7:$AO$506,"주의")&"건 · 무예산 "&COUNTIF(변동분석!$AO$7:$AO$506,"무예산")&"건"
S4: 고갈 추세 (대시보드 주의 대상 상세 그래프용)
A5: 순위 | B5: 부서 | C5: 계정 | D5: 당월 | E5: 전월 대비 | F5: 전년동월 대비 | G5: 분기 판정 | H5: 분기 소진율 | I5: 연간 판정 | J5: 빠른 신호 | K5: 점수 | L5: 키 | M5: 확인된 원인 (코멘트) | N5: 행 | O5: 당분기 | P5: 전분기 대비 | Q5: 당해 누계 | R5: 전년동기 누계 대비 | S5: 연간가용 | T5: 월 소진속도 | U5: 절편 | V5: 추세 연말 누계 | W5: 고갈 예상(개월) | X5: 고갈 예상일 | Y5: 추세 판정 | Z5: 분기 고갈 예상일 | AA5: 누계 1월 | AB5: 누계 2월 | AC5: 누계 3월 | AD5: 누계 4월 | AE5: 누계 5월 | AF5: 누계 6월 | AG5: 누계 7월 | AH5: 누계 8월 | AI5: 누계 9월 | AJ5: 누계 10월 | AK5: 누계 11월 | AL5: 누계 12월 | AM5: 전년 남은기간 월평균 | AN5: 전월 증감액 | AO5: 전분기 증감액 | AP5: 전년동기누계 증감액
A6: 1 | B6: =IF($N6="","",INDEX(변동분석!$B$7:$B$506,$N6)) | C6: =IF($N6="","",INDEX(변동분석!$D$7:$D$506,$N6)) | D6: =IF($N6="","",INDEX(변동분석!$F$7:$F$506,$N6)) | E6: =IF($N6="","",INDEX(변동분석!$H$7:$H$506,$N6)) | F6: =IF($N6="","",INDEX(변동분석!$J$7:$J$506,$N6)) | G6: =IF($N6="","",INDEX(변동분석!$AO$7:$AO$506,$N6)) | H6: =IF($N6="","",INDEX(변동분석!$AN$7:$AN$506,$N6)) | I6: =IF($N6="","",INDEX(변동분석!$W$7:$W$506,$N6)) | J6: =IF($N6="","",INDEX(변동분석!$Z$7:$Z$506,$N6)) | K6: =IF($N6="","",INDEX(변동분석!$AA$7:$AA$506,$N6)) | L6: =IF($N6="","",INDEX(변동분석!$E$7:$E$506,$N6)) | M6: =IF($L6="","",IFERROR(INDEX(코멘트!$F$5:$F$2004,MATCH(설정!$C$6&"|"&설정!$C$7&"|"&$L6,코멘트!$I$5:$I$2004,0)),"(미확인)")) | N6: =IFERROR(MATCH(LARGE(변동분석!$AB$7:$AB$506,A6),변동분석!$AB$7:$AB$506,0),"") | O6: =IF($N6="","",INDEX(변동분석!$K$7:$K$506,$N6)) | P6: =IF($N6="","",INDEX(변동분석!$M$7:$M$506,$N6)) | Q6: =IF($N6="","",INDEX(변동분석!$Q$7:$Q$506,$N6)) | R6: =IF($N6="","",INDEX(변동분석!$AY$7:$AY$506,$N6)) | S6: =IF($N6="","",INDEX(변동분석!$P$7:$P$506,$N6)) | T6: =IF($N6="","",INDEX(변동분석!$AP$7:$AP$506,$N6)) | U6: =IF($N6="","",INDEX(변동분석!$AQ$7:$AQ$506,$N6)) | V6: =IF($N6="","",INDEX(변동분석!$AR$7:$AR$506,$N6)) | W6: =IF($N6="","",INDEX(변동분석!$AS$7:$AS$506,$N6)) | X6: =IF($N6="","",INDEX(변동분석!$AT$7:$AT$506,$N6)) | Y6: =IF($N6="","",INDEX(변동분석!$AU$7:$AU$506,$N6)) | Z6: =IF($N6="","",INDEX(변동분석!$AV$7:$AV$506,$N6)) | AA6: =IF($N6="","",INDEX(월별집계!$AB$7:$AB$506,$N6)) | AB6: =IF($N6="","",INDEX(월별집계!$AC$7:$AC$506,$N6)) | AC6: =IF($N6="","",INDEX(월별집계!$AD$7:$AD$506,$N6)) | AD6: =IF($N6="","",INDEX(월별집계!$AE$7:$AE$506,$N6)) | AE6: =IF($N6="","",INDEX(월별집계!$AF$7:$AF$506,$N6)) | AF6: =IF($N6="","",INDEX(월별집계!$AG$7:$AG$506,$N6)) | AG6: =IF($N6="","",INDEX(월별집계!$AH$7:$AH$506,$N6)) | AH6: =IF($N6="","",INDEX(월별집계!$AI$7:$AI$506,$N6)) | AI6: =IF($N6="","",INDEX(월별집계!$AJ$7:$AJ$506,$N6)) | AJ6: =IF($N6="","",INDEX(월별집계!$AK$7:$AK$506,$N6)) | AK6: =IF($N6="","",INDEX(월별집계!$AL$7:$AL$506,$N6)) | AL6: =IF($N6="","",INDEX(월별집계!$AM$7:$AM$506,$N6)) | AM6: =IF($N6="","",INDEX(변동분석!$AZ$7:$AZ$506,$N6)) | AN6: =IF($N6="","",INDEX(변동분석!$F$7:$F$506,$N6)-INDEX(변동분석!$G$7:$G$506,$N6)) | AO6: =IF($N6="","",INDEX(변동분석!$K$7:$K$506,$N6)-INDEX(변동분석!$L$7:$L$506,$N6)) | AP6: =IF($N6="","",INDEX(변동분석!$Q$7:$Q$506,$N6)-INDEX(변동분석!$AX$7:$AX$506,$N6))
A7: 2 | B7: =IF($N7="","",INDEX(변동분석!$B$7:$B$506,$N7)) | C7: =IF($N7="","",INDEX(변동분석!$D$7:$D$506,$N7)) | D7: =IF($N7="","",INDEX(변동분석!$F$7:$F$506,$N7)) | E7: =IF($N7="","",INDEX(변동분석!$H$7:$H$506,$N7)) | F7: =IF($N7="","",INDEX(변동분석!$J$7:$J$506,$N7)) | G7: =IF($N7="","",INDEX(변동분석!$AO$7:$AO$506,$N7)) | H7: =IF($N7="","",INDEX(변동분석!$AN$7:$AN$506,$N7)) | I7: =IF($N7="","",INDEX(변동분석!$W$7:$W$506,$N7)) | J7: =IF($N7="","",INDEX(변동분석!$Z$7:$Z$506,$N7)) | K7: =IF($N7="","",INDEX(변동분석!$AA$7:$AA$506,$N7)) | L7: =IF($N7="","",INDEX(변동분석!$E$7:$E$506,$N7)) | M7: =IF($L7="","",IFERROR(INDEX(코멘트!$F$5:$F$2004,MATCH(설정!$C$6&"|"&설정!$C$7&"|"&$L7,코멘트!$I$5:$I$2004,0)),"(미확인)")) | N7: =IFERROR(MATCH(LARGE(변동분석!$AB$7:$AB$506,A7),변동분석!$AB$7:$AB$506,0),"") | O7: =IF($N7="","",INDEX(변동분석!$K$7:$K$506,$N7)) | P7: =IF($N7="","",INDEX(변동분석!$M$7:$M$506,$N7)) | Q7: =IF($N7="","",INDEX(변동분석!$Q$7:$Q$506,$N7)) | R7: =IF($N7="","",INDEX(변동분석!$AY$7:$AY$506,$N7)) | S7: =IF($N7="","",INDEX(변동분석!$P$7:$P$506,$N7)) | T7: =IF($N7="","",INDEX(변동분석!$AP$7:$AP$506,$N7)) | U7: =IF($N7="","",INDEX(변동분석!$AQ$7:$AQ$506,$N7)) | V7: =IF($N7="","",INDEX(변동분석!$AR$7:$AR$506,$N7)) | W7: =IF($N7="","",INDEX(변동분석!$AS$7:$AS$506,$N7)) | X7: =IF($N7="","",INDEX(변동분석!$AT$7:$AT$506,$N7)) | Y7: =IF($N7="","",INDEX(변동분석!$AU$7:$AU$506,$N7)) | Z7: =IF($N7="","",INDEX(변동분석!$AV$7:$AV$506,$N7)) | AA7: =IF($N7="","",INDEX(월별집계!$AB$7:$AB$506,$N7)) | AB7: =IF($N7="","",INDEX(월별집계!$AC$7:$AC$506,$N7)) | AC7: =IF($N7="","",INDEX(월별집계!$AD$7:$AD$506,$N7)) | AD7: =IF($N7="","",INDEX(월별집계!$AE$7:$AE$506,$N7)) | AE7: =IF($N7="","",INDEX(월별집계!$AF$7:$AF$506,$N7)) | AF7: =IF($N7="","",INDEX(월별집계!$AG$7:$AG$506,$N7)) | AG7: =IF($N7="","",INDEX(월별집계!$AH$7:$AH$506,$N7)) | AH7: =IF($N7="","",INDEX(월별집계!$AI$7:$AI$506,$N7)) | AI7: =IF($N7="","",INDEX(월별집계!$AJ$7:$AJ$506,$N7)) | AJ7: =IF($N7="","",INDEX(월별집계!$AK$7:$AK$506,$N7)) | AK7: =IF($N7="","",INDEX(월별집계!$AL$7:$AL$506,$N7)) | AL7: =IF($N7="","",INDEX(월별집계!$AM$7:$AM$506,$N7)) | AM7: =IF($N7="","",INDEX(변동분석!$AZ$7:$AZ$506,$N7)) | AN7: =IF($N7="","",INDEX(변동분석!$F$7:$F$506,$N7)-INDEX(변동분석!$G$7:$G$506,$N7)) | AO7: =IF($N7="","",INDEX(변동분석!$K$7:$K$506,$N7)-INDEX(변동분석!$L$7:$L$506,$N7)) | AP7: =IF($N7="","",INDEX(변동분석!$Q$7:$Q$506,$N7)-INDEX(변동분석!$AX$7:$AX$506,$N7))
A8: 3 | B8: =IF($N8="","",INDEX(변동분석!$B$7:$B$506,$N8)) | C8: =IF($N8="","",INDEX(변동분석!$D$7:$D$506,$N8)) | D8: =IF($N8="","",INDEX(변동분석!$F$7:$F$506,$N8)) | E8: =IF($N8="","",INDEX(변동분석!$H$7:$H$506,$N8)) | F8: =IF($N8="","",INDEX(변동분석!$J$7:$J$506,$N8)) | G8: =IF($N8="","",INDEX(변동분석!$AO$7:$AO$506,$N8)) | H8: =IF($N8="","",INDEX(변동분석!$AN$7:$AN$506,$N8)) | I8: =IF($N8="","",INDEX(변동분석!$W$7:$W$506,$N8)) | J8: =IF($N8="","",INDEX(변동분석!$Z$7:$Z$506,$N8)) | K8: =IF($N8="","",INDEX(변동분석!$AA$7:$AA$506,$N8)) | L8: =IF($N8="","",INDEX(변동분석!$E$7:$E$506,$N8)) | M8: =IF($L8="","",IFERROR(INDEX(코멘트!$F$5:$F$2004,MATCH(설정!$C$6&"|"&설정!$C$7&"|"&$L8,코멘트!$I$5:$I$2004,0)),"(미확인)")) | N8: =IFERROR(MATCH(LARGE(변동분석!$AB$7:$AB$506,A8),변동분석!$AB$7:$AB$506,0),"") | O8: =IF($N8="","",INDEX(변동분석!$K$7:$K$506,$N8)) | P8: =IF($N8="","",INDEX(변동분석!$M$7:$M$506,$N8)) | Q8: =IF($N8="","",INDEX(변동분석!$Q$7:$Q$506,$N8)) | R8: =IF($N8="","",INDEX(변동분석!$AY$7:$AY$506,$N8)) | S8: =IF($N8="","",INDEX(변동분석!$P$7:$P$506,$N8)) | T8: =IF($N8="","",INDEX(변동분석!$AP$7:$AP$506,$N8)) | U8: =IF($N8="","",INDEX(변동분석!$AQ$7:$AQ$506,$N8)) | V8: =IF($N8="","",INDEX(변동분석!$AR$7:$AR$506,$N8)) | W8: =IF($N8="","",INDEX(변동분석!$AS$7:$AS$506,$N8)) | X8: =IF($N8="","",INDEX(변동분석!$AT$7:$AT$506,$N8)) | Y8: =IF($N8="","",INDEX(변동분석!$AU$7:$AU$506,$N8)) | Z8: =IF($N8="","",INDEX(변동분석!$AV$7:$AV$506,$N8)) | AA8: =IF($N8="","",INDEX(월별집계!$AB$7:$AB$506,$N8)) | AB8: =IF($N8="","",INDEX(월별집계!$AC$7:$AC$506,$N8)) | AC8: =IF($N8="","",INDEX(월별집계!$AD$7:$AD$506,$N8)) | AD8: =IF($N8="","",INDEX(월별집계!$AE$7:$AE$506,$N8)) | AE8: =IF($N8="","",INDEX(월별집계!$AF$7:$AF$506,$N8)) | AF8: =IF($N8="","",INDEX(월별집계!$AG$7:$AG$506,$N8)) | AG8: =IF($N8="","",INDEX(월별집계!$AH$7:$AH$506,$N8)) | AH8: =IF($N8="","",INDEX(월별집계!$AI$7:$AI$506,$N8)) | AI8: =IF($N8="","",INDEX(월별집계!$AJ$7:$AJ$506,$N8)) | AJ8: =IF($N8="","",INDEX(월별집계!$AK$7:$AK$506,$N8)) | AK8: =IF($N8="","",INDEX(월별집계!$AL$7:$AL$506,$N8)) | AL8: =IF($N8="","",INDEX(월별집계!$AM$7:$AM$506,$N8)) | AM8: =IF($N8="","",INDEX(변동분석!$AZ$7:$AZ$506,$N8)) | AN8: =IF($N8="","",INDEX(변동분석!$F$7:$F$506,$N8)-INDEX(변동분석!$G$7:$G$506,$N8)) | AO8: =IF($N8="","",INDEX(변동분석!$K$7:$K$506,$N8)-INDEX(변동분석!$L$7:$L$506,$N8)) | AP8: =IF($N8="","",INDEX(변동분석!$Q$7:$Q$506,$N8)-INDEX(변동분석!$AX$7:$AX$506,$N8))
A9: 4 | B9: =IF($N9="","",INDEX(변동분석!$B$7:$B$506,$N9)) | C9: =IF($N9="","",INDEX(변동분석!$D$7:$D$506,$N9)) | D9: =IF($N9="","",INDEX(변동분석!$F$7:$F$506,$N9)) | E9: =IF($N9="","",INDEX(변동분석!$H$7:$H$506,$N9)) | F9: =IF($N9="","",INDEX(변동분석!$J$7:$J$506,$N9)) | G9: =IF($N9="","",INDEX(변동분석!$AO$7:$AO$506,$N9)) | H9: =IF($N9="","",INDEX(변동분석!$AN$7:$AN$506,$N9)) | I9: =IF($N9="","",INDEX(변동분석!$W$7:$W$506,$N9)) | J9: =IF($N9="","",INDEX(변동분석!$Z$7:$Z$506,$N9)) | K9: =IF($N9="","",INDEX(변동분석!$AA$7:$AA$506,$N9)) | L9: =IF($N9="","",INDEX(변동분석!$E$7:$E$506,$N9)) | M9: =IF($L9="","",IFERROR(INDEX(코멘트!$F$5:$F$2004,MATCH(설정!$C$6&"|"&설정!$C$7&"|"&$L9,코멘트!$I$5:$I$2004,0)),"(미확인)")) | N9: =IFERROR(MATCH(LARGE(변동분석!$AB$7:$AB$506,A9),변동분석!$AB$7:$AB$506,0),"") | O9: =IF($N9="","",INDEX(변동분석!$K$7:$K$506,$N9)) | P9: =IF($N9="","",INDEX(변동분석!$M$7:$M$506,$N9)) | Q9: =IF($N9="","",INDEX(변동분석!$Q$7:$Q$506,$N9)) | R9: =IF($N9="","",INDEX(변동분석!$AY$7:$AY$506,$N9)) | S9: =IF($N9="","",INDEX(변동분석!$P$7:$P$506,$N9)) | T9: =IF($N9="","",INDEX(변동분석!$AP$7:$AP$506,$N9)) | U9: =IF($N9="","",INDEX(변동분석!$AQ$7:$AQ$506,$N9)) | V9: =IF($N9="","",INDEX(변동분석!$AR$7:$AR$506,$N9)) | W9: =IF($N9="","",INDEX(변동분석!$AS$7:$AS$506,$N9)) | X9: =IF($N9="","",INDEX(변동분석!$AT$7:$AT$506,$N9)) | Y9: =IF($N9="","",INDEX(변동분석!$AU$7:$AU$506,$N9)) | Z9: =IF($N9="","",INDEX(변동분석!$AV$7:$AV$506,$N9)) | AA9: =IF($N9="","",INDEX(월별집계!$AB$7:$AB$506,$N9)) | AB9: =IF($N9="","",INDEX(월별집계!$AC$7:$AC$506,$N9)) | AC9: =IF($N9="","",INDEX(월별집계!$AD$7:$AD$506,$N9)) | AD9: =IF($N9="","",INDEX(월별집계!$AE$7:$AE$506,$N9)) | AE9: =IF($N9="","",INDEX(월별집계!$AF$7:$AF$506,$N9)) | AF9: =IF($N9="","",INDEX(월별집계!$AG$7:$AG$506,$N9)) | AG9: =IF($N9="","",INDEX(월별집계!$AH$7:$AH$506,$N9)) | AH9: =IF($N9="","",INDEX(월별집계!$AI$7:$AI$506,$N9)) | AI9: =IF($N9="","",INDEX(월별집계!$AJ$7:$AJ$506,$N9)) | AJ9: =IF($N9="","",INDEX(월별집계!$AK$7:$AK$506,$N9)) | AK9: =IF($N9="","",INDEX(월별집계!$AL$7:$AL$506,$N9)) | AL9: =IF($N9="","",INDEX(월별집계!$AM$7:$AM$506,$N9)) | AM9: =IF($N9="","",INDEX(변동분석!$AZ$7:$AZ$506,$N9)) | AN9: =IF($N9="","",INDEX(변동분석!$F$7:$F$506,$N9)-INDEX(변동분석!$G$7:$G$506,$N9)) | AO9: =IF($N9="","",INDEX(변동분석!$K$7:$K$506,$N9)-INDEX(변동분석!$L$7:$L$506,$N9)) | AP9: =IF($N9="","",INDEX(변동분석!$Q$7:$Q$506,$N9)-INDEX(변동분석!$AX$7:$AX$506,$N9))
A10: 5 | B10: =IF($N10="","",INDEX(변동분석!$B$7:$B$506,$N10)) | C10: =IF($N10="","",INDEX(변동분석!$D$7:$D$506,$N10)) | D10: =IF($N10="","",INDEX(변동분석!$F$7:$F$506,$N10)) | E10: =IF($N10="","",INDEX(변동분석!$H$7:$H$506,$N10)) | F10: =IF($N10="","",INDEX(변동분석!$J$7:$J$506,$N10)) | G10: =IF($N10="","",INDEX(변동분석!$AO$7:$AO$506,$N10)) | H10: =IF($N10="","",INDEX(변동분석!$AN$7:$AN$506,$N10)) | I10: =IF($N10="","",INDEX(변동분석!$W$7:$W$506,$N10)) | J10: =IF($N10="","",INDEX(변동분석!$Z$7:$Z$506,$N10)) | K10: =IF($N10="","",INDEX(변동분석!$AA$7:$AA$506,$N10)) | L10: =IF($N10="","",INDEX(변동분석!$E$7:$E$506,$N10)) | M10: =IF($L10="","",IFERROR(INDEX(코멘트!$F$5:$F$2004,MATCH(설정!$C$6&"|"&설정!$C$7&"|"&$L10,코멘트!$I$5:$I$2004,0)),"(미확인)")) | N10: =IFERROR(MATCH(LARGE(변동분석!$AB$7:$AB$506,A10),변동분석!$AB$7:$AB$506,0),"") | O10: =IF($N10="","",INDEX(변동분석!$K$7:$K$506,$N10)) | P10: =IF($N10="","",INDEX(변동분석!$M$7:$M$506,$N10)) | Q10: =IF($N10="","",INDEX(변동분석!$Q$7:$Q$506,$N10)) | R10: =IF($N10="","",INDEX(변동분석!$AY$7:$AY$506,$N10)) | S10: =IF($N10="","",INDEX(변동분석!$P$7:$P$506,$N10)) | T10: =IF($N10="","",INDEX(변동분석!$AP$7:$AP$506,$N10)) | U10: =IF($N10="","",INDEX(변동분석!$AQ$7:$AQ$506,$N10)) | V10: =IF($N10="","",INDEX(변동분석!$AR$7:$AR$506,$N10)) | W10: =IF($N10="","",INDEX(변동분석!$AS$7:$AS$506,$N10)) | X10: =IF($N10="","",INDEX(변동분석!$AT$7:$AT$506,$N10)) | Y10: =IF($N10="","",INDEX(변동분석!$AU$7:$AU$506,$N10)) | Z10: =IF($N10="","",INDEX(변동분석!$AV$7:$AV$506,$N10)) | AA10: =IF($N10="","",INDEX(월별집계!$AB$7:$AB$506,$N10)) | AB10: =IF($N10="","",INDEX(월별집계!$AC$7:$AC$506,$N10)) | AC10: =IF($N10="","",INDEX(월별집계!$AD$7:$AD$506,$N10)) | AD10: =IF($N10="","",INDEX(월별집계!$AE$7:$AE$506,$N10)) | AE10: =IF($N10="","",INDEX(월별집계!$AF$7:$AF$506,$N10)) | AF10: =IF($N10="","",INDEX(월별집계!$AG$7:$AG$506,$N10)) | AG10: =IF($N10="","",INDEX(월별집계!$AH$7:$AH$506,$N10)) | AH10: =IF($N10="","",INDEX(월별집계!$AI$7:$AI$506,$N10)) | AI10: =IF($N10="","",INDEX(월별집계!$AJ$7:$AJ$506,$N10)) | AJ10: =IF($N10="","",INDEX(월별집계!$AK$7:$AK$506,$N10)) | AK10: =IF($N10="","",INDEX(월별집계!$AL$7:$AL$506,$N10)) | AL10: =IF($N10="","",INDEX(월별집계!$AM$7:$AM$506,$N10)) | AM10: =IF($N10="","",INDEX(변동분석!$AZ$7:$AZ$506,$N10)) | AN10: =IF($N10="","",INDEX(변동분석!$F$7:$F$506,$N10)-INDEX(변동분석!$G$7:$G$506,$N10)) | AO10: =IF($N10="","",INDEX(변동분석!$K$7:$K$506,$N10)-INDEX(변동분석!$L$7:$L$506,$N10)) | AP10: =IF($N10="","",INDEX(변동분석!$Q$7:$Q$506,$N10)-INDEX(변동분석!$AX$7:$AX$506,$N10))
A11: 6 | B11: =IF($N11="","",INDEX(변동분석!$B$7:$B$506,$N11)) | C11: =IF($N11="","",INDEX(변동분석!$D$7:$D$506,$N11)) | D11: =IF($N11="","",INDEX(변동분석!$F$7:$F$506,$N11)) | E11: =IF($N11="","",INDEX(변동분석!$H$7:$H$506,$N11)) | F11: =IF($N11="","",INDEX(변동분석!$J$7:$J$506,$N11)) | G11: =IF($N11="","",INDEX(변동분석!$AO$7:$AO$506,$N11)) | H11: =IF($N11="","",INDEX(변동분석!$AN$7:$AN$506,$N11)) | I11: =IF($N11="","",INDEX(변동분석!$W$7:$W$506,$N11)) | J11: =IF($N11="","",INDEX(변동분석!$Z$7:$Z$506,$N11)) | K11: =IF($N11="","",INDEX(변동분석!$AA$7:$AA$506,$N11)) | L11: =IF($N11="","",INDEX(변동분석!$E$7:$E$506,$N11)) | M11: =IF($L11="","",IFERROR(INDEX(코멘트!$F$5:$F$2004,MATCH(설정!$C$6&"|"&설정!$C$7&"|"&$L11,코멘트!$I$5:$I$2004,0)),"(미확인)")) | N11: =IFERROR(MATCH(LARGE(변동분석!$AB$7:$AB$506,A11),변동분석!$AB$7:$AB$506,0),"") | O11: =IF($N11="","",INDEX(변동분석!$K$7:$K$506,$N11)) | P11: =IF($N11="","",INDEX(변동분석!$M$7:$M$506,$N11)) | Q11: =IF($N11="","",INDEX(변동분석!$Q$7:$Q$506,$N11)) | R11: =IF($N11="","",INDEX(변동분석!$AY$7:$AY$506,$N11)) | S11: =IF($N11="","",INDEX(변동분석!$P$7:$P$506,$N11)) | T11: =IF($N11="","",INDEX(변동분석!$AP$7:$AP$506,$N11)) | U11: =IF($N11="","",INDEX(변동분석!$AQ$7:$AQ$506,$N11)) | V11: =IF($N11="","",INDEX(변동분석!$AR$7:$AR$506,$N11)) | W11: =IF($N11="","",INDEX(변동분석!$AS$7:$AS$506,$N11)) | X11: =IF($N11="","",INDEX(변동분석!$AT$7:$AT$506,$N11)) | Y11: =IF($N11="","",INDEX(변동분석!$AU$7:$AU$506,$N11)) | Z11: =IF($N11="","",INDEX(변동분석!$AV$7:$AV$506,$N11)) | AA11: =IF($N11="","",INDEX(월별집계!$AB$7:$AB$506,$N11)) | AB11: =IF($N11="","",INDEX(월별집계!$AC$7:$AC$506,$N11)) | AC11: =IF($N11="","",INDEX(월별집계!$AD$7:$AD$506,$N11)) | AD11: =IF($N11="","",INDEX(월별집계!$AE$7:$AE$506,$N11)) | AE11: =IF($N11="","",INDEX(월별집계!$AF$7:$AF$506,$N11)) | AF11: =IF($N11="","",INDEX(월별집계!$AG$7:$AG$506,$N11)) | AG11: =IF($N11="","",INDEX(월별집계!$AH$7:$AH$506,$N11)) | AH11: =IF($N11="","",INDEX(월별집계!$AI$7:$AI$506,$N11)) | AI11: =IF($N11="","",INDEX(월별집계!$AJ$7:$AJ$506,$N11)) | AJ11: =IF($N11="","",INDEX(월별집계!$AK$7:$AK$506,$N11)) | AK11: =IF($N11="","",INDEX(월별집계!$AL$7:$AL$506,$N11)) | AL11: =IF($N11="","",INDEX(월별집계!$AM$7:$AM$506,$N11)) | AM11: =IF($N11="","",INDEX(변동분석!$AZ$7:$AZ$506,$N11)) | AN11: =IF($N11="","",INDEX(변동분석!$F$7:$F$506,$N11)-INDEX(변동분석!$G$7:$G$506,$N11)) | AO11: =IF($N11="","",INDEX(변동분석!$K$7:$K$506,$N11)-INDEX(변동분석!$L$7:$L$506,$N11)) | AP11: =IF($N11="","",INDEX(변동분석!$Q$7:$Q$506,$N11)-INDEX(변동분석!$AX$7:$AX$506,$N11))
A12: 7 | B12: =IF($N12="","",INDEX(변동분석!$B$7:$B$506,$N12)) | C12: =IF($N12="","",INDEX(변동분석!$D$7:$D$506,$N12)) | D12: =IF($N12="","",INDEX(변동분석!$F$7:$F$506,$N12)) | E12: =IF($N12="","",INDEX(변동분석!$H$7:$H$506,$N12)) | F12: =IF($N12="","",INDEX(변동분석!$J$7:$J$506,$N12)) | G12: =IF($N12="","",INDEX(변동분석!$AO$7:$AO$506,$N12)) | H12: =IF($N12="","",INDEX(변동분석!$AN$7:$AN$506,$N12)) | I12: =IF($N12="","",INDEX(변동분석!$W$7:$W$506,$N12)) | J12: =IF($N12="","",INDEX(변동분석!$Z$7:$Z$506,$N12)) | K12: =IF($N12="","",INDEX(변동분석!$AA$7:$AA$506,$N12)) | L12: =IF($N12="","",INDEX(변동분석!$E$7:$E$506,$N12)) | M12: =IF($L12="","",IFERROR(INDEX(코멘트!$F$5:$F$2004,MATCH(설정!$C$6&"|"&설정!$C$7&"|"&$L12,코멘트!$I$5:$I$2004,0)),"(미확인)")) | N12: =IFERROR(MATCH(LARGE(변동분석!$AB$7:$AB$506,A12),변동분석!$AB$7:$AB$506,0),"") | O12: =IF($N12="","",INDEX(변동분석!$K$7:$K$506,$N12)) | P12: =IF($N12="","",INDEX(변동분석!$M$7:$M$506,$N12)) | Q12: =IF($N12="","",INDEX(변동분석!$Q$7:$Q$506,$N12)) | R12: =IF($N12="","",INDEX(변동분석!$AY$7:$AY$506,$N12)) | S12: =IF($N12="","",INDEX(변동분석!$P$7:$P$506,$N12)) | T12: =IF($N12="","",INDEX(변동분석!$AP$7:$AP$506,$N12)) | U12: =IF($N12="","",INDEX(변동분석!$AQ$7:$AQ$506,$N12)) | V12: =IF($N12="","",INDEX(변동분석!$AR$7:$AR$506,$N12)) | W12: =IF($N12="","",INDEX(변동분석!$AS$7:$AS$506,$N12)) | X12: =IF($N12="","",INDEX(변동분석!$AT$7:$AT$506,$N12)) | Y12: =IF($N12="","",INDEX(변동분석!$AU$7:$AU$506,$N12)) | Z12: =IF($N12="","",INDEX(변동분석!$AV$7:$AV$506,$N12)) | AA12: =IF($N12="","",INDEX(월별집계!$AB$7:$AB$506,$N12)) | AB12: =IF($N12="","",INDEX(월별집계!$AC$7:$AC$506,$N12)) | AC12: =IF($N12="","",INDEX(월별집계!$AD$7:$AD$506,$N12)) | AD12: =IF($N12="","",INDEX(월별집계!$AE$7:$AE$506,$N12)) | AE12: =IF($N12="","",INDEX(월별집계!$AF$7:$AF$506,$N12)) | AF12: =IF($N12="","",INDEX(월별집계!$AG$7:$AG$506,$N12)) | AG12: =IF($N12="","",INDEX(월별집계!$AH$7:$AH$506,$N12)) | AH12: =IF($N12="","",INDEX(월별집계!$AI$7:$AI$506,$N12)) | AI12: =IF($N12="","",INDEX(월별집계!$AJ$7:$AJ$506,$N12)) | AJ12: =IF($N12="","",INDEX(월별집계!$AK$7:$AK$506,$N12)) | AK12: =IF($N12="","",INDEX(월별집계!$AL$7:$AL$506,$N12)) | AL12: =IF($N12="","",INDEX(월별집계!$AM$7:$AM$506,$N12)) | AM12: =IF($N12="","",INDEX(변동분석!$AZ$7:$AZ$506,$N12)) | AN12: =IF($N12="","",INDEX(변동분석!$F$7:$F$506,$N12)-INDEX(변동분석!$G$7:$G$506,$N12)) | AO12: =IF($N12="","",INDEX(변동분석!$K$7:$K$506,$N12)-INDEX(변동분석!$L$7:$L$506,$N12)) | AP12: =IF($N12="","",INDEX(변동분석!$Q$7:$Q$506,$N12)-INDEX(변동분석!$AX$7:$AX$506,$N12))
A13: 8 | B13: =IF($N13="","",INDEX(변동분석!$B$7:$B$506,$N13)) | C13: =IF($N13="","",INDEX(변동분석!$D$7:$D$506,$N13)) | D13: =IF($N13="","",INDEX(변동분석!$F$7:$F$506,$N13)) | E13: =IF($N13="","",INDEX(변동분석!$H$7:$H$506,$N13)) | F13: =IF($N13="","",INDEX(변동분석!$J$7:$J$506,$N13)) | G13: =IF($N13="","",INDEX(변동분석!$AO$7:$AO$506,$N13)) | H13: =IF($N13="","",INDEX(변동분석!$AN$7:$AN$506,$N13)) | I13: =IF($N13="","",INDEX(변동분석!$W$7:$W$506,$N13)) | J13: =IF($N13="","",INDEX(변동분석!$Z$7:$Z$506,$N13)) | K13: =IF($N13="","",INDEX(변동분석!$AA$7:$AA$506,$N13)) | L13: =IF($N13="","",INDEX(변동분석!$E$7:$E$506,$N13)) | M13: =IF($L13="","",IFERROR(INDEX(코멘트!$F$5:$F$2004,MATCH(설정!$C$6&"|"&설정!$C$7&"|"&$L13,코멘트!$I$5:$I$2004,0)),"(미확인)")) | N13: =IFERROR(MATCH(LARGE(변동분석!$AB$7:$AB$506,A13),변동분석!$AB$7:$AB$506,0),"") | O13: =IF($N13="","",INDEX(변동분석!$K$7:$K$506,$N13)) | P13: =IF($N13="","",INDEX(변동분석!$M$7:$M$506,$N13)) | Q13: =IF($N13="","",INDEX(변동분석!$Q$7:$Q$506,$N13)) | R13: =IF($N13="","",INDEX(변동분석!$AY$7:$AY$506,$N13)) | S13: =IF($N13="","",INDEX(변동분석!$P$7:$P$506,$N13)) | T13: =IF($N13="","",INDEX(변동분석!$AP$7:$AP$506,$N13)) | U13: =IF($N13="","",INDEX(변동분석!$AQ$7:$AQ$506,$N13)) | V13: =IF($N13="","",INDEX(변동분석!$AR$7:$AR$506,$N13)) | W13: =IF($N13="","",INDEX(변동분석!$AS$7:$AS$506,$N13)) | X13: =IF($N13="","",INDEX(변동분석!$AT$7:$AT$506,$N13)) | Y13: =IF($N13="","",INDEX(변동분석!$AU$7:$AU$506,$N13)) | Z13: =IF($N13="","",INDEX(변동분석!$AV$7:$AV$506,$N13)) | AA13: =IF($N13="","",INDEX(월별집계!$AB$7:$AB$506,$N13)) | AB13: =IF($N13="","",INDEX(월별집계!$AC$7:$AC$506,$N13)) | AC13: =IF($N13="","",INDEX(월별집계!$AD$7:$AD$506,$N13)) | AD13: =IF($N13="","",INDEX(월별집계!$AE$7:$AE$506,$N13)) | AE13: =IF($N13="","",INDEX(월별집계!$AF$7:$AF$506,$N13)) | AF13: =IF($N13="","",INDEX(월별집계!$AG$7:$AG$506,$N13)) | AG13: =IF($N13="","",INDEX(월별집계!$AH$7:$AH$506,$N13)) | AH13: =IF($N13="","",INDEX(월별집계!$AI$7:$AI$506,$N13)) | AI13: =IF($N13="","",INDEX(월별집계!$AJ$7:$AJ$506,$N13)) | AJ13: =IF($N13="","",INDEX(월별집계!$AK$7:$AK$506,$N13)) | AK13: =IF($N13="","",INDEX(월별집계!$AL$7:$AL$506,$N13)) | AL13: =IF($N13="","",INDEX(월별집계!$AM$7:$AM$506,$N13)) | AM13: =IF($N13="","",INDEX(변동분석!$AZ$7:$AZ$506,$N13)) | AN13: =IF($N13="","",INDEX(변동분석!$F$7:$F$506,$N13)-INDEX(변동분석!$G$7:$G$506,$N13)) | AO13: =IF($N13="","",INDEX(변동분석!$K$7:$K$506,$N13)-INDEX(변동분석!$L$7:$L$506,$N13)) | AP13: =IF($N13="","",INDEX(변동분석!$Q$7:$Q$506,$N13)-INDEX(변동분석!$AX$7:$AX$506,$N13))
A14: 9 | B14: =IF($N14="","",INDEX(변동분석!$B$7:$B$506,$N14)) | C14: =IF($N14="","",INDEX(변동분석!$D$7:$D$506,$N14)) | D14: =IF($N14="","",INDEX(변동분석!$F$7:$F$506,$N14)) | E14: =IF($N14="","",INDEX(변동분석!$H$7:$H$506,$N14)) | F14: =IF($N14="","",INDEX(변동분석!$J$7:$J$506,$N14)) | G14: =IF($N14="","",INDEX(변동분석!$AO$7:$AO$506,$N14)) | H14: =IF($N14="","",INDEX(변동분석!$AN$7:$AN$506,$N14)) | I14: =IF($N14="","",INDEX(변동분석!$W$7:$W$506,$N14)) | J14: =IF($N14="","",INDEX(변동분석!$Z$7:$Z$506,$N14)) | K14: =IF($N14="","",INDEX(변동분석!$AA$7:$AA$506,$N14)) | L14: =IF($N14="","",INDEX(변동분석!$E$7:$E$506,$N14)) | M14: =IF($L14="","",IFERROR(INDEX(코멘트!$F$5:$F$2004,MATCH(설정!$C$6&"|"&설정!$C$7&"|"&$L14,코멘트!$I$5:$I$2004,0)),"(미확인)")) | N14: =IFERROR(MATCH(LARGE(변동분석!$AB$7:$AB$506,A14),변동분석!$AB$7:$AB$506,0),"") | O14: =IF($N14="","",INDEX(변동분석!$K$7:$K$506,$N14)) | P14: =IF($N14="","",INDEX(변동분석!$M$7:$M$506,$N14)) | Q14: =IF($N14="","",INDEX(변동분석!$Q$7:$Q$506,$N14)) | R14: =IF($N14="","",INDEX(변동분석!$AY$7:$AY$506,$N14)) | S14: =IF($N14="","",INDEX(변동분석!$P$7:$P$506,$N14)) | T14: =IF($N14="","",INDEX(변동분석!$AP$7:$AP$506,$N14)) | U14: =IF($N14="","",INDEX(변동분석!$AQ$7:$AQ$506,$N14)) | V14: =IF($N14="","",INDEX(변동분석!$AR$7:$AR$506,$N14)) | W14: =IF($N14="","",INDEX(변동분석!$AS$7:$AS$506,$N14)) | X14: =IF($N14="","",INDEX(변동분석!$AT$7:$AT$506,$N14)) | Y14: =IF($N14="","",INDEX(변동분석!$AU$7:$AU$506,$N14)) | Z14: =IF($N14="","",INDEX(변동분석!$AV$7:$AV$506,$N14)) | AA14: =IF($N14="","",INDEX(월별집계!$AB$7:$AB$506,$N14)) | AB14: =IF($N14="","",INDEX(월별집계!$AC$7:$AC$506,$N14)) | AC14: =IF($N14="","",INDEX(월별집계!$AD$7:$AD$506,$N14)) | AD14: =IF($N14="","",INDEX(월별집계!$AE$7:$AE$506,$N14)) | AE14: =IF($N14="","",INDEX(월별집계!$AF$7:$AF$506,$N14)) | AF14: =IF($N14="","",INDEX(월별집계!$AG$7:$AG$506,$N14)) | AG14: =IF($N14="","",INDEX(월별집계!$AH$7:$AH$506,$N14)) | AH14: =IF($N14="","",INDEX(월별집계!$AI$7:$AI$506,$N14)) | AI14: =IF($N14="","",INDEX(월별집계!$AJ$7:$AJ$506,$N14)) | AJ14: =IF($N14="","",INDEX(월별집계!$AK$7:$AK$506,$N14)) | AK14: =IF($N14="","",INDEX(월별집계!$AL$7:$AL$506,$N14)) | AL14: =IF($N14="","",INDEX(월별집계!$AM$7:$AM$506,$N14)) | AM14: =IF($N14="","",INDEX(변동분석!$AZ$7:$AZ$506,$N14)) | AN14: =IF($N14="","",INDEX(변동분석!$F$7:$F$506,$N14)-INDEX(변동분석!$G$7:$G$506,$N14)) | AO14: =IF($N14="","",INDEX(변동분석!$K$7:$K$506,$N14)-INDEX(변동분석!$L$7:$L$506,$N14)) | AP14: =IF($N14="","",INDEX(변동분석!$Q$7:$Q$506,$N14)-INDEX(변동분석!$AX$7:$AX$506,$N14))
A15: 10 | B15: =IF($N15="","",INDEX(변동분석!$B$7:$B$506,$N15)) | C15: =IF($N15="","",INDEX(변동분석!$D$7:$D$506,$N15)) | D15: =IF($N15="","",INDEX(변동분석!$F$7:$F$506,$N15)) | E15: =IF($N15="","",INDEX(변동분석!$H$7:$H$506,$N15)) | F15: =IF($N15="","",INDEX(변동분석!$J$7:$J$506,$N15)) | G15: =IF($N15="","",INDEX(변동분석!$AO$7:$AO$506,$N15)) | H15: =IF($N15="","",INDEX(변동분석!$AN$7:$AN$506,$N15)) | I15: =IF($N15="","",INDEX(변동분석!$W$7:$W$506,$N15)) | J15: =IF($N15="","",INDEX(변동분석!$Z$7:$Z$506,$N15)) | K15: =IF($N15="","",INDEX(변동분석!$AA$7:$AA$506,$N15)) | L15: =IF($N15="","",INDEX(변동분석!$E$7:$E$506,$N15)) | M15: =IF($L15="","",IFERROR(INDEX(코멘트!$F$5:$F$2004,MATCH(설정!$C$6&"|"&설정!$C$7&"|"&$L15,코멘트!$I$5:$I$2004,0)),"(미확인)")) | N15: =IFERROR(MATCH(LARGE(변동분석!$AB$7:$AB$506,A15),변동분석!$AB$7:$AB$506,0),"") | O15: =IF($N15="","",INDEX(변동분석!$K$7:$K$506,$N15)) | P15: =IF($N15="","",INDEX(변동분석!$M$7:$M$506,$N15)) | Q15: =IF($N15="","",INDEX(변동분석!$Q$7:$Q$506,$N15)) | R15: =IF($N15="","",INDEX(변동분석!$AY$7:$AY$506,$N15)) | S15: =IF($N15="","",INDEX(변동분석!$P$7:$P$506,$N15)) | T15: =IF($N15="","",INDEX(변동분석!$AP$7:$AP$506,$N15)) | U15: =IF($N15="","",INDEX(변동분석!$AQ$7:$AQ$506,$N15)) | V15: =IF($N15="","",INDEX(변동분석!$AR$7:$AR$506,$N15)) | W15: =IF($N15="","",INDEX(변동분석!$AS$7:$AS$506,$N15)) | X15: =IF($N15="","",INDEX(변동분석!$AT$7:$AT$506,$N15)) | Y15: =IF($N15="","",INDEX(변동분석!$AU$7:$AU$506,$N15)) | Z15: =IF($N15="","",INDEX(변동분석!$AV$7:$AV$506,$N15)) | AA15: =IF($N15="","",INDEX(월별집계!$AB$7:$AB$506,$N15)) | AB15: =IF($N15="","",INDEX(월별집계!$AC$7:$AC$506,$N15)) | AC15: =IF($N15="","",INDEX(월별집계!$AD$7:$AD$506,$N15)) | AD15: =IF($N15="","",INDEX(월별집계!$AE$7:$AE$506,$N15)) | AE15: =IF($N15="","",INDEX(월별집계!$AF$7:$AF$506,$N15)) | AF15: =IF($N15="","",INDEX(월별집계!$AG$7:$AG$506,$N15)) | AG15: =IF($N15="","",INDEX(월별집계!$AH$7:$AH$506,$N15)) | AH15: =IF($N15="","",INDEX(월별집계!$AI$7:$AI$506,$N15)) | AI15: =IF($N15="","",INDEX(월별집계!$AJ$7:$AJ$506,$N15)) | AJ15: =IF($N15="","",INDEX(월별집계!$AK$7:$AK$506,$N15)) | AK15: =IF($N15="","",INDEX(월별집계!$AL$7:$AL$506,$N15)) | AL15: =IF($N15="","",INDEX(월별집계!$AM$7:$AM$506,$N15)) | AM15: =IF($N15="","",INDEX(변동분석!$AZ$7:$AZ$506,$N15)) | AN15: =IF($N15="","",INDEX(변동분석!$F$7:$F$506,$N15)-INDEX(변동분석!$G$7:$G$506,$N15)) | AO15: =IF($N15="","",INDEX(변동분석!$K$7:$K$506,$N15)-INDEX(변동분석!$L$7:$L$506,$N15)) | AP15: =IF($N15="","",INDEX(변동분석!$Q$7:$Q$506,$N15)-INDEX(변동분석!$AX$7:$AX$506,$N15))

Sheet 원인분석
A1: TRACE · 원인분석 (한 항목씩)
A2: C5~C8만 입력 · 선택 항목의 증가분을 거래처·전표로 쪼개고 8가지 패턴으로 원인 후보를 만듭니다 · 금액: 보고단위
B5: 주의대상 순위 | C5: 1 | D5: 1~10 | E5: 선택 항목
B6: 비교 기준 | C6: 전월 | D6: 전월 / 전분기 / 전년동기누적 / 전년동월 | E6: =IF($C$9="","(선택 없음)",IFERROR(INDEX(부서매핑!$D$5:$D$504,MATCH(LEFT($C$9,FIND("|",$C$9)-1),부서매핑!$C$5:$C$504,0)),LEFT($C$9,FIND("|",$C$9)-1))&" · "&IFERROR(INDEX(계정매핑!$B$5:$B$504,MATCH(MID($C$9,FIND("|",$C$9)+1,20),계정매핑!$A$5:$A$504,0)),MID($C$9,FIND("|",$C$9)+1,20)))
B7: 직접 지정: 부서코드 | D7: 비워두면 순위 사용 | E7: ="당기 "&INT(($C$10-1)/12)&"-"&TEXT(MOD($C$10-1,12)+1,"00")&IF($C$10<>$C$11," ~ "&INT(($C$11-1)/12)&"-"&TEXT(MOD($C$11-1,12)+1,"00"),"")&" vs 비교 "&INT(($C$12-1)/12)&"-"&TEXT(MOD($C$12-1,12)+1,"00")&IF($C$12<>$C$13," ~ "&INT(($C$13-1)/12)&"-"&TEXT(MOD($C$13-1,12)+1,"00"),"")
B8: 직접 지정: G/L 계정 | D8: 부서코드와 함께 입력
B9: (계산) 선택 키 | C9: =IF(AND(C7<>"",C8<>""),C7&"|"&C8,IFERROR(INDEX(주의대상!$L$6:$L$15,C5),"")) | E9: =E6&" ("&C6&" 대비)"
B10: (계산) 당기 시작 | C10: =IF(C6="전분기",설정!$C$22,IF(C6="전년동기누적",설정!$C$6*12+1,설정!$C$20))
B11: (계산) 당기 끝 | C11: =설정!$C$20
B12: (계산) 비교 시작 | C12: =IF(C6="전월",설정!$C$20-1,IF(C6="전년동월",설정!$C$20-12,IF(C6="전년동기누적",(설정!$C$6-1)*12+1,설정!$C$22-3)))
B13: (계산) 비교 끝 | C13: =IF(C6="전월",설정!$C$20-1,IF(C6="전년동월",설정!$C$20-12,IF(C6="전년동기누적",설정!$C$20-12,설정!$C$20-3)))
A15: 당기 합계 | B15: 비교 합계 | C15: 증감 | D15: 증감률 | E15: 분기 판정 | F15: 연간 부족 예상액 (추세 연말) | G15: 고갈 예상일 (추세)
A16: =SUMIFS(전표_원본!$P$5:$P$100000,전표_원본!$Q$5:$Q$100000,"당기") | B16: =SUMIFS(전표_원본!$P$5:$P$100000,전표_원본!$Q$5:$Q$100000,"비교") | C16: =A16-B16 | D16: =IF(B16<=0,IF(A16>0,1,0),A16/B16-1) | E16: =IFERROR(INDEX(변동분석!$AO$7:$AO$506,MATCH($C$9,변동분석!$E$7:$E$506,0)),"-") | F16: =IFERROR(IF(INDEX(변동분석!$P$7:$P$506,MATCH($C$9,변동분석!$E$7:$E$506,0))<=0,0,MAX(0,INDEX(변동분석!$AR$7:$AR$506,MATCH($C$9,변동분석!$E$7:$E$506,0))-INDEX(변동분석!$P$7:$P$506,MATCH($C$9,변동분석!$E$7:$E$506,0)))),0) | G16: =IFERROR(INDEX(변동분석!$AT$7:$AT$506,MATCH($C$9,변동분석!$E$7:$E$506,0)),"")
A18: =IF($C$9="","선택된 항목이 없습니다.",$E$6&" "&$C$6&" 대비 "&TEXT($C$16,"+#,##0.0;-#,##0.0;0")&" ("&TEXT($D$16,"+0%;-0%;0%")&"). "&IF($C$16<=0,"감소 또는 변동 없음 - 원인 후보는 증가 항목에만 만듭니다. ",$D$21&". ")&"분기 한도: "&$E$16&IF($G$16="소진됨",", 연간 예산 이미 소진",IF(N($F$16)>0,", 연간 "&TEXT($F$16,"#,##0.0")&" 부족 예상 ("&$G$16&" 고갈)",""))&".")
A19: 원인 후보 (근거 강도 순) | N19: 패턴 | O19: 해당 | P19: 강도 | Q19: 강도점수 | R19: 비중 | S19: 문장 | T19: 정렬키 | Y19: 보조값 | Z19: 값
A20: 순위 | B20: 패턴 | C20: 근거 강도 | D20: 설명 (근거 포함) | N20: 일회성 대형 지출 | O20: =IF(OR(Z20="",$C$16<=0),"N",IF(AND(Z21>0,Z21/$C$16>=설정!$C$14,LEFT(Z24,1)<>"(",Z21>=3*Z45),"Y","N")) | P20: 높음 | Q20: 3 | R20: =IF(O20="Y",MIN(1,Z21/$C$16),0) | S20: =IF(O20="Y","전표 "&Z22&" ("&TEXT(Z23,"m/d")&", "&Z24&", 적요 '"&Z25&"') "&TEXT(Z21,"#,##0.0")&"이 증가분의 "&TEXT(R20,"0%")&" (거래처 평소 월평균 "&TEXT(Z45,"#,##0.0")&"). 일회성 지출 가능성","") | T20: =IF(O20="Y",Q20*10+R20+ROW()/1000000,-1) | Y20: 최대 단건 위치 | Z20: =IFERROR(MATCH(LARGE(전표_원본!$T$5:$T$100000,1),전표_원본!$T$5:$T$100000,0),"")
A21: 1 | B21: =IF($K21="",IF(1=1,"뚜렷한 패턴 없음",""),INDEX($N$20:$N$27,$K21)) | C21: =IF($K21="","",INDEX($P$20:$P$27,$K21)) | D21: =IF($K21="",IF(1=1,"근거 전표 목록을 직접 확인하세요",""),INDEX($S$20:$S$27,$K21)) | K21: =IF(LARGE($T$20:$T$27,1)<0,"",MATCH(LARGE($T$20:$T$27,1),$T$20:$T$27,0)) | N21: 신규 거래처 | O21: =IF($C$16<=0,"N",IF(Z42/$C$16>=설정!$C$15,"Y","N")) | P21: 중간 | Q21: 2 | R21: =IF(O21="Y",MIN(1,Z42/$C$16),0) | S21: =IF(O21="Y","최근 12개월 거래가 없던 거래처("&Z44&IF(Z43>1," 등 "&Z43&"곳","")&")가 증가분의 "&TEXT(R21,"0%")&". 신규 계약·거래 개시 가능성","") | T21: =IF(O21="Y",Q21*10+R21+ROW()/1000000,-1) | Y21: 최대 단건 금액 | Z21: =IF(Z20="","",INDEX(전표_원본!$P$5:$P$100000,Z20))
A22: 2 | B22: =IF($K22="",IF(2=1,"뚜렷한 패턴 없음",""),INDEX($N$20:$N$27,$K22)) | C22: =IF($K22="","",INDEX($P$20:$P$27,$K22)) | D22: =IF($K22="",IF(2=1,"근거 전표 목록을 직접 확인하세요",""),INDEX($S$20:$S$27,$K22)) | K22: =IF(LARGE($T$20:$T$27,2)<0,"",MATCH(LARGE($T$20:$T$27,2),$T$20:$T$27,0)) | N22: 단가 인상 | O22: =IF(OR($C$16<=0,$A$32=""),"N",IF(AND($I$32="N",$F$32=$G$32,$G$32>0,$C$32>0),IF(AND($D$32/$C$32>=설정!$C$18,$D$32/$C$32<=0.5),"Y","N"),"N")) | P22: 중간 | Q22: 2 | R22: =IF(O22="Y",MIN(1,$D$32/$C$16),0) | S22: =IF(O22="Y","같은 건수("&$F$32&"건)로 "&$A$32&" 금액이 "&TEXT(IF($C$32>0,$D$32/$C$32,0),"0%")&" 상승. 단가·계약 조건 변경 가능성 (최근 몇 달 추이 확인)","") | T22: =IF(O22="Y",Q22*10+R22+ROW()/1000000,-1) | Y22: 전표번호 | Z22: =IF(Z20="","",INDEX(전표_원본!$C$5:$C$100000,Z20))
A23: 3 | B23: =IF($K23="",IF(3=1,"뚜렷한 패턴 없음",""),INDEX($N$20:$N$27,$K23)) | C23: =IF($K23="","",INDEX($P$20:$P$27,$K23)) | D23: =IF($K23="",IF(3=1,"근거 전표 목록을 직접 확인하세요",""),INDEX($S$20:$S$27,$K23)) | K23: =IF(LARGE($T$20:$T$27,3)<0,"",MATCH(LARGE($T$20:$T$27,3),$T$20:$T$27,0)) | N23: 계상 시점 이동 | O23: =IF(AND(Z29>0,Z28<0.5*Z29,Z27>1.5*Z29),"Y","N") | P23: 중간 | Q23: 2 | R23: =IF(O23="Y",0.5,0) | S23: =IF(O23="Y","전월 "&TEXT(Z28,"#,##0.0")&" (직전 3개월 평균 "&TEXT(Z29,"#,##0.0")&") → 당월 "&TEXT(Z27,"#,##0.0")&". 전월에 계상될 금액이 당월로 넘어왔을 가능성","") | T23: =IF(O23="Y",Q23*10+R23+ROW()/1000000,-1) | Y23: 전기일 | Z23: =IF(Z20="","",INDEX(전표_원본!$D$5:$D$100000,Z20))
A24: 4 | B24: =IF($K24="",IF(4=1,"뚜렷한 패턴 없음",""),INDEX($N$20:$N$27,$K24)) | C24: =IF($K24="","",INDEX($P$20:$P$27,$K24)) | D24: =IF($K24="",IF(4=1,"근거 전표 목록을 직접 확인하세요",""),INDEX($S$20:$S$27,$K24)) | K24: =IF(LARGE($T$20:$T$27,4)<0,"",MATCH(LARGE($T$20:$T$27,4),$T$20:$T$27,0)) | N24: 정정 · 역분개 | O24: =IF(Z30>0,"Y","N") | P24: 높음 | Q24: 3 | R24: =IF(O24="Y",MIN(1,ABS(Z31)/MAX(ABS($C$16),0.000001)),0) | S24: =IF(O24="Y","음수(정정·역분개) 전표 "&Z30&"건, 합계 "&TEXT(Z31,"#,##0.0")&". 정정 전후 순액 기준으로 다시 확인","") | T24: =IF(O24="Y",Q24*10+R24+ROW()/1000000,-1) | Y24: 거래처 | Z24: =IF(Z20="","",INDEX(전표_원본!$K$5:$K$100000,Z20))
A25: 5 | B25: =IF($K25="",IF(5=1,"뚜렷한 패턴 없음",""),INDEX($N$20:$N$27,$K25)) | C25: =IF($K25="","",INDEX($P$20:$P$27,$K25)) | D25: =IF($K25="",IF(5=1,"근거 전표 목록을 직접 확인하세요",""),INDEX($S$20:$S$27,$K25)) | K25: =IF(LARGE($T$20:$T$27,5)<0,"",MATCH(LARGE($T$20:$T$27,5),$T$20:$T$27,0)) | N25: 재분류 (수기 대체) | O25: =IF($C$16<=0,"N",IF(Z32/$C$16>=설정!$C$16,"Y","N")) | P25: 높음 | Q25: 3 | R25: =IF(O25="Y",MIN(1,Z32/$C$16),0) | S25: =IF(O25="Y","수기 대체전표(SA) 순증 "&TEXT(Z32,"#,##0.0")&"이 증가분의 "&TEXT(R25,"0%")&". 다른 부서·계정에서 이관됐을 가능성 (적요: '"&Z33&"')","") | T25: =IF(O25="Y",Q25*10+R25+ROW()/1000000,-1) | Y25: 적요 | Z25: =IF(Z20="","",INDEX(전표_원본!$I$5:$I$100000,Z20))
A26: 6 | B26: =IF($K26="",IF(6=1,"뚜렷한 패턴 없음",""),INDEX($N$20:$N$27,$K26)) | C26: =IF($K26="","",INDEX($P$20:$P$27,$K26)) | D26: =IF($K26="",IF(6=1,"근거 전표 목록을 직접 확인하세요",""),INDEX($S$20:$S$27,$K26)) | K26: =IF(LARGE($T$20:$T$27,6)<0,"",MATCH(LARGE($T$20:$T$27,6),$T$20:$T$27,0)) | N26: 적요 키워드 | O26: =IF(OR($C$16<=0,Z35=""),"N",IF(Z34>=설정!$C$17,"Y","N")) | P26: 중간 | Q26: 2 | R26: =IF(O26="Y",MIN(1,Z34),0) | S26: =IF(O26="Y",IF(Z35="","",INDEX(키워드사전!$A$5:$A$19,Z35)&": 적요에 '"&INDEX(키워드사전!$B$5:$B$19,Z35)&IF(INDEX(키워드사전!$C$5:$C$19,Z35)<>"","·"&INDEX(키워드사전!$C$5:$C$19,Z35),"")&IF(INDEX(키워드사전!$D$5:$D$19,Z35)<>"","·"&INDEX(키워드사전!$D$5:$D$19,Z35),"")&"' 등이 있는 전표 "&TEXT(INDEX(키워드사전!$H$5:$H$19,Z35),"#,##0.0")&" (증가분의 "&TEXT(Z34,"0%")&"). "&INDEX(키워드사전!$G$5:$G$19,Z35)),"") | T26: =IF(O26="Y",Q26*10+R26+ROW()/1000000,-1) | Y26: 월별집계 행 | Z26: =IFERROR(MATCH($C$9,월별집계!$A$7:$A$506,0),"")
A27: 7 | B27: =IF($K27="",IF(7=1,"뚜렷한 패턴 없음",""),INDEX($N$20:$N$27,$K27)) | C27: =IF($K27="","",INDEX($P$20:$P$27,$K27)) | D27: =IF($K27="",IF(7=1,"근거 전표 목록을 직접 확인하세요",""),INDEX($S$20:$S$27,$K27)) | K27: =IF(LARGE($T$20:$T$27,7)<0,"",MATCH(LARGE($T$20:$T$27,7),$T$20:$T$27,0)) | N27: 물량 vs 단가 | O27: =IF(AND($C$16>0,Z36>0,Z37>0),"Y","N") | P27: 참고 | Q27: 1 | R27: =0 | S27: =IF(O27="Y","건수 "&Z37&"→"&Z36&" ("&TEXT(Z36/MAX(Z37,1)-1,"+0%;-0%;0%")&"), 건당 "&TEXT(Z41,"#,##0.0")&"→"&TEXT(Z40,"#,##0.0")&". "&IF(ABS((Z36-Z37)*Z41)>=ABS((Z40-Z41)*Z36),"건수(물량) 증가","건당 금액(단가) 상승")&" 영향이 더 큼","") | T27: =IF(O27="Y",Q27*10+R27+ROW()/1000000,-1) | Y27: 당월 (기준월) | Z27: =IF(Z26="",0,INDEX(월별집계!$Z$7:$Z$506,Z26))
A28: 8 | B28: =IF($K28="",IF(8=1,"뚜렷한 패턴 없음",""),INDEX($N$20:$N$27,$K28)) | C28: =IF($K28="","",INDEX($P$20:$P$27,$K28)) | D28: =IF($K28="",IF(8=1,"근거 전표 목록을 직접 확인하세요",""),INDEX($S$20:$S$27,$K28)) | K28: =IF(LARGE($T$20:$T$27,8)<0,"",MATCH(LARGE($T$20:$T$27,8),$T$20:$T$27,0)) | Y28: 전월 | Z28: =IF(Z26="",0,INDEX(월별집계!$Y$7:$Y$506,Z26))
Y29: 직전3개월 평균 (전월 제외) | Z29: =IF(Z26="",0,(INDEX(월별집계!$V$7:$V$506,Z26)+INDEX(월별집계!$W$7:$W$506,Z26)+INDEX(월별집계!$X$7:$X$506,Z26))/3)
A30: 거래처별 증감 분해 (증가 큰 순) | Y30: 음수 전표 건수 | Z30: =COUNTIFS(전표_원본!$Q$5:$Q$100000,"당기",전표_원본!$P$5:$P$100000,"<0")
A31: 거래처 | B31: 당기 | C31: 비교 | D31: 증감 | E31: 증가분 기여율 | F31: 당기 건수 | G31: 비교 건수 | H31: 당기 최대 단건 | I31: 신규 거래처 | N31: 첫등장행 | O31: 거래처 | P31: 당기 | Q31: 비교 | R31: 증감 | S31: 당기건수 | T31: 비교건수 | U31: 최대단건 | V31: 신규 | W31: 정렬키 | Y31: 음수 전표 합계 | Z31: =SUMIFS(전표_원본!$P$5:$P$100000,전표_원본!$Q$5:$Q$100000,"당기",전표_원본!$P$5:$P$100000,"<0")
A32: =IF($K32="","",INDEX($O$32:$O$46,$K32)) | B32: =IF($K32="","",INDEX($P$32:$P$46,$K32)) | C32: =IF($K32="","",INDEX($Q$32:$Q$46,$K32)) | D32: =IF($K32="","",INDEX($R$32:$R$46,$K32)) | E32: =IF(OR($K32="",$C$16<=0),"",D32/$C$16) | F32: =IF($K32="","",INDEX($S$32:$S$46,$K32)) | G32: =IF($K32="","",INDEX($T$32:$T$46,$K32)) | H32: =IF($K32="","",INDEX($U$32:$U$46,$K32)) | I32: =IF($K32="","",INDEX($V$32:$V$46,$K32)) | K32: =IF(COUNT($W$32:$W$46)<1,"",MATCH(LARGE($W$32:$W$46,1),$W$32:$W$46,0)) | N32: =IFERROR(SMALL(전표_원본!$S$5:$S$100000,1),"") | O32: =IF(N32="","",INDEX(전표_원본!$K$1:$K$100000,N32)) | P32: =IF(O32="","",SUMIFS(전표_원본!$P$5:$P$100000,전표_원본!$Q$5:$Q$100000,"당기",전표_원본!$R$5:$R$100000,O32)) | Q32: =IF(O32="","",SUMIFS(전표_원본!$P$5:$P$100000,전표_원본!$Q$5:$Q$100000,"비교",전표_원본!$R$5:$R$100000,O32)) | R32: =IF(O32="","",P32-Q32) | S32: =IF(O32="","",COUNTIFS(전표_원본!$Q$5:$Q$100000,"당기",전표_원본!$R$5:$R$100000,O32,전표_원본!$P$5:$P$100000,">0")) | T32: =IF(O32="","",COUNTIFS(전표_원본!$Q$5:$Q$100000,"비교",전표_원본!$R$5:$R$100000,O32,전표_원본!$P$5:$P$100000,">0")) | U32: =IF(O32="","",SUMPRODUCT(MAX((전표_원본!$Q$5:$Q$100000="당기")*(전표_원본!$R$5:$R$100000=O32)*전표_원본!$P$5:$P$100000))) | V32: =IF(O32="","",IF(LEFT(O32,1)="(","N",IF(COUNTIFS(전표_원본!$O$5:$O$100000,$C$9,전표_원본!$K$5:$K$100000,O32,전표_원본!$M$5:$M$100000,">="&($C$10-12),전표_원본!$M$5:$M$100000,"<"&$C$10)=0,"Y","N"))) | W32: =IF(O32="","",R32+ROW()/1000000) | Y32: SA 순증 | Z32: =SUMIFS(전표_원본!$P$5:$P$100000,전표_원본!$Q$5:$Q$100000,"당기",전표_원본!$E$5:$E$100000,"SA")-SUMIFS(전표_원본!$P$5:$P$100000,전표_원본!$Q$5:$Q$100000,"비교",전표_원본!$E$5:$E$100000,"SA")
A33: =IF($K33="","",INDEX($O$32:$O$46,$K33)) | B33: =IF($K33="","",INDEX($P$32:$P$46,$K33)) | C33: =IF($K33="","",INDEX($Q$32:$Q$46,$K33)) | D33: =IF($K33="","",INDEX($R$32:$R$46,$K33)) | E33: =IF(OR($K33="",$C$16<=0),"",D33/$C$16) | F33: =IF($K33="","",INDEX($S$32:$S$46,$K33)) | G33: =IF($K33="","",INDEX($T$32:$T$46,$K33)) | H33: =IF($K33="","",INDEX($U$32:$U$46,$K33)) | I33: =IF($K33="","",INDEX($V$32:$V$46,$K33)) | K33: =IF(COUNT($W$32:$W$46)<2,"",MATCH(LARGE($W$32:$W$46,2),$W$32:$W$46,0)) | N33: =IFERROR(SMALL(전표_원본!$S$5:$S$100000,2),"") | O33: =IF(N33="","",INDEX(전표_원본!$K$1:$K$100000,N33)) | P33: =IF(O33="","",SUMIFS(전표_원본!$P$5:$P$100000,전표_원본!$Q$5:$Q$100000,"당기",전표_원본!$R$5:$R$100000,O33)) | Q33: =IF(O33="","",SUMIFS(전표_원본!$P$5:$P$100000,전표_원본!$Q$5:$Q$100000,"비교",전표_원본!$R$5:$R$100000,O33)) | R33: =IF(O33="","",P33-Q33) | S33: =IF(O33="","",COUNTIFS(전표_원본!$Q$5:$Q$100000,"당기",전표_원본!$R$5:$R$100000,O33,전표_원본!$P$5:$P$100000,">0")) | T33: =IF(O33="","",COUNTIFS(전표_원본!$Q$5:$Q$100000,"비교",전표_원본!$R$5:$R$100000,O33,전표_원본!$P$5:$P$100000,">0")) | U33: =IF(O33="","",SUMPRODUCT(MAX((전표_원본!$Q$5:$Q$100000="당기")*(전표_원본!$R$5:$R$100000=O33)*전표_원본!$P$5:$P$100000))) | V33: =IF(O33="","",IF(LEFT(O33,1)="(","N",IF(COUNTIFS(전표_원본!$O$5:$O$100000,$C$9,전표_원본!$K$5:$K$100000,O33,전표_원본!$M$5:$M$100000,">="&($C$10-12),전표_원본!$M$5:$M$100000,"<"&$C$10)=0,"Y","N"))) | W33: =IF(O33="","",R33+ROW()/1000000) | Y33: SA 첫 적요 | Z33: =IFERROR(INDEX(전표_원본!$I$5:$I$100000,MATCH(1,INDEX((전표_원본!$Q$5:$Q$100000="당기")*(전표_원본!$E$5:$E$100000="SA"),0),0)),"")
A34: =IF($K34="","",INDEX($O$32:$O$46,$K34)) | B34: =IF($K34="","",INDEX($P$32:$P$46,$K34)) | C34: =IF($K34="","",INDEX($Q$32:$Q$46,$K34)) | D34: =IF($K34="","",INDEX($R$32:$R$46,$K34)) | E34: =IF(OR($K34="",$C$16<=0),"",D34/$C$16) | F34: =IF($K34="","",INDEX($S$32:$S$46,$K34)) | G34: =IF($K34="","",INDEX($T$32:$T$46,$K34)) | H34: =IF($K34="","",INDEX($U$32:$U$46,$K34)) | I34: =IF($K34="","",INDEX($V$32:$V$46,$K34)) | K34: =IF(COUNT($W$32:$W$46)<3,"",MATCH(LARGE($W$32:$W$46,3),$W$32:$W$46,0)) | N34: =IFERROR(SMALL(전표_원본!$S$5:$S$100000,3),"") | O34: =IF(N34="","",INDEX(전표_원본!$K$1:$K$100000,N34)) | P34: =IF(O34="","",SUMIFS(전표_원본!$P$5:$P$100000,전표_원본!$Q$5:$Q$100000,"당기",전표_원본!$R$5:$R$100000,O34)) | Q34: =IF(O34="","",SUMIFS(전표_원본!$P$5:$P$100000,전표_원본!$Q$5:$Q$100000,"비교",전표_원본!$R$5:$R$100000,O34)) | R34: =IF(O34="","",P34-Q34) | S34: =IF(O34="","",COUNTIFS(전표_원본!$Q$5:$Q$100000,"당기",전표_원본!$R$5:$R$100000,O34,전표_원본!$P$5:$P$100000,">0")) | T34: =IF(O34="","",COUNTIFS(전표_원본!$Q$5:$Q$100000,"비교",전표_원본!$R$5:$R$100000,O34,전표_원본!$P$5:$P$100000,">0")) | U34: =IF(O34="","",SUMPRODUCT(MAX((전표_원본!$Q$5:$Q$100000="당기")*(전표_원본!$R$5:$R$100000=O34)*전표_원본!$P$5:$P$100000))) | V34: =IF(O34="","",IF(LEFT(O34,1)="(","N",IF(COUNTIFS(전표_원본!$O$5:$O$100000,$C$9,전표_원본!$K$5:$K$100000,O34,전표_원본!$M$5:$M$100000,">="&($C$10-12),전표_원본!$M$5:$M$100000,"<"&$C$10)=0,"Y","N"))) | W34: =IF(O34="","",R34+ROW()/1000000) | Y34: 키워드 최대 비중 | Z34: =IF(COUNT(키워드사전!$I$5:$I$19)=0,0,MAX(키워드사전!$I$5:$I$19))
A35: =IF($K35="","",INDEX($O$32:$O$46,$K35)) | B35: =IF($K35="","",INDEX($P$32:$P$46,$K35)) | C35: =IF($K35="","",INDEX($Q$32:$Q$46,$K35)) | D35: =IF($K35="","",INDEX($R$32:$R$46,$K35)) | E35: =IF(OR($K35="",$C$16<=0),"",D35/$C$16) | F35: =IF($K35="","",INDEX($S$32:$S$46,$K35)) | G35: =IF($K35="","",INDEX($T$32:$T$46,$K35)) | H35: =IF($K35="","",INDEX($U$32:$U$46,$K35)) | I35: =IF($K35="","",INDEX($V$32:$V$46,$K35)) | K35: =IF(COUNT($W$32:$W$46)<4,"",MATCH(LARGE($W$32:$W$46,4),$W$32:$W$46,0)) | N35: =IFERROR(SMALL(전표_원본!$S$5:$S$100000,4),"") | O35: =IF(N35="","",INDEX(전표_원본!$K$1:$K$100000,N35)) | P35: =IF(O35="","",SUMIFS(전표_원본!$P$5:$P$100000,전표_원본!$Q$5:$Q$100000,"당기",전표_원본!$R$5:$R$100000,O35)) | Q35: =IF(O35="","",SUMIFS(전표_원본!$P$5:$P$100000,전표_원본!$Q$5:$Q$100000,"비교",전표_원본!$R$5:$R$100000,O35)) | R35: =IF(O35="","",P35-Q35) | S35: =IF(O35="","",COUNTIFS(전표_원본!$Q$5:$Q$100000,"당기",전표_원본!$R$5:$R$100000,O35,전표_원본!$P$5:$P$100000,">0")) | T35: =IF(O35="","",COUNTIFS(전표_원본!$Q$5:$Q$100000,"비교",전표_원본!$R$5:$R$100000,O35,전표_원본!$P$5:$P$100000,">0")) | U35: =IF(O35="","",SUMPRODUCT(MAX((전표_원본!$Q$5:$Q$100000="당기")*(전표_원본!$R$5:$R$100000=O35)*전표_원본!$P$5:$P$100000))) | V35: =IF(O35="","",IF(LEFT(O35,1)="(","N",IF(COUNTIFS(전표_원본!$O$5:$O$100000,$C$9,전표_원본!$K$5:$K$100000,O35,전표_원본!$M$5:$M$100000,">="&($C$10-12),전표_원본!$M$5:$M$100000,"<"&$C$10)=0,"Y","N"))) | W35: =IF(O35="","",R35+ROW()/1000000) | Y35: 키워드 유형 행 | Z35: =IF(Z34<=0,"",MATCH(Z34,키워드사전!$I$5:$I$19,0))
A36: =IF($K36="","",INDEX($O$32:$O$46,$K36)) | B36: =IF($K36="","",INDEX($P$32:$P$46,$K36)) | C36: =IF($K36="","",INDEX($Q$32:$Q$46,$K36)) | D36: =IF($K36="","",INDEX($R$32:$R$46,$K36)) | E36: =IF(OR($K36="",$C$16<=0),"",D36/$C$16) | F36: =IF($K36="","",INDEX($S$32:$S$46,$K36)) | G36: =IF($K36="","",INDEX($T$32:$T$46,$K36)) | H36: =IF($K36="","",INDEX($U$32:$U$46,$K36)) | I36: =IF($K36="","",INDEX($V$32:$V$46,$K36)) | K36: =IF(COUNT($W$32:$W$46)<5,"",MATCH(LARGE($W$32:$W$46,5),$W$32:$W$46,0)) | N36: =IFERROR(SMALL(전표_원본!$S$5:$S$100000,5),"") | O36: =IF(N36="","",INDEX(전표_원본!$K$1:$K$100000,N36)) | P36: =IF(O36="","",SUMIFS(전표_원본!$P$5:$P$100000,전표_원본!$Q$5:$Q$100000,"당기",전표_원본!$R$5:$R$100000,O36)) | Q36: =IF(O36="","",SUMIFS(전표_원본!$P$5:$P$100000,전표_원본!$Q$5:$Q$100000,"비교",전표_원본!$R$5:$R$100000,O36)) | R36: =IF(O36="","",P36-Q36) | S36: =IF(O36="","",COUNTIFS(전표_원본!$Q$5:$Q$100000,"당기",전표_원본!$R$5:$R$100000,O36,전표_원본!$P$5:$P$100000,">0")) | T36: =IF(O36="","",COUNTIFS(전표_원본!$Q$5:$Q$100000,"비교",전표_원본!$R$5:$R$100000,O36,전표_원본!$P$5:$P$100000,">0")) | U36: =IF(O36="","",SUMPRODUCT(MAX((전표_원본!$Q$5:$Q$100000="당기")*(전표_원본!$R$5:$R$100000=O36)*전표_원본!$P$5:$P$100000))) | V36: =IF(O36="","",IF(LEFT(O36,1)="(","N",IF(COUNTIFS(전표_원본!$O$5:$O$100000,$C$9,전표_원본!$K$5:$K$100000,O36,전표_원본!$M$5:$M$100000,">="&($C$10-12),전표_원본!$M$5:$M$100000,"<"&$C$10)=0,"Y","N"))) | W36: =IF(O36="","",R36+ROW()/1000000) | Y36: 당기 건수 (+) | Z36: =COUNTIFS(전표_원본!$Q$5:$Q$100000,"당기",전표_원본!$P$5:$P$100000,">0")
A37: =IF($K37="","",INDEX($O$32:$O$46,$K37)) | B37: =IF($K37="","",INDEX($P$32:$P$46,$K37)) | C37: =IF($K37="","",INDEX($Q$32:$Q$46,$K37)) | D37: =IF($K37="","",INDEX($R$32:$R$46,$K37)) | E37: =IF(OR($K37="",$C$16<=0),"",D37/$C$16) | F37: =IF($K37="","",INDEX($S$32:$S$46,$K37)) | G37: =IF($K37="","",INDEX($T$32:$T$46,$K37)) | H37: =IF($K37="","",INDEX($U$32:$U$46,$K37)) | I37: =IF($K37="","",INDEX($V$32:$V$46,$K37)) | K37: =IF(COUNT($W$32:$W$46)<6,"",MATCH(LARGE($W$32:$W$46,6),$W$32:$W$46,0)) | N37: =IFERROR(SMALL(전표_원본!$S$5:$S$100000,6),"") | O37: =IF(N37="","",INDEX(전표_원본!$K$1:$K$100000,N37)) | P37: =IF(O37="","",SUMIFS(전표_원본!$P$5:$P$100000,전표_원본!$Q$5:$Q$100000,"당기",전표_원본!$R$5:$R$100000,O37)) | Q37: =IF(O37="","",SUMIFS(전표_원본!$P$5:$P$100000,전표_원본!$Q$5:$Q$100000,"비교",전표_원본!$R$5:$R$100000,O37)) | R37: =IF(O37="","",P37-Q37) | S37: =IF(O37="","",COUNTIFS(전표_원본!$Q$5:$Q$100000,"당기",전표_원본!$R$5:$R$100000,O37,전표_원본!$P$5:$P$100000,">0")) | T37: =IF(O37="","",COUNTIFS(전표_원본!$Q$5:$Q$100000,"비교",전표_원본!$R$5:$R$100000,O37,전표_원본!$P$5:$P$100000,">0")) | U37: =IF(O37="","",SUMPRODUCT(MAX((전표_원본!$Q$5:$Q$100000="당기")*(전표_원본!$R$5:$R$100000=O37)*전표_원본!$P$5:$P$100000))) | V37: =IF(O37="","",IF(LEFT(O37,1)="(","N",IF(COUNTIFS(전표_원본!$O$5:$O$100000,$C$9,전표_원본!$K$5:$K$100000,O37,전표_원본!$M$5:$M$100000,">="&($C$10-12),전표_원본!$M$5:$M$100000,"<"&$C$10)=0,"Y","N"))) | W37: =IF(O37="","",R37+ROW()/1000000) | Y37: 비교 건수 (+) | Z37: =COUNTIFS(전표_원본!$Q$5:$Q$100000,"비교",전표_원본!$P$5:$P$100000,">0")
A38: =IF($K38="","",INDEX($O$32:$O$46,$K38)) | B38: =IF($K38="","",INDEX($P$32:$P$46,$K38)) | C38: =IF($K38="","",INDEX($Q$32:$Q$46,$K38)) | D38: =IF($K38="","",INDEX($R$32:$R$46,$K38)) | E38: =IF(OR($K38="",$C$16<=0),"",D38/$C$16) | F38: =IF($K38="","",INDEX($S$32:$S$46,$K38)) | G38: =IF($K38="","",INDEX($T$32:$T$46,$K38)) | H38: =IF($K38="","",INDEX($U$32:$U$46,$K38)) | I38: =IF($K38="","",INDEX($V$32:$V$46,$K38)) | K38: =IF(COUNT($W$32:$W$46)<7,"",MATCH(LARGE($W$32:$W$46,7),$W$32:$W$46,0)) | N38: =IFERROR(SMALL(전표_원본!$S$5:$S$100000,7),"") | O38: =IF(N38="","",INDEX(전표_원본!$K$1:$K$100000,N38)) | P38: =IF(O38="","",SUMIFS(전표_원본!$P$5:$P$100000,전표_원본!$Q$5:$Q$100000,"당기",전표_원본!$R$5:$R$100000,O38)) | Q38: =IF(O38="","",SUMIFS(전표_원본!$P$5:$P$100000,전표_원본!$Q$5:$Q$100000,"비교",전표_원본!$R$5:$R$100000,O38)) | R38: =IF(O38="","",P38-Q38) | S38: =IF(O38="","",COUNTIFS(전표_원본!$Q$5:$Q$100000,"당기",전표_원본!$R$5:$R$100000,O38,전표_원본!$P$5:$P$100000,">0")) | T38: =IF(O38="","",COUNTIFS(전표_원본!$Q$5:$Q$100000,"비교",전표_원본!$R$5:$R$100000,O38,전표_원본!$P$5:$P$100000,">0")) | U38: =IF(O38="","",SUMPRODUCT(MAX((전표_원본!$Q$5:$Q$100000="당기")*(전표_원본!$R$5:$R$100000=O38)*전표_원본!$P$5:$P$100000))) | V38: =IF(O38="","",IF(LEFT(O38,1)="(","N",IF(COUNTIFS(전표_원본!$O$5:$O$100000,$C$9,전표_원본!$K$5:$K$100000,O38,전표_원본!$M$5:$M$100000,">="&($C$10-12),전표_원본!$M$5:$M$100000,"<"&$C$10)=0,"Y","N"))) | W38: =IF(O38="","",R38+ROW()/1000000) | Y38: 당기 금액 (+) | Z38: =SUMIFS(전표_원본!$P$5:$P$100000,전표_원본!$Q$5:$Q$100000,"당기",전표_원본!$P$5:$P$100000,">0")
A39: =IF($K39="","",INDEX($O$32:$O$46,$K39)) | B39: =IF($K39="","",INDEX($P$32:$P$46,$K39)) | C39: =IF($K39="","",INDEX($Q$32:$Q$46,$K39)) | D39: =IF($K39="","",INDEX($R$32:$R$46,$K39)) | E39: =IF(OR($K39="",$C$16<=0),"",D39/$C$16) | F39: =IF($K39="","",INDEX($S$32:$S$46,$K39)) | G39: =IF($K39="","",INDEX($T$32:$T$46,$K39)) | H39: =IF($K39="","",INDEX($U$32:$U$46,$K39)) | I39: =IF($K39="","",INDEX($V$32:$V$46,$K39)) | K39: =IF(COUNT($W$32:$W$46)<8,"",MATCH(LARGE($W$32:$W$46,8),$W$32:$W$46,0)) | N39: =IFERROR(SMALL(전표_원본!$S$5:$S$100000,8),"") | O39: =IF(N39="","",INDEX(전표_원본!$K$1:$K$100000,N39)) | P39: =IF(O39="","",SUMIFS(전표_원본!$P$5:$P$100000,전표_원본!$Q$5:$Q$100000,"당기",전표_원본!$R$5:$R$100000,O39)) | Q39: =IF(O39="","",SUMIFS(전표_원본!$P$5:$P$100000,전표_원본!$Q$5:$Q$100000,"비교",전표_원본!$R$5:$R$100000,O39)) | R39: =IF(O39="","",P39-Q39) | S39: =IF(O39="","",COUNTIFS(전표_원본!$Q$5:$Q$100000,"당기",전표_원본!$R$5:$R$100000,O39,전표_원본!$P$5:$P$100000,">0")) | T39: =IF(O39="","",COUNTIFS(전표_원본!$Q$5:$Q$100000,"비교",전표_원본!$R$5:$R$100000,O39,전표_원본!$P$5:$P$100000,">0")) | U39: =IF(O39="","",SUMPRODUCT(MAX((전표_원본!$Q$5:$Q$100000="당기")*(전표_원본!$R$5:$R$100000=O39)*전표_원본!$P$5:$P$100000))) | V39: =IF(O39="","",IF(LEFT(O39,1)="(","N",IF(COUNTIFS(전표_원본!$O$5:$O$100000,$C$9,전표_원본!$K$5:$K$100000,O39,전표_원본!$M$5:$M$100000,">="&($C$10-12),전표_원본!$M$5:$M$100000,"<"&$C$10)=0,"Y","N"))) | W39: =IF(O39="","",R39+ROW()/1000000) | Y39: 비교 금액 (+) | Z39: =SUMIFS(전표_원본!$P$5:$P$100000,전표_원본!$Q$5:$Q$100000,"비교",전표_원본!$P$5:$P$100000,">0")
A40: =IF($K40="","",INDEX($O$32:$O$46,$K40)) | B40: =IF($K40="","",INDEX($P$32:$P$46,$K40)) | C40: =IF($K40="","",INDEX($Q$32:$Q$46,$K40)) | D40: =IF($K40="","",INDEX($R$32:$R$46,$K40)) | E40: =IF(OR($K40="",$C$16<=0),"",D40/$C$16) | F40: =IF($K40="","",INDEX($S$32:$S$46,$K40)) | G40: =IF($K40="","",INDEX($T$32:$T$46,$K40)) | H40: =IF($K40="","",INDEX($U$32:$U$46,$K40)) | I40: =IF($K40="","",INDEX($V$32:$V$46,$K40)) | K40: =IF(COUNT($W$32:$W$46)<9,"",MATCH(LARGE($W$32:$W$46,9),$W$32:$W$46,0)) | N40: =IFERROR(SMALL(전표_원본!$S$5:$S$100000,9),"") | O40: =IF(N40="","",INDEX(전표_원본!$K$1:$K$100000,N40)) | P40: =IF(O40="","",SUMIFS(전표_원본!$P$5:$P$100000,전표_원본!$Q$5:$Q$100000,"당기",전표_원본!$R$5:$R$100000,O40)) | Q40: =IF(O40="","",SUMIFS(전표_원본!$P$5:$P$100000,전표_원본!$Q$5:$Q$100000,"비교",전표_원본!$R$5:$R$100000,O40)) | R40: =IF(O40="","",P40-Q40) | S40: =IF(O40="","",COUNTIFS(전표_원본!$Q$5:$Q$100000,"당기",전표_원본!$R$5:$R$100000,O40,전표_원본!$P$5:$P$100000,">0")) | T40: =IF(O40="","",COUNTIFS(전표_원본!$Q$5:$Q$100000,"비교",전표_원본!$R$5:$R$100000,O40,전표_원본!$P$5:$P$100000,">0")) | U40: =IF(O40="","",SUMPRODUCT(MAX((전표_원본!$Q$5:$Q$100000="당기")*(전표_원본!$R$5:$R$100000=O40)*전표_원본!$P$5:$P$100000))) | V40: =IF(O40="","",IF(LEFT(O40,1)="(","N",IF(COUNTIFS(전표_원본!$O$5:$O$100000,$C$9,전표_원본!$K$5:$K$100000,O40,전표_원본!$M$5:$M$100000,">="&($C$10-12),전표_원본!$M$5:$M$100000,"<"&$C$10)=0,"Y","N"))) | W40: =IF(O40="","",R40+ROW()/1000000) | Y40: 건당 당기 | Z40: =IF(Z36=0,0,Z38/Z36)
A41: =IF($K41="","",INDEX($O$32:$O$46,$K41)) | B41: =IF($K41="","",INDEX($P$32:$P$46,$K41)) | C41: =IF($K41="","",INDEX($Q$32:$Q$46,$K41)) | D41: =IF($K41="","",INDEX($R$32:$R$46,$K41)) | E41: =IF(OR($K41="",$C$16<=0),"",D41/$C$16) | F41: =IF($K41="","",INDEX($S$32:$S$46,$K41)) | G41: =IF($K41="","",INDEX($T$32:$T$46,$K41)) | H41: =IF($K41="","",INDEX($U$32:$U$46,$K41)) | I41: =IF($K41="","",INDEX($V$32:$V$46,$K41)) | K41: =IF(COUNT($W$32:$W$46)<10,"",MATCH(LARGE($W$32:$W$46,10),$W$32:$W$46,0)) | N41: =IFERROR(SMALL(전표_원본!$S$5:$S$100000,10),"") | O41: =IF(N41="","",INDEX(전표_원본!$K$1:$K$100000,N41)) | P41: =IF(O41="","",SUMIFS(전표_원본!$P$5:$P$100000,전표_원본!$Q$5:$Q$100000,"당기",전표_원본!$R$5:$R$100000,O41)) | Q41: =IF(O41="","",SUMIFS(전표_원본!$P$5:$P$100000,전표_원본!$Q$5:$Q$100000,"비교",전표_원본!$R$5:$R$100000,O41)) | R41: =IF(O41="","",P41-Q41) | S41: =IF(O41="","",COUNTIFS(전표_원본!$Q$5:$Q$100000,"당기",전표_원본!$R$5:$R$100000,O41,전표_원본!$P$5:$P$100000,">0")) | T41: =IF(O41="","",COUNTIFS(전표_원본!$Q$5:$Q$100000,"비교",전표_원본!$R$5:$R$100000,O41,전표_원본!$P$5:$P$100000,">0")) | U41: =IF(O41="","",SUMPRODUCT(MAX((전표_원본!$Q$5:$Q$100000="당기")*(전표_원본!$R$5:$R$100000=O41)*전표_원본!$P$5:$P$100000))) | V41: =IF(O41="","",IF(LEFT(O41,1)="(","N",IF(COUNTIFS(전표_원본!$O$5:$O$100000,$C$9,전표_원본!$K$5:$K$100000,O41,전표_원본!$M$5:$M$100000,">="&($C$10-12),전표_원본!$M$5:$M$100000,"<"&$C$10)=0,"Y","N"))) | W41: =IF(O41="","",R41+ROW()/1000000) | Y41: 건당 비교 | Z41: =IF(Z37=0,0,Z39/Z37)
A42: =IF($K42="","",INDEX($O$32:$O$46,$K42)) | B42: =IF($K42="","",INDEX($P$32:$P$46,$K42)) | C42: =IF($K42="","",INDEX($Q$32:$Q$46,$K42)) | D42: =IF($K42="","",INDEX($R$32:$R$46,$K42)) | E42: =IF(OR($K42="",$C$16<=0),"",D42/$C$16) | F42: =IF($K42="","",INDEX($S$32:$S$46,$K42)) | G42: =IF($K42="","",INDEX($T$32:$T$46,$K42)) | H42: =IF($K42="","",INDEX($U$32:$U$46,$K42)) | I42: =IF($K42="","",INDEX($V$32:$V$46,$K42)) | K42: =IF(COUNT($W$32:$W$46)<11,"",MATCH(LARGE($W$32:$W$46,11),$W$32:$W$46,0)) | N42: =IFERROR(SMALL(전표_원본!$S$5:$S$100000,11),"") | O42: =IF(N42="","",INDEX(전표_원본!$K$1:$K$100000,N42)) | P42: =IF(O42="","",SUMIFS(전표_원본!$P$5:$P$100000,전표_원본!$Q$5:$Q$100000,"당기",전표_원본!$R$5:$R$100000,O42)) | Q42: =IF(O42="","",SUMIFS(전표_원본!$P$5:$P$100000,전표_원본!$Q$5:$Q$100000,"비교",전표_원본!$R$5:$R$100000,O42)) | R42: =IF(O42="","",P42-Q42) | S42: =IF(O42="","",COUNTIFS(전표_원본!$Q$5:$Q$100000,"당기",전표_원본!$R$5:$R$100000,O42,전표_원본!$P$5:$P$100000,">0")) | T42: =IF(O42="","",COUNTIFS(전표_원본!$Q$5:$Q$100000,"비교",전표_원본!$R$5:$R$100000,O42,전표_원본!$P$5:$P$100000,">0")) | U42: =IF(O42="","",SUMPRODUCT(MAX((전표_원본!$Q$5:$Q$100000="당기")*(전표_원본!$R$5:$R$100000=O42)*전표_원본!$P$5:$P$100000))) | V42: =IF(O42="","",IF(LEFT(O42,1)="(","N",IF(COUNTIFS(전표_원본!$O$5:$O$100000,$C$9,전표_원본!$K$5:$K$100000,O42,전표_원본!$M$5:$M$100000,">="&($C$10-12),전표_원본!$M$5:$M$100000,"<"&$C$10)=0,"Y","N"))) | W42: =IF(O42="","",R42+ROW()/1000000) | Y42: 신규 거래처 증감 | Z42: =SUMIFS($R$32:$R$46,$V$32:$V$46,"Y")
A43: =IF($K43="","",INDEX($O$32:$O$46,$K43)) | B43: =IF($K43="","",INDEX($P$32:$P$46,$K43)) | C43: =IF($K43="","",INDEX($Q$32:$Q$46,$K43)) | D43: =IF($K43="","",INDEX($R$32:$R$46,$K43)) | E43: =IF(OR($K43="",$C$16<=0),"",D43/$C$16) | F43: =IF($K43="","",INDEX($S$32:$S$46,$K43)) | G43: =IF($K43="","",INDEX($T$32:$T$46,$K43)) | H43: =IF($K43="","",INDEX($U$32:$U$46,$K43)) | I43: =IF($K43="","",INDEX($V$32:$V$46,$K43)) | K43: =IF(COUNT($W$32:$W$46)<12,"",MATCH(LARGE($W$32:$W$46,12),$W$32:$W$46,0)) | N43: =IFERROR(SMALL(전표_원본!$S$5:$S$100000,12),"") | O43: =IF(N43="","",INDEX(전표_원본!$K$1:$K$100000,N43)) | P43: =IF(O43="","",SUMIFS(전표_원본!$P$5:$P$100000,전표_원본!$Q$5:$Q$100000,"당기",전표_원본!$R$5:$R$100000,O43)) | Q43: =IF(O43="","",SUMIFS(전표_원본!$P$5:$P$100000,전표_원본!$Q$5:$Q$100000,"비교",전표_원본!$R$5:$R$100000,O43)) | R43: =IF(O43="","",P43-Q43) | S43: =IF(O43="","",COUNTIFS(전표_원본!$Q$5:$Q$100000,"당기",전표_원본!$R$5:$R$100000,O43,전표_원본!$P$5:$P$100000,">0")) | T43: =IF(O43="","",COUNTIFS(전표_원본!$Q$5:$Q$100000,"비교",전표_원본!$R$5:$R$100000,O43,전표_원본!$P$5:$P$100000,">0")) | U43: =IF(O43="","",SUMPRODUCT(MAX((전표_원본!$Q$5:$Q$100000="당기")*(전표_원본!$R$5:$R$100000=O43)*전표_원본!$P$5:$P$100000))) | V43: =IF(O43="","",IF(LEFT(O43,1)="(","N",IF(COUNTIFS(전표_원본!$O$5:$O$100000,$C$9,전표_원본!$K$5:$K$100000,O43,전표_원본!$M$5:$M$100000,">="&($C$10-12),전표_원본!$M$5:$M$100000,"<"&$C$10)=0,"Y","N"))) | W43: =IF(O43="","",R43+ROW()/1000000) | Y43: 신규 거래처 수 | Z43: =COUNTIFS($V$32:$V$46,"Y",$R$32:$R$46,">0")
A44: =IF($K44="","",INDEX($O$32:$O$46,$K44)) | B44: =IF($K44="","",INDEX($P$32:$P$46,$K44)) | C44: =IF($K44="","",INDEX($Q$32:$Q$46,$K44)) | D44: =IF($K44="","",INDEX($R$32:$R$46,$K44)) | E44: =IF(OR($K44="",$C$16<=0),"",D44/$C$16) | F44: =IF($K44="","",INDEX($S$32:$S$46,$K44)) | G44: =IF($K44="","",INDEX($T$32:$T$46,$K44)) | H44: =IF($K44="","",INDEX($U$32:$U$46,$K44)) | I44: =IF($K44="","",INDEX($V$32:$V$46,$K44)) | K44: =IF(COUNT($W$32:$W$46)<13,"",MATCH(LARGE($W$32:$W$46,13),$W$32:$W$46,0)) | N44: =IFERROR(SMALL(전표_원본!$S$5:$S$100000,13),"") | O44: =IF(N44="","",INDEX(전표_원본!$K$1:$K$100000,N44)) | P44: =IF(O44="","",SUMIFS(전표_원본!$P$5:$P$100000,전표_원본!$Q$5:$Q$100000,"당기",전표_원본!$R$5:$R$100000,O44)) | Q44: =IF(O44="","",SUMIFS(전표_원본!$P$5:$P$100000,전표_원본!$Q$5:$Q$100000,"비교",전표_원본!$R$5:$R$100000,O44)) | R44: =IF(O44="","",P44-Q44) | S44: =IF(O44="","",COUNTIFS(전표_원본!$Q$5:$Q$100000,"당기",전표_원본!$R$5:$R$100000,O44,전표_원본!$P$5:$P$100000,">0")) | T44: =IF(O44="","",COUNTIFS(전표_원본!$Q$5:$Q$100000,"비교",전표_원본!$R$5:$R$100000,O44,전표_원본!$P$5:$P$100000,">0")) | U44: =IF(O44="","",SUMPRODUCT(MAX((전표_원본!$Q$5:$Q$100000="당기")*(전표_원본!$R$5:$R$100000=O44)*전표_원본!$P$5:$P$100000))) | V44: =IF(O44="","",IF(LEFT(O44,1)="(","N",IF(COUNTIFS(전표_원본!$O$5:$O$100000,$C$9,전표_원본!$K$5:$K$100000,O44,전표_원본!$M$5:$M$100000,">="&($C$10-12),전표_원본!$M$5:$M$100000,"<"&$C$10)=0,"Y","N"))) | W44: =IF(O44="","",R44+ROW()/1000000) | Y44: 첫 신규 거래처 | Z44: =IFERROR(INDEX($A$32:$A$46,MATCH("Y",$I$32:$I$46,0)),"")
A45: =IF($K45="","",INDEX($O$32:$O$46,$K45)) | B45: =IF($K45="","",INDEX($P$32:$P$46,$K45)) | C45: =IF($K45="","",INDEX($Q$32:$Q$46,$K45)) | D45: =IF($K45="","",INDEX($R$32:$R$46,$K45)) | E45: =IF(OR($K45="",$C$16<=0),"",D45/$C$16) | F45: =IF($K45="","",INDEX($S$32:$S$46,$K45)) | G45: =IF($K45="","",INDEX($T$32:$T$46,$K45)) | H45: =IF($K45="","",INDEX($U$32:$U$46,$K45)) | I45: =IF($K45="","",INDEX($V$32:$V$46,$K45)) | K45: =IF(COUNT($W$32:$W$46)<14,"",MATCH(LARGE($W$32:$W$46,14),$W$32:$W$46,0)) | N45: =IFERROR(SMALL(전표_원본!$S$5:$S$100000,14),"") | O45: =IF(N45="","",INDEX(전표_원본!$K$1:$K$100000,N45)) | P45: =IF(O45="","",SUMIFS(전표_원본!$P$5:$P$100000,전표_원본!$Q$5:$Q$100000,"당기",전표_원본!$R$5:$R$100000,O45)) | Q45: =IF(O45="","",SUMIFS(전표_원본!$P$5:$P$100000,전표_원본!$Q$5:$Q$100000,"비교",전표_원본!$R$5:$R$100000,O45)) | R45: =IF(O45="","",P45-Q45) | S45: =IF(O45="","",COUNTIFS(전표_원본!$Q$5:$Q$100000,"당기",전표_원본!$R$5:$R$100000,O45,전표_원본!$P$5:$P$100000,">0")) | T45: =IF(O45="","",COUNTIFS(전표_원본!$Q$5:$Q$100000,"비교",전표_원본!$R$5:$R$100000,O45,전표_원본!$P$5:$P$100000,">0")) | U45: =IF(O45="","",SUMPRODUCT(MAX((전표_원본!$Q$5:$Q$100000="당기")*(전표_원본!$R$5:$R$100000=O45)*전표_원본!$P$5:$P$100000))) | V45: =IF(O45="","",IF(LEFT(O45,1)="(","N",IF(COUNTIFS(전표_원본!$O$5:$O$100000,$C$9,전표_원본!$K$5:$K$100000,O45,전표_원본!$M$5:$M$100000,">="&($C$10-12),전표_원본!$M$5:$M$100000,"<"&$C$10)=0,"Y","N"))) | W45: =IF(O45="","",R45+ROW()/1000000) | Y45: 최대 단건 거래처 평소 월평균 | Z45: =IF(Z20="",0,SUMIFS(전표_원본!$P$5:$P$100000,전표_원본!$O$5:$O$100000,$C$9,전표_원본!$K$5:$K$100000,Z24,전표_원본!$M$5:$M$100000,">="&($C$10-12),전표_원본!$M$5:$M$100000,"<"&$C$10)/12)
A46: =IF($K46="","",INDEX($O$32:$O$46,$K46)) | B46: =IF($K46="","",INDEX($P$32:$P$46,$K46)) | C46: =IF($K46="","",INDEX($Q$32:$Q$46,$K46)) | D46: =IF($K46="","",INDEX($R$32:$R$46,$K46)) | E46: =IF(OR($K46="",$C$16<=0),"",D46/$C$16) | F46: =IF($K46="","",INDEX($S$32:$S$46,$K46)) | G46: =IF($K46="","",INDEX($T$32:$T$46,$K46)) | H46: =IF($K46="","",INDEX($U$32:$U$46,$K46)) | I46: =IF($K46="","",INDEX($V$32:$V$46,$K46)) | K46: =IF(COUNT($W$32:$W$46)<15,"",MATCH(LARGE($W$32:$W$46,15),$W$32:$W$46,0)) | N46: =IFERROR(SMALL(전표_원본!$S$5:$S$100000,15),"") | O46: =IF(N46="","",INDEX(전표_원본!$K$1:$K$100000,N46)) | P46: =IF(O46="","",SUMIFS(전표_원본!$P$5:$P$100000,전표_원본!$Q$5:$Q$100000,"당기",전표_원본!$R$5:$R$100000,O46)) | Q46: =IF(O46="","",SUMIFS(전표_원본!$P$5:$P$100000,전표_원본!$Q$5:$Q$100000,"비교",전표_원본!$R$5:$R$100000,O46)) | R46: =IF(O46="","",P46-Q46) | S46: =IF(O46="","",COUNTIFS(전표_원본!$Q$5:$Q$100000,"당기",전표_원본!$R$5:$R$100000,O46,전표_원본!$P$5:$P$100000,">0")) | T46: =IF(O46="","",COUNTIFS(전표_원본!$Q$5:$Q$100000,"비교",전표_원본!$R$5:$R$100000,O46,전표_원본!$P$5:$P$100000,">0")) | U46: =IF(O46="","",SUMPRODUCT(MAX((전표_원본!$Q$5:$Q$100000="당기")*(전표_원본!$R$5:$R$100000=O46)*전표_원본!$P$5:$P$100000))) | V46: =IF(O46="","",IF(LEFT(O46,1)="(","N",IF(COUNTIFS(전표_원본!$O$5:$O$100000,$C$9,전표_원본!$K$5:$K$100000,O46,전표_원본!$M$5:$M$100000,">="&($C$10-12),전표_원본!$M$5:$M$100000,"<"&$C$10)=0,"Y","N"))) | W46: =IF(O46="","",R46+ROW()/1000000)
A49: 근거 전표 · 당기 (금액 절댓값 큰 순)
A50: 전기일 | B50: 전표번호 | C50: 유형 | D50: 거래처 | E50: 적요 | F50: 금액 | G50: 코스트센터
A51: =IF($K51="","",INDEX(전표_원본!$D$5:$D$100000,$K51)) | B51: =IF($K51="","",INDEX(전표_원본!$C$5:$C$100000,$K51)) | C51: =IF($K51="","",INDEX(전표_원본!$E$5:$E$100000,$K51)) | D51: =IF($K51="","",INDEX(전표_원본!$K$5:$K$100000,$K51)) | E51: =IF($K51="","",INDEX(전표_원본!$I$5:$I$100000,$K51)) | F51: =IF($K51="","",INDEX(전표_원본!$P$5:$P$100000,$K51)) | G51: =IF($K51="","",INDEX(전표_원본!$G$5:$G$100000,$K51)) | K51: =IFERROR(MATCH(LARGE(전표_원본!$T$5:$T$100000,1),전표_원본!$T$5:$T$100000,0),"")
A52: =IF($K52="","",INDEX(전표_원본!$D$5:$D$100000,$K52)) | B52: =IF($K52="","",INDEX(전표_원본!$C$5:$C$100000,$K52)) | C52: =IF($K52="","",INDEX(전표_원본!$E$5:$E$100000,$K52)) | D52: =IF($K52="","",INDEX(전표_원본!$K$5:$K$100000,$K52)) | E52: =IF($K52="","",INDEX(전표_원본!$I$5:$I$100000,$K52)) | F52: =IF($K52="","",INDEX(전표_원본!$P$5:$P$100000,$K52)) | G52: =IF($K52="","",INDEX(전표_원본!$G$5:$G$100000,$K52)) | K52: =IFERROR(MATCH(LARGE(전표_원본!$T$5:$T$100000,2),전표_원본!$T$5:$T$100000,0),"")
A53: =IF($K53="","",INDEX(전표_원본!$D$5:$D$100000,$K53)) | B53: =IF($K53="","",INDEX(전표_원본!$C$5:$C$100000,$K53)) | C53: =IF($K53="","",INDEX(전표_원본!$E$5:$E$100000,$K53)) | D53: =IF($K53="","",INDEX(전표_원본!$K$5:$K$100000,$K53)) | E53: =IF($K53="","",INDEX(전표_원본!$I$5:$I$100000,$K53)) | F53: =IF($K53="","",INDEX(전표_원본!$P$5:$P$100000,$K53)) | G53: =IF($K53="","",INDEX(전표_원본!$G$5:$G$100000,$K53)) | K53: =IFERROR(MATCH(LARGE(전표_원본!$T$5:$T$100000,3),전표_원본!$T$5:$T$100000,0),"")
A54: =IF($K54="","",INDEX(전표_원본!$D$5:$D$100000,$K54)) | B54: =IF($K54="","",INDEX(전표_원본!$C$5:$C$100000,$K54)) | C54: =IF($K54="","",INDEX(전표_원본!$E$5:$E$100000,$K54)) | D54: =IF($K54="","",INDEX(전표_원본!$K$5:$K$100000,$K54)) | E54: =IF($K54="","",INDEX(전표_원본!$I$5:$I$100000,$K54)) | F54: =IF($K54="","",INDEX(전표_원본!$P$5:$P$100000,$K54)) | G54: =IF($K54="","",INDEX(전표_원본!$G$5:$G$100000,$K54)) | K54: =IFERROR(MATCH(LARGE(전표_원본!$T$5:$T$100000,4),전표_원본!$T$5:$T$100000,0),"")
A55: =IF($K55="","",INDEX(전표_원본!$D$5:$D$100000,$K55)) | B55: =IF($K55="","",INDEX(전표_원본!$C$5:$C$100000,$K55)) | C55: =IF($K55="","",INDEX(전표_원본!$E$5:$E$100000,$K55)) | D55: =IF($K55="","",INDEX(전표_원본!$K$5:$K$100000,$K55)) | E55: =IF($K55="","",INDEX(전표_원본!$I$5:$I$100000,$K55)) | F55: =IF($K55="","",INDEX(전표_원본!$P$5:$P$100000,$K55)) | G55: =IF($K55="","",INDEX(전표_원본!$G$5:$G$100000,$K55)) | K55: =IFERROR(MATCH(LARGE(전표_원본!$T$5:$T$100000,5),전표_원본!$T$5:$T$100000,0),"")
A56: =IF($K56="","",INDEX(전표_원본!$D$5:$D$100000,$K56)) | B56: =IF($K56="","",INDEX(전표_원본!$C$5:$C$100000,$K56)) | C56: =IF($K56="","",INDEX(전표_원본!$E$5:$E$100000,$K56)) | D56: =IF($K56="","",INDEX(전표_원본!$K$5:$K$100000,$K56)) | E56: =IF($K56="","",INDEX(전표_원본!$I$5:$I$100000,$K56)) | F56: =IF($K56="","",INDEX(전표_원본!$P$5:$P$100000,$K56)) | G56: =IF($K56="","",INDEX(전표_원본!$G$5:$G$100000,$K56)) | K56: =IFERROR(MATCH(LARGE(전표_원본!$T$5:$T$100000,6),전표_원본!$T$5:$T$100000,0),"")
A57: =IF($K57="","",INDEX(전표_원본!$D$5:$D$100000,$K57)) | B57: =IF($K57="","",INDEX(전표_원본!$C$5:$C$100000,$K57)) | C57: =IF($K57="","",INDEX(전표_원본!$E$5:$E$100000,$K57)) | D57: =IF($K57="","",INDEX(전표_원본!$K$5:$K$100000,$K57)) | E57: =IF($K57="","",INDEX(전표_원본!$I$5:$I$100000,$K57)) | F57: =IF($K57="","",INDEX(전표_원본!$P$5:$P$100000,$K57)) | G57: =IF($K57="","",INDEX(전표_원본!$G$5:$G$100000,$K57)) | K57: =IFERROR(MATCH(LARGE(전표_원본!$T$5:$T$100000,7),전표_원본!$T$5:$T$100000,0),"")
A58: =IF($K58="","",INDEX(전표_원본!$D$5:$D$100000,$K58)) | B58: =IF($K58="","",INDEX(전표_원본!$C$5:$C$100000,$K58)) | C58: =IF($K58="","",INDEX(전표_원본!$E$5:$E$100000,$K58)) | D58: =IF($K58="","",INDEX(전표_원본!$K$5:$K$100000,$K58)) | E58: =IF($K58="","",INDEX(전표_원본!$I$5:$I$100000,$K58)) | F58: =IF($K58="","",INDEX(전표_원본!$P$5:$P$100000,$K58)) | G58: =IF($K58="","",INDEX(전표_원본!$G$5:$G$100000,$K58)) | K58: =IFERROR(MATCH(LARGE(전표_원본!$T$5:$T$100000,8),전표_원본!$T$5:$T$100000,0),"")
A59: =IF($K59="","",INDEX(전표_원본!$D$5:$D$100000,$K59)) | B59: =IF($K59="","",INDEX(전표_원본!$C$5:$C$100000,$K59)) | C59: =IF($K59="","",INDEX(전표_원본!$E$5:$E$100000,$K59)) | D59: =IF($K59="","",INDEX(전표_원본!$K$5:$K$100000,$K59)) | E59: =IF($K59="","",INDEX(전표_원본!$I$5:$I$100000,$K59)) | F59: =IF($K59="","",INDEX(전표_원본!$P$5:$P$100000,$K59)) | G59: =IF($K59="","",INDEX(전표_원본!$G$5:$G$100000,$K59)) | K59: =IFERROR(MATCH(LARGE(전표_원본!$T$5:$T$100000,9),전표_원본!$T$5:$T$100000,0),"")
A60: =IF($K60="","",INDEX(전표_원본!$D$5:$D$100000,$K60)) | B60: =IF($K60="","",INDEX(전표_원본!$C$5:$C$100000,$K60)) | C60: =IF($K60="","",INDEX(전표_원본!$E$5:$E$100000,$K60)) | D60: =IF($K60="","",INDEX(전표_원본!$K$5:$K$100000,$K60)) | E60: =IF($K60="","",INDEX(전표_원본!$I$5:$I$100000,$K60)) | F60: =IF($K60="","",INDEX(전표_원본!$P$5:$P$100000,$K60)) | G60: =IF($K60="","",INDEX(전표_원본!$G$5:$G$100000,$K60)) | K60: =IFERROR(MATCH(LARGE(전표_원본!$T$5:$T$100000,10),전표_원본!$T$5:$T$100000,0),"")
A61: =IF($K61="","",INDEX(전표_원본!$D$5:$D$100000,$K61)) | B61: =IF($K61="","",INDEX(전표_원본!$C$5:$C$100000,$K61)) | C61: =IF($K61="","",INDEX(전표_원본!$E$5:$E$100000,$K61)) | D61: =IF($K61="","",INDEX(전표_원본!$K$5:$K$100000,$K61)) | E61: =IF($K61="","",INDEX(전표_원본!$I$5:$I$100000,$K61)) | F61: =IF($K61="","",INDEX(전표_원본!$P$5:$P$100000,$K61)) | G61: =IF($K61="","",INDEX(전표_원본!$G$5:$G$100000,$K61)) | K61: =IFERROR(MATCH(LARGE(전표_원본!$T$5:$T$100000,11),전표_원본!$T$5:$T$100000,0),"")
A62: =IF($K62="","",INDEX(전표_원본!$D$5:$D$100000,$K62)) | B62: =IF($K62="","",INDEX(전표_원본!$C$5:$C$100000,$K62)) | C62: =IF($K62="","",INDEX(전표_원본!$E$5:$E$100000,$K62)) | D62: =IF($K62="","",INDEX(전표_원본!$K$5:$K$100000,$K62)) | E62: =IF($K62="","",INDEX(전표_원본!$I$5:$I$100000,$K62)) | F62: =IF($K62="","",INDEX(전표_원본!$P$5:$P$100000,$K62)) | G62: =IF($K62="","",INDEX(전표_원본!$G$5:$G$100000,$K62)) | K62: =IFERROR(MATCH(LARGE(전표_원본!$T$5:$T$100000,12),전표_원본!$T$5:$T$100000,0),"")
A63: =IF($K63="","",INDEX(전표_원본!$D$5:$D$100000,$K63)) | B63: =IF($K63="","",INDEX(전표_원본!$C$5:$C$100000,$K63)) | C63: =IF($K63="","",INDEX(전표_원본!$E$5:$E$100000,$K63)) | D63: =IF($K63="","",INDEX(전표_원본!$K$5:$K$100000,$K63)) | E63: =IF($K63="","",INDEX(전표_원본!$I$5:$I$100000,$K63)) | F63: =IF($K63="","",INDEX(전표_원본!$P$5:$P$100000,$K63)) | G63: =IF($K63="","",INDEX(전표_원본!$G$5:$G$100000,$K63)) | K63: =IFERROR(MATCH(LARGE(전표_원본!$T$5:$T$100000,13),전표_원본!$T$5:$T$100000,0),"")
A64: =IF($K64="","",INDEX(전표_원본!$D$5:$D$100000,$K64)) | B64: =IF($K64="","",INDEX(전표_원본!$C$5:$C$100000,$K64)) | C64: =IF($K64="","",INDEX(전표_원본!$E$5:$E$100000,$K64)) | D64: =IF($K64="","",INDEX(전표_원본!$K$5:$K$100000,$K64)) | E64: =IF($K64="","",INDEX(전표_원본!$I$5:$I$100000,$K64)) | F64: =IF($K64="","",INDEX(전표_원본!$P$5:$P$100000,$K64)) | G64: =IF($K64="","",INDEX(전표_원본!$G$5:$G$100000,$K64)) | K64: =IFERROR(MATCH(LARGE(전표_원본!$T$5:$T$100000,14),전표_원본!$T$5:$T$100000,0),"")
A65: =IF($K65="","",INDEX(전표_원본!$D$5:$D$100000,$K65)) | B65: =IF($K65="","",INDEX(전표_원본!$C$5:$C$100000,$K65)) | C65: =IF($K65="","",INDEX(전표_원본!$E$5:$E$100000,$K65)) | D65: =IF($K65="","",INDEX(전표_원본!$K$5:$K$100000,$K65)) | E65: =IF($K65="","",INDEX(전표_원본!$I$5:$I$100000,$K65)) | F65: =IF($K65="","",INDEX(전표_원본!$P$5:$P$100000,$K65)) | G65: =IF($K65="","",INDEX(전표_원본!$G$5:$G$100000,$K65)) | K65: =IFERROR(MATCH(LARGE(전표_원본!$T$5:$T$100000,15),전표_원본!$T$5:$T$100000,0),"")
A67: 근거 전표 · 비교 기간 (상위 5건)
A68: 전기일 | B68: 전표번호 | C68: 유형 | D68: 거래처 | E68: 적요 | F68: 금액 | G68: 코스트센터
A69: =IF($K69="","",INDEX(전표_원본!$D$5:$D$100000,$K69)) | B69: =IF($K69="","",INDEX(전표_원본!$C$5:$C$100000,$K69)) | C69: =IF($K69="","",INDEX(전표_원본!$E$5:$E$100000,$K69)) | D69: =IF($K69="","",INDEX(전표_원본!$K$5:$K$100000,$K69)) | E69: =IF($K69="","",INDEX(전표_원본!$I$5:$I$100000,$K69)) | F69: =IF($K69="","",INDEX(전표_원본!$P$5:$P$100000,$K69)) | G69: =IF($K69="","",INDEX(전표_원본!$G$5:$G$100000,$K69)) | K69: =IFERROR(MATCH(LARGE(전표_원본!$U$5:$U$100000,1),전표_원본!$U$5:$U$100000,0),"")
A70: =IF($K70="","",INDEX(전표_원본!$D$5:$D$100000,$K70)) | B70: =IF($K70="","",INDEX(전표_원본!$C$5:$C$100000,$K70)) | C70: =IF($K70="","",INDEX(전표_원본!$E$5:$E$100000,$K70)) | D70: =IF($K70="","",INDEX(전표_원본!$K$5:$K$100000,$K70)) | E70: =IF($K70="","",INDEX(전표_원본!$I$5:$I$100000,$K70)) | F70: =IF($K70="","",INDEX(전표_원본!$P$5:$P$100000,$K70)) | G70: =IF($K70="","",INDEX(전표_원본!$G$5:$G$100000,$K70)) | K70: =IFERROR(MATCH(LARGE(전표_원본!$U$5:$U$100000,2),전표_원본!$U$5:$U$100000,0),"")
A71: =IF($K71="","",INDEX(전표_원본!$D$5:$D$100000,$K71)) | B71: =IF($K71="","",INDEX(전표_원본!$C$5:$C$100000,$K71)) | C71: =IF($K71="","",INDEX(전표_원본!$E$5:$E$100000,$K71)) | D71: =IF($K71="","",INDEX(전표_원본!$K$5:$K$100000,$K71)) | E71: =IF($K71="","",INDEX(전표_원본!$I$5:$I$100000,$K71)) | F71: =IF($K71="","",INDEX(전표_원본!$P$5:$P$100000,$K71)) | G71: =IF($K71="","",INDEX(전표_원본!$G$5:$G$100000,$K71)) | K71: =IFERROR(MATCH(LARGE(전표_원본!$U$5:$U$100000,3),전표_원본!$U$5:$U$100000,0),"")
A72: =IF($K72="","",INDEX(전표_원본!$D$5:$D$100000,$K72)) | B72: =IF($K72="","",INDEX(전표_원본!$C$5:$C$100000,$K72)) | C72: =IF($K72="","",INDEX(전표_원본!$E$5:$E$100000,$K72)) | D72: =IF($K72="","",INDEX(전표_원본!$K$5:$K$100000,$K72)) | E72: =IF($K72="","",INDEX(전표_원본!$I$5:$I$100000,$K72)) | F72: =IF($K72="","",INDEX(전표_원본!$P$5:$P$100000,$K72)) | G72: =IF($K72="","",INDEX(전표_원본!$G$5:$G$100000,$K72)) | K72: =IFERROR(MATCH(LARGE(전표_원본!$U$5:$U$100000,4),전표_원본!$U$5:$U$100000,0),"")
A73: =IF($K73="","",INDEX(전표_원본!$D$5:$D$100000,$K73)) | B73: =IF($K73="","",INDEX(전표_원본!$C$5:$C$100000,$K73)) | C73: =IF($K73="","",INDEX(전표_원본!$E$5:$E$100000,$K73)) | D73: =IF($K73="","",INDEX(전표_원본!$K$5:$K$100000,$K73)) | E73: =IF($K73="","",INDEX(전표_원본!$I$5:$I$100000,$K73)) | F73: =IF($K73="","",INDEX(전표_원본!$P$5:$P$100000,$K73)) | G73: =IF($K73="","",INDEX(전표_원본!$G$5:$G$100000,$K73)) | K73: =IFERROR(MATCH(LARGE(전표_원본!$U$5:$U$100000,5),전표_원본!$U$5:$U$100000,0),"")

Sheet 변동분석
A1: TRACE · 변동분석 (부서 × 계정)
A2: A·C열만 입력 · 전월/전분기/전년동월 비교 → 예산 점검 → 주의 점수 · 금액: 보고단위
A3: ="기준: "&INT((설정!$C$20-1)/12)&"-"&TEXT(MOD(설정!$C$20-1,12)+1,"00")&" · 단위: "&설정!$C$9
F5: ③ 변동 | P5: ④ 예산 점검 | Z5: ⑤ 주의 | AJ5: ④-2 분기 한도 점검 (예산 통제 단위: 부서 × 계정 × 분기) | AP5: ④-3 소진 추세 (선형: 설정 C19의 기울기로 누계실적 직선을 그어 연간가용에 닿는 시점) | AX5: ③-2 누계 비교
A6: 부서코드 | B6: 부서명 | C6: G/L 계정 | D6: 계정명 | E6: 키 | F6: 당월 | G6: 전월 | H6: 전월 대비 | I6: 전년 동월 | J6: 전년동월 대비 | K6: 당분기 | L6: 전분기 | M6: 전분기 대비 | N6: 주요 증가액 | O6: 이상치 (z) | P6: 연간가용 (배정+조정) | Q6: 누계실적 | R6: 잔여 | S6: 남은기간 예상 A (최근추세) | T6: 남은기간 예상 B (전년패턴) | U6: 예상 연간실적 | V6: 예상 소진율 | W6: 예산판정 | X6: 부족 예상액 | Y6: 소진 예상월 | Z6: 빠른 신호 (당월) | AA6: 주의 점수 | AB6: 정렬키 | AC6: 단건비중 | AD6: SA순증 | AE6: 음수건수 | AF6: 증가액 (30) | AG6: 증가율 (20) | AH6: 이상치 (25) | AI6: 예산 (25) | AJ6: 분기 한도 (배정+조정) | AK6: 분기 실적 | AL6: 분기 잔여 | AM6: 분기말 예상 | AN6: 분기 소진율 | AO6: 분기 판정 | AP6: 월 소진속도 (기울기) | AQ6: 절편 | AR6: 추세 연말 누계 | AS6: 고갈 예상(개월) | AT6: 고갈 예상일 | AU6: 추세 판정 | AV6: 분기 고갈 예상일 | AW6: 고갈 정렬키 | AX6: 전년동기 누계 | AY6: 전년동기 누계 대비 | AZ6: 전년 남은기간 월평균
A7: D100 | B7: =IF($A7="","",IFERROR(INDEX(부서매핑!$D$5:$D$504,MATCH($A7,부서매핑!$C$5:$C$504,0)),"부서매핑 없음")) | C7: 62101000 | D7: =IF($A7="","",IFERROR(INDEX(계정매핑!$B$5:$B$504,MATCH($C7&"",계정매핑!$A$5:$A$504,0)),"계정매핑 없음")) | E7: =IF($A7="","",$A7&"|"&$C7) | F7: =IF($A7="","",월별집계!$Z7) | G7: =IF($A7="","",월별집계!$Y7) | H7: =IF($A7="","",IF(G7<=0,IF(F7>0,1,0),F7/G7-1)) | I7: =IF($A7="","",월별집계!$N7) | J7: =IF($A7="","",IF(I7<=0,IF(F7>0,1,0),F7/I7-1)) | K7: =IF($A7="","",SUMIFS(월별집계!$C7:$Z7,월별집계!$C$5:$Z$5,">="&설정!$C$22,월별집계!$C$5:$Z$5,"<="&설정!$C$20)) | L7: =IF($A7="","",SUMIFS(월별집계!$C7:$Z7,월별집계!$C$5:$Z$5,">="&(설정!$C$22-3),월별집계!$C$5:$Z$5,"<="&(설정!$C$20-3))) | M7: =IF($A7="","",IF(L7<=0,IF(K7>0,1,0),K7/L7-1)) | N7: =IF($A7="","",MAX(F7-G7,F7-I7)) | O7: =IF($A7="","",IFERROR((월별집계!$Z7-AVERAGE(월별집계!N7:Y7))/STDEV(월별집계!N7:Y7),0)) | P7: =IF($A7="","",SUMIFS(예산판_원본!$O$5:$O$5000,예산판_원본!$L$5:$L$5000,$E7,예산판_원본!$M$5:$M$5000,설정!$C$6)) | Q7: =IF($A7="","",SUMIFS(월별집계!$C7:$Z7,월별집계!$C$5:$Z$5,">="&(설정!$C$6*12+1),월별집계!$C$5:$Z$5,"<="&설정!$C$20)) | R7: =IF($A7="","",P7-Q7) | S7: =IF($A7="","",AVERAGE(월별집계!X7:Z7)*(12-설정!$C$7)) | T7: =IF($A7="","",IFERROR(Q7/(SUMIFS(월별집계!$C7:$Z7,월별집계!$C$5:$Z$5,">="&((설정!$C$6-1)*12+1),월별집계!$C$5:$Z$5,"<="&(설정!$C$20-12))/SUMIFS(월별집계!$C7:$Z7,월별집계!$C$5:$Z$5,">="&((설정!$C$6-1)*12+1),월별집계!$C$5:$Z$5,"<="&((설정!$C$6-1)*12+12)))-Q7,S7)) | U7: =IF($A7="","",Q7+MAX(S7,T7)) | V7: =IF($A7="","",IF(P7=0,0,U7/P7)) | W7: =IF($A7="","",IF(AND(P7=0,Q7>0),"무예산",IF(P7=0,"-",IF(V7>설정!$C$12,"부족 예상",IF(V7>설정!$C$11,"주의","여유"))))) | X7: =IF($A7="","",IF(P7=0,0,MAX(0,U7-P7))) | Y7: =IF($A7="","",IF(OR(W7<>"부족 예상",설정!$C$7=12),"",IF(R7<=0,"이미 초과",MIN(12,설정!$C$7+ROUNDUP(R7/(MAX(S7,T7)/(12-설정!$C$7)),0))&"월"))) | Z7: =IF($A7="","",TRIM(IF(AND(N(AC7)>=설정!$C$14,N7>=설정!$C$10),"단건"&TEXT(MIN(AC7,1),"0%")&" ","")&IF(AND(N7>0,AD7>0),IF(AD7/N7>=설정!$C$16,"SA대체 ",""),"")&IF(AE7>0,"역분개"&AE7&"건 ","")&IF(O7>=설정!$C$13,"이상치 ","")&IF(AND(I7=0,F7>0),"신규지출 ",""))) | AA7: =IF($A7="","",ROUND((AF7+AG7+AH7+AI7)*IF(AND(F7<설정!$C$10,N7<설정!$C$10),0.3,1),1)) | AB7: =IF($A7="","",AA7+ROW()/1000000) | AC7: =IF(OR($A7="",N7<=0),"",SUMPRODUCT(MAX((전표_원본!$O$5:$O$100000=$E7)*(전표_원본!$M$5:$M$100000=설정!$C$20)*전표_원본!$P$5:$P$100000))/N7) | AD7: =IF($A7="","",SUMIFS(전표_원본!$P$5:$P$100000,전표_원본!$O$5:$O$100000,$E7,전표_원본!$M$5:$M$100000,설정!$C$20,전표_원본!$E$5:$E$100000,"SA")-SUMIFS(전표_원본!$P$5:$P$100000,전표_원본!$O$5:$O$100000,$E7,전표_원본!$M$5:$M$100000,설정!$C$20-1,전표_원본!$E$5:$E$100000,"SA")) | AE7: =IF($A7="","",COUNTIFS(전표_원본!$O$5:$O$100000,$E7,전표_원본!$M$5:$M$100000,설정!$C$20,전표_원본!$P$5:$P$100000,"<0")) | AF7: =IF($A7="","",MIN(MAX(0,N7)/(설정!$C$10*5),1)*30) | AG7: =IF($A7="","",MIN(MAX(0,H7,J7),1)*20) | AH7: =IF($A7="","",MIN(MAX(0,O7)/3,1)*25) | AI7: =IF($A7="","",IF(OR(W7="부족 예상",W7="무예산",AO7="한도 초과",AO7="초과 예상",AO7="무예산"),25,IF(OR(W7="주의",AO7="주의"),15,0))) | AJ7: =IF($A7="","",SUMIFS(예산판_원본!$O$5:$O$5000,예산판_원본!$L$5:$L$5000,$E7,예산판_원본!$M$5:$M$5000,설정!$C$6,예산판_원본!$N$5:$N$5000,설정!$C$21)) | AK7: =IF($A7="","",K7) | AL7: =IF($A7="","",AJ7-AK7) | AM7: =IF($A7="","",AK7+AVERAGE(월별집계!X7:Z7)*MAX(0,설정!$C$22+2-설정!$C$20)) | AN7: =IF($A7="","",IF(AJ7=0,0,AM7/AJ7)) | AO7: =IF($A7="","",IF(AND(AJ7=0,AK7>0),"무예산",IF(AJ7=0,"-",IF(AK7>AJ7,"한도 초과",IF(AN7>설정!$C$12,"초과 예상",IF(AN7>설정!$C$11,"주의","여유")))))) | AP7: =IF($A7="","",IF(설정!$C$19="최근월",(INDEX(월별집계!$AB7:$AM7,설정!$C$7)-INDEX(월별집계!$AB7:$AM7,MAX(1,설정!$C$7-1))*(설정!$C$7>1)),IF(설정!$C$19="최근분기",((INDEX(월별집계!$AB7:$AM7,설정!$C$7)-INDEX(월별집계!$AB7:$AM7,MAX(1,설정!$C$7-3))*(설정!$C$7>3))/MIN(3,설정!$C$7)),IF(설정!$C$19="전년추세",AZ7,((설정!$C$7+1)*SUMPRODUCT(월별집계!$AB$5:$AM$5,월별집계!$AB7:$AM7)-(설정!$C$7*(설정!$C$7+1)/2)*SUM(월별집계!$AB7:$AM7))/((설정!$C$7+1)*(설정!$C$7*(설정!$C$7+1)*(2*설정!$C$7+1)/6)-(설정!$C$7*(설정!$C$7+1)/2)^2))))) | AQ7: =IF($A7="","",IF(설정!$C$19="연내누적",(SUM(월별집계!$AB7:$AM7)-AP7*(설정!$C$7*(설정!$C$7+1)/2))/(설정!$C$7+1),INDEX(월별집계!$AB7:$AM7,설정!$C$7)-AP7*설정!$C$7)) | AR7: =IF($A7="","",AQ7+AP7*12) | AS7: =IF($A7="","",IF(OR(P7<=0,Q7>=P7,AP7<=0),"",MAX(설정!$C$7,(P7-AQ7)/AP7))) | AT7: =IF($A7="","",IF(AS7="",IF(AU7="이미 소진","소진됨",""),YEAR((DATE(설정!$C$6,1,1)+ROUND(AS7*365/12,0)-1))&"-"&TEXT(MONTH((DATE(설정!$C$6,1,1)+ROUND(AS7*365/12,0)-1)),"00")&"-"&TEXT(DAY((DATE(설정!$C$6,1,1)+ROUND(AS7*365/12,0)-1)),"00"))) | AU7: =IF($A7="","",IF(AND(P7<=0,Q7>0),"무예산",IF(P7<=0,"-",IF(Q7>=P7,"이미 소진",IF(AP7<=0,"소진 안 됨",IF(AS7<=12,"연내 고갈","연내 여유")))))) | AV7: =IF($A7="","",IF(AJ7<=0,"",IF(AK7>=AJ7,"한도 소진",IF(AK7<=0,"",IF(AJ7/(AK7/(설정!$C$20-설정!$C$22+1))>3,"분기 내 여유",YEAR((DATE(설정!$C$6,설정!$C$22-설정!$C$6*12,1)+ROUND(MAX((설정!$C$20-설정!$C$22+1),AJ7/(AK7/(설정!$C$20-설정!$C$22+1)))*365/12,0)-1))&"-"&TEXT(MONTH((DATE(설정!$C$6,설정!$C$22-설정!$C$6*12,1)+ROUND(MAX((설정!$C$20-설정!$C$22+1),AJ7/(AK7/(설정!$C$20-설정!$C$22+1)))*365/12,0)-1)),"00")&"-"&TEXT(DAY((DATE(설정!$C$6,설정!$C$22-설정!$C$6*12,1)+ROUND(MAX((설정!$C$20-설정!$C$22+1),AJ7/(AK7/(설정!$C$20-설정!$C$22+1)))*365/12,0)-1)),"00")))))) | AW7: =IF($A7="",999+ROW()/1000000,IF(AU7="이미 소진",ROW()/1000000,IF(AU7="연내 고갈",AS7+ROW()/1000000,99+ROW()/1000000))) | AX7: =IF($A7="","",SUMIFS(월별집계!$C7:$Z7,월별집계!$C$5:$Z$5,">="&((설정!$C$6-1)*12+1),월별집계!$C$5:$Z$5,"<="&(설정!$C$20-12))) | AY7: =IF($A7="","",IF(AX7<=0,IF(Q7>0,1,0),Q7/AX7-1)) | AZ7: =IF($A7="","",SUMIFS(월별집계!$C7:$Z7,월별집계!$C$5:$Z$5,">"&(설정!$C$20-12),월별집계!$C$5:$Z$5,"<="&((설정!$C$6-1)*12+12))/MAX(1,12-설정!$C$7))
A8: D100 | B8: =IF($A8="","",IFERROR(INDEX(부서매핑!$D$5:$D$504,MATCH($A8,부서매핑!$C$5:$C$504,0)),"부서매핑 없음")) | C8: 62102000 | D8: =IF($A8="","",IFERROR(INDEX(계정매핑!$B$5:$B$504,MATCH($C8&"",계정매핑!$A$5:$A$504,0)),"계정매핑 없음")) | E8: =IF($A8="","",$A8&"|"&$C8) | F8: =IF($A8="","",월별집계!$Z8) | G8: =IF($A8="","",월별집계!$Y8) | H8: =IF($A8="","",IF(G8<=0,IF(F8>0,1,0),F8/G8-1)) | I8: =IF($A8="","",월별집계!$N8) | J8: =IF($A8="","",IF(I8<=0,IF(F8>0,1,0),F8/I8-1)) | K8: =IF($A8="","",SUMIFS(월별집계!$C8:$Z8,월별집계!$C$5:$Z$5,">="&설정!$C$22,월별집계!$C$5:$Z$5,"<="&설정!$C$20)) | L8: =IF($A8="","",SUMIFS(월별집계!$C8:$Z8,월별집계!$C$5:$Z$5,">="&(설정!$C$22-3),월별집계!$C$5:$Z$5,"<="&(설정!$C$20-3))) | M8: =IF($A8="","",IF(L8<=0,IF(K8>0,1,0),K8/L8-1)) | N8: =IF($A8="","",MAX(F8-G8,F8-I8)) | O8: =IF($A8="","",IFERROR((월별집계!$Z8-AVERAGE(월별집계!N8:Y8))/STDEV(월별집계!N8:Y8),0)) | P8: =IF($A8="","",SUMIFS(예산판_원본!$O$5:$O$5000,예산판_원본!$L$5:$L$5000,$E8,예산판_원본!$M$5:$M$5000,설정!$C$6)) | Q8: =IF($A8="","",SUMIFS(월별집계!$C8:$Z8,월별집계!$C$5:$Z$5,">="&(설정!$C$6*12+1),월별집계!$C$5:$Z$5,"<="&설정!$C$20)) | R8: =IF($A8="","",P8-Q8) | S8: =IF($A8="","",AVERAGE(월별집계!X8:Z8)*(12-설정!$C$7)) | T8: =IF($A8="","",IFERROR(Q8/(SUMIFS(월별집계!$C8:$Z8,월별집계!$C$5:$Z$5,">="&((설정!$C$6-1)*12+1),월별집계!$C$5:$Z$5,"<="&(설정!$C$20-12))/SUMIFS(월별집계!$C8:$Z8,월별집계!$C$5:$Z$5,">="&((설정!$C$6-1)*12+1),월별집계!$C$5:$Z$5,"<="&((설정!$C$6-1)*12+12)))-Q8,S8)) | U8: =IF($A8="","",Q8+MAX(S8,T8)) | V8: =IF($A8="","",IF(P8=0,0,U8/P8)) | W8: =IF($A8="","",IF(AND(P8=0,Q8>0),"무예산",IF(P8=0,"-",IF(V8>설정!$C$12,"부족 예상",IF(V8>설정!$C$11,"주의","여유"))))) | X8: =IF($A8="","",IF(P8=0,0,MAX(0,U8-P8))) | Y8: =IF($A8="","",IF(OR(W8<>"부족 예상",설정!$C$7=12),"",IF(R8<=0,"이미 초과",MIN(12,설정!$C$7+ROUNDUP(R8/(MAX(S8,T8)/(12-설정!$C$7)),0))&"월"))) | Z8: =IF($A8="","",TRIM(IF(AND(N(AC8)>=설정!$C$14,N8>=설정!$C$10),"단건"&TEXT(MIN(AC8,1),"0%")&" ","")&IF(AND(N8>0,AD8>0),IF(AD8/N8>=설정!$C$16,"SA대체 ",""),"")&IF(AE8>0,"역분개"&AE8&"건 ","")&IF(O8>=설정!$C$13,"이상치 ","")&IF(AND(I8=0,F8>0),"신규지출 ",""))) | AA8: =IF($A8="","",ROUND((AF8+AG8+AH8+AI8)*IF(AND(F8<설정!$C$10,N8<설정!$C$10),0.3,1),1)) | AB8: =IF($A8="","",AA8+ROW()/1000000) | AC8: =IF(OR($A8="",N8<=0),"",SUMPRODUCT(MAX((전표_원본!$O$5:$O$100000=$E8)*(전표_원본!$M$5:$M$100000=설정!$C$20)*전표_원본!$P$5:$P$100000))/N8) | AD8: =IF($A8="","",SUMIFS(전표_원본!$P$5:$P$100000,전표_원본!$O$5:$O$100000,$E8,전표_원본!$M$5:$M$100000,설정!$C$20,전표_원본!$E$5:$E$100000,"SA")-SUMIFS(전표_원본!$P$5:$P$100000,전표_원본!$O$5:$O$100000,$E8,전표_원본!$M$5:$M$100000,설정!$C$20-1,전표_원본!$E$5:$E$100000,"SA")) | AE8: =IF($A8="","",COUNTIFS(전표_원본!$O$5:$O$100000,$E8,전표_원본!$M$5:$M$100000,설정!$C$20,전표_원본!$P$5:$P$100000,"<0")) | AF8: =IF($A8="","",MIN(MAX(0,N8)/(설정!$C$10*5),1)*30) | AG8: =IF($A8="","",MIN(MAX(0,H8,J8),1)*20) | AH8: =IF($A8="","",MIN(MAX(0,O8)/3,1)*25) | AI8: =IF($A8="","",IF(OR(W8="부족 예상",W8="무예산",AO8="한도 초과",AO8="초과 예상",AO8="무예산"),25,IF(OR(W8="주의",AO8="주의"),15,0))) | AJ8: =IF($A8="","",SUMIFS(예산판_원본!$O$5:$O$5000,예산판_원본!$L$5:$L$5000,$E8,예산판_원본!$M$5:$M$5000,설정!$C$6,예산판_원본!$N$5:$N$5000,설정!$C$21)) | AK8: =IF($A8="","",K8) | AL8: =IF($A8="","",AJ8-AK8) | AM8: =IF($A8="","",AK8+AVERAGE(월별집계!X8:Z8)*MAX(0,설정!$C$22+2-설정!$C$20)) | AN8: =IF($A8="","",IF(AJ8=0,0,AM8/AJ8)) | AO8: =IF($A8="","",IF(AND(AJ8=0,AK8>0),"무예산",IF(AJ8=0,"-",IF(AK8>AJ8,"한도 초과",IF(AN8>설정!$C$12,"초과 예상",IF(AN8>설정!$C$11,"주의","여유")))))) | AP8: =IF($A8="","",IF(설정!$C$19="최근월",(INDEX(월별집계!$AB8:$AM8,설정!$C$7)-INDEX(월별집계!$AB8:$AM8,MAX(1,설정!$C$7-1))*(설정!$C$7>1)),IF(설정!$C$19="최근분기",((INDEX(월별집계!$AB8:$AM8,설정!$C$7)-INDEX(월별집계!$AB8:$AM8,MAX(1,설정!$C$7-3))*(설정!$C$7>3))/MIN(3,설정!$C$7)),IF(설정!$C$19="전년추세",AZ8,((설정!$C$7+1)*SUMPRODUCT(월별집계!$AB$5:$AM$5,월별집계!$AB8:$AM8)-(설정!$C$7*(설정!$C$7+1)/2)*SUM(월별집계!$AB8:$AM8))/((설정!$C$7+1)*(설정!$C$7*(설정!$C$7+1)*(2*설정!$C$7+1)/6)-(설정!$C$7*(설정!$C$7+1)/2)^2))))) | AQ8: =IF($A8="","",IF(설정!$C$19="연내누적",(SUM(월별집계!$AB8:$AM8)-AP8*(설정!$C$7*(설정!$C$7+1)/2))/(설정!$C$7+1),INDEX(월별집계!$AB8:$AM8,설정!$C$7)-AP8*설정!$C$7)) | AR8: =IF($A8="","",AQ8+AP8*12) | AS8: =IF($A8="","",IF(OR(P8<=0,Q8>=P8,AP8<=0),"",MAX(설정!$C$7,(P8-AQ8)/AP8))) | AT8: =IF($A8="","",IF(AS8="",IF(AU8="이미 소진","소진됨",""),YEAR((DATE(설정!$C$6,1,1)+ROUND(AS8*365/12,0)-1))&"-"&TEXT(MONTH((DATE(설정!$C$6,1,1)+ROUND(AS8*365/12,0)-1)),"00")&"-"&TEXT(DAY((DATE(설정!$C$6,1,1)+ROUND(AS8*365/12,0)-1)),"00"))) | AU8: =IF($A8="","",IF(AND(P8<=0,Q8>0),"무예산",IF(P8<=0,"-",IF(Q8>=P8,"이미 소진",IF(AP8<=0,"소진 안 됨",IF(AS8<=12,"연내 고갈","연내 여유")))))) | AV8: =IF($A8="","",IF(AJ8<=0,"",IF(AK8>=AJ8,"한도 소진",IF(AK8<=0,"",IF(AJ8/(AK8/(설정!$C$20-설정!$C$22+1))>3,"분기 내 여유",YEAR((DATE(설정!$C$6,설정!$C$22-설정!$C$6*12,1)+ROUND(MAX((설정!$C$20-설정!$C$22+1),AJ8/(AK8/(설정!$C$20-설정!$C$22+1)))*365/12,0)-1))&"-"&TEXT(MONTH((DATE(설정!$C$6,설정!$C$22-설정!$C$6*12,1)+ROUND(MAX((설정!$C$20-설정!$C$22+1),AJ8/(AK8/(설정!$C$20-설정!$C$22+1)))*365/12,0)-1)),"00")&"-"&TEXT(DAY((DATE(설정!$C$6,설정!$C$22-설정!$C$6*12,1)+ROUND(MAX((설정!$C$20-설정!$C$22+1),AJ8/(AK8/(설정!$C$20-설정!$C$22+1)))*365/12,0)-1)),"00")))))) | AW8: =IF($A8="",999+ROW()/1000000,IF(AU8="이미 소진",ROW()/1000000,IF(AU8="연내 고갈",AS8+ROW()/1000000,99+ROW()/1000000))) | AX8: =IF($A8="","",SUMIFS(월별집계!$C8:$Z8,월별집계!$C$5:$Z$5,">="&((설정!$C$6-1)*12+1),월별집계!$C$5:$Z$5,"<="&(설정!$C$20-12))) | AY8: =IF($A8="","",IF(AX8<=0,IF(Q8>0,1,0),Q8/AX8-1)) | AZ8: =IF($A8="","",SUMIFS(월별집계!$C8:$Z8,월별집계!$C$5:$Z$5,">"&(설정!$C$20-12),월별집계!$C$5:$Z$5,"<="&((설정!$C$6-1)*12+12))/MAX(1,12-설정!$C$7))
A9: D100 | B9: =IF($A9="","",IFERROR(INDEX(부서매핑!$D$5:$D$504,MATCH($A9,부서매핑!$C$5:$C$504,0)),"부서매핑 없음")) | C9: 62201000 | D9: =IF($A9="","",IFERROR(INDEX(계정매핑!$B$5:$B$504,MATCH($C9&"",계정매핑!$A$5:$A$504,0)),"계정매핑 없음")) | E9: =IF($A9="","",$A9&"|"&$C9) | F9: =IF($A9="","",월별집계!$Z9) | G9: =IF($A9="","",월별집계!$Y9) | H9: =IF($A9="","",IF(G9<=0,IF(F9>0,1,0),F9/G9-1)) | I9: =IF($A9="","",월별집계!$N9) | J9: =IF($A9="","",IF(I9<=0,IF(F9>0,1,0),F9/I9-1)) | K9: =IF($A9="","",SUMIFS(월별집계!$C9:$Z9,월별집계!$C$5:$Z$5,">="&설정!$C$22,월별집계!$C$5:$Z$5,"<="&설정!$C$20)) | L9: =IF($A9="","",SUMIFS(월별집계!$C9:$Z9,월별집계!$C$5:$Z$5,">="&(설정!$C$22-3),월별집계!$C$5:$Z$5,"<="&(설정!$C$20-3))) | M9: =IF($A9="","",IF(L9<=0,IF(K9>0,1,0),K9/L9-1)) | N9: =IF($A9="","",MAX(F9-G9,F9-I9)) | O9: =IF($A9="","",IFERROR((월별집계!$Z9-AVERAGE(월별집계!N9:Y9))/STDEV(월별집계!N9:Y9),0)) | P9: =IF($A9="","",SUMIFS(예산판_원본!$O$5:$O$5000,예산판_원본!$L$5:$L$5000,$E9,예산판_원본!$M$5:$M$5000,설정!$C$6)) | Q9: =IF($A9="","",SUMIFS(월별집계!$C9:$Z9,월별집계!$C$5:$Z$5,">="&(설정!$C$6*12+1),월별집계!$C$5:$Z$5,"<="&설정!$C$20)) | R9: =IF($A9="","",P9-Q9) | S9: =IF($A9="","",AVERAGE(월별집계!X9:Z9)*(12-설정!$C$7)) | T9: =IF($A9="","",IFERROR(Q9/(SUMIFS(월별집계!$C9:$Z9,월별집계!$C$5:$Z$5,">="&((설정!$C$6-1)*12+1),월별집계!$C$5:$Z$5,"<="&(설정!$C$20-12))/SUMIFS(월별집계!$C9:$Z9,월별집계!$C$5:$Z$5,">="&((설정!$C$6-1)*12+1),월별집계!$C$5:$Z$5,"<="&((설정!$C$6-1)*12+12)))-Q9,S9)) | U9: =IF($A9="","",Q9+MAX(S9,T9)) | V9: =IF($A9="","",IF(P9=0,0,U9/P9)) | W9: =IF($A9="","",IF(AND(P9=0,Q9>0),"무예산",IF(P9=0,"-",IF(V9>설정!$C$12,"부족 예상",IF(V9>설정!$C$11,"주의","여유"))))) | X9: =IF($A9="","",IF(P9=0,0,MAX(0,U9-P9))) | Y9: =IF($A9="","",IF(OR(W9<>"부족 예상",설정!$C$7=12),"",IF(R9<=0,"이미 초과",MIN(12,설정!$C$7+ROUNDUP(R9/(MAX(S9,T9)/(12-설정!$C$7)),0))&"월"))) | Z9: =IF($A9="","",TRIM(IF(AND(N(AC9)>=설정!$C$14,N9>=설정!$C$10),"단건"&TEXT(MIN(AC9,1),"0%")&" ","")&IF(AND(N9>0,AD9>0),IF(AD9/N9>=설정!$C$16,"SA대체 ",""),"")&IF(AE9>0,"역분개"&AE9&"건 ","")&IF(O9>=설정!$C$13,"이상치 ","")&IF(AND(I9=0,F9>0),"신규지출 ",""))) | AA9: =IF($A9="","",ROUND((AF9+AG9+AH9+AI9)*IF(AND(F9<설정!$C$10,N9<설정!$C$10),0.3,1),1)) | AB9: =IF($A9="","",AA9+ROW()/1000000) | AC9: =IF(OR($A9="",N9<=0),"",SUMPRODUCT(MAX((전표_원본!$O$5:$O$100000=$E9)*(전표_원본!$M$5:$M$100000=설정!$C$20)*전표_원본!$P$5:$P$100000))/N9) | AD9: =IF($A9="","",SUMIFS(전표_원본!$P$5:$P$100000,전표_원본!$O$5:$O$100000,$E9,전표_원본!$M$5:$M$100000,설정!$C$20,전표_원본!$E$5:$E$100000,"SA")-SUMIFS(전표_원본!$P$5:$P$100000,전표_원본!$O$5:$O$100000,$E9,전표_원본!$M$5:$M$100000,설정!$C$20-1,전표_원본!$E$5:$E$100000,"SA")) | AE9: =IF($A9="","",COUNTIFS(전표_원본!$O$5:$O$100000,$E9,전표_원본!$M$5:$M$100000,설정!$C$20,전표_원본!$P$5:$P$100000,"<0")) | AF9: =IF($A9="","",MIN(MAX(0,N9)/(설정!$C$10*5),1)*30) | AG9: =IF($A9="","",MIN(MAX(0,H9,J9),1)*20) | AH9: =IF($A9="","",MIN(MAX(0,O9)/3,1)*25) | AI9: =IF($A9="","",IF(OR(W9="부족 예상",W9="무예산",AO9="한도 초과",AO9="초과 예상",AO9="무예산"),25,IF(OR(W9="주의",AO9="주의"),15,0))) | AJ9: =IF($A9="","",SUMIFS(예산판_원본!$O$5:$O$5000,예산판_원본!$L$5:$L$5000,$E9,예산판_원본!$M$5:$M$5000,설정!$C$6,예산판_원본!$N$5:$N$5000,설정!$C$21)) | AK9: =IF($A9="","",K9) | AL9: =IF($A9="","",AJ9-AK9) | AM9: =IF($A9="","",AK9+AVERAGE(월별집계!X9:Z9)*MAX(0,설정!$C$22+2-설정!$C$20)) | AN9: =IF($A9="","",IF(AJ9=0,0,AM9/AJ9)) | AO9: =IF($A9="","",IF(AND(AJ9=0,AK9>0),"무예산",IF(AJ9=0,"-",IF(AK9>AJ9,"한도 초과",IF(AN9>설정!$C$12,"초과 예상",IF(AN9>설정!$C$11,"주의","여유")))))) | AP9: =IF($A9="","",IF(설정!$C$19="최근월",(INDEX(월별집계!$AB9:$AM9,설정!$C$7)-INDEX(월별집계!$AB9:$AM9,MAX(1,설정!$C$7-1))*(설정!$C$7>1)),IF(설정!$C$19="최근분기",((INDEX(월별집계!$AB9:$AM9,설정!$C$7)-INDEX(월별집계!$AB9:$AM9,MAX(1,설정!$C$7-3))*(설정!$C$7>3))/MIN(3,설정!$C$7)),IF(설정!$C$19="전년추세",AZ9,((설정!$C$7+1)*SUMPRODUCT(월별집계!$AB$5:$AM$5,월별집계!$AB9:$AM9)-(설정!$C$7*(설정!$C$7+1)/2)*SUM(월별집계!$AB9:$AM9))/((설정!$C$7+1)*(설정!$C$7*(설정!$C$7+1)*(2*설정!$C$7+1)/6)-(설정!$C$7*(설정!$C$7+1)/2)^2))))) | AQ9: =IF($A9="","",IF(설정!$C$19="연내누적",(SUM(월별집계!$AB9:$AM9)-AP9*(설정!$C$7*(설정!$C$7+1)/2))/(설정!$C$7+1),INDEX(월별집계!$AB9:$AM9,설정!$C$7)-AP9*설정!$C$7)) | AR9: =IF($A9="","",AQ9+AP9*12) | AS9: =IF($A9="","",IF(OR(P9<=0,Q9>=P9,AP9<=0),"",MAX(설정!$C$7,(P9-AQ9)/AP9))) | AT9: =IF($A9="","",IF(AS9="",IF(AU9="이미 소진","소진됨",""),YEAR((DATE(설정!$C$6,1,1)+ROUND(AS9*365/12,0)-1))&"-"&TEXT(MONTH((DATE(설정!$C$6,1,1)+ROUND(AS9*365/12,0)-1)),"00")&"-"&TEXT(DAY((DATE(설정!$C$6,1,1)+ROUND(AS9*365/12,0)-1)),"00"))) | AU9: =IF($A9="","",IF(AND(P9<=0,Q9>0),"무예산",IF(P9<=0,"-",IF(Q9>=P9,"이미 소진",IF(AP9<=0,"소진 안 됨",IF(AS9<=12,"연내 고갈","연내 여유")))))) | AV9: =IF($A9="","",IF(AJ9<=0,"",IF(AK9>=AJ9,"한도 소진",IF(AK9<=0,"",IF(AJ9/(AK9/(설정!$C$20-설정!$C$22+1))>3,"분기 내 여유",YEAR((DATE(설정!$C$6,설정!$C$22-설정!$C$6*12,1)+ROUND(MAX((설정!$C$20-설정!$C$22+1),AJ9/(AK9/(설정!$C$20-설정!$C$22+1)))*365/12,0)-1))&"-"&TEXT(MONTH((DATE(설정!$C$6,설정!$C$22-설정!$C$6*12,1)+ROUND(MAX((설정!$C$20-설정!$C$22+1),AJ9/(AK9/(설정!$C$20-설정!$C$22+1)))*365/12,0)-1)),"00")&"-"&TEXT(DAY((DATE(설정!$C$6,설정!$C$22-설정!$C$6*12,1)+ROUND(MAX((설정!$C$20-설정!$C$22+1),AJ9/(AK9/(설정!$C$20-설정!$C$22+1)))*365/12,0)-1)),"00")))))) | AW9: =IF($A9="",999+ROW()/1000000,IF(AU9="이미 소진",ROW()/1000000,IF(AU9="연내 고갈",AS9+ROW()/1000000,99+ROW()/1000000))) | AX9: =IF($A9="","",SUMIFS(월별집계!$C9:$Z9,월별집계!$C$5:$Z$5,">="&((설정!$C$6-1)*12+1),월별집계!$C$5:$Z$5,"<="&(설정!$C$20-12))) | AY9: =IF($A9="","",IF(AX9<=0,IF(Q9>0,1,0),Q9/AX9-1)) | AZ9: =IF($A9="","",SUMIFS(월별집계!$C9:$Z9,월별집계!$C$5:$Z$5,">"&(설정!$C$20-12),월별집계!$C$5:$Z$5,"<="&((설정!$C$6-1)*12+12))/MAX(1,12-설정!$C$7))
A10: D100 | B10: =IF($A10="","",IFERROR(INDEX(부서매핑!$D$5:$D$504,MATCH($A10,부서매핑!$C$5:$C$504,0)),"부서매핑 없음")) | C10: 62301000 | D10: =IF($A10="","",IFERROR(INDEX(계정매핑!$B$5:$B$504,MATCH($C10&"",계정매핑!$A$5:$A$504,0)),"계정매핑 없음")) | E10: =IF($A10="","",$A10&"|"&$C10) | F10: =IF($A10="","",월별집계!$Z10) | G10: =IF($A10="","",월별집계!$Y10) | H10: =IF($A10="","",IF(G10<=0,IF(F10>0,1,0),F10/G10-1)) | I10: =IF($A10="","",월별집계!$N10) | J10: =IF($A10="","",IF(I10<=0,IF(F10>0,1,0),F10/I10-1)) | K10: =IF($A10="","",SUMIFS(월별집계!$C10:$Z10,월별집계!$C$5:$Z$5,">="&설정!$C$22,월별집계!$C$5:$Z$5,"<="&설정!$C$20)) | L10: =IF($A10="","",SUMIFS(월별집계!$C10:$Z10,월별집계!$C$5:$Z$5,">="&(설정!$C$22-3),월별집계!$C$5:$Z$5,"<="&(설정!$C$20-3))) | M10: =IF($A10="","",IF(L10<=0,IF(K10>0,1,0),K10/L10-1)) | N10: =IF($A10="","",MAX(F10-G10,F10-I10)) | O10: =IF($A10="","",IFERROR((월별집계!$Z10-AVERAGE(월별집계!N10:Y10))/STDEV(월별집계!N10:Y10),0)) | P10: =IF($A10="","",SUMIFS(예산판_원본!$O$5:$O$5000,예산판_원본!$L$5:$L$5000,$E10,예산판_원본!$M$5:$M$5000,설정!$C$6)) | Q10: =IF($A10="","",SUMIFS(월별집계!$C10:$Z10,월별집계!$C$5:$Z$5,">="&(설정!$C$6*12+1),월별집계!$C$5:$Z$5,"<="&설정!$C$20)) | R10: =IF($A10="","",P10-Q10) | S10: =IF($A10="","",AVERAGE(월별집계!X10:Z10)*(12-설정!$C$7)) | T10: =IF($A10="","",IFERROR(Q10/(SUMIFS(월별집계!$C10:$Z10,월별집계!$C$5:$Z$5,">="&((설정!$C$6-1)*12+1),월별집계!$C$5:$Z$5,"<="&(설정!$C$20-12))/SUMIFS(월별집계!$C10:$Z10,월별집계!$C$5:$Z$5,">="&((설정!$C$6-1)*12+1),월별집계!$C$5:$Z$5,"<="&((설정!$C$6-1)*12+12)))-Q10,S10)) | U10: =IF($A10="","",Q10+MAX(S10,T10)) | V10: =IF($A10="","",IF(P10=0,0,U10/P10)) | W10: =IF($A10="","",IF(AND(P10=0,Q10>0),"무예산",IF(P10=0,"-",IF(V10>설정!$C$12,"부족 예상",IF(V10>설정!$C$11,"주의","여유"))))) | X10: =IF($A10="","",IF(P10=0,0,MAX(0,U10-P10))) | Y10: =IF($A10="","",IF(OR(W10<>"부족 예상",설정!$C$7=12),"",IF(R10<=0,"이미 초과",MIN(12,설정!$C$7+ROUNDUP(R10/(MAX(S10,T10)/(12-설정!$C$7)),0))&"월"))) | Z10: =IF($A10="","",TRIM(IF(AND(N(AC10)>=설정!$C$14,N10>=설정!$C$10),"단건"&TEXT(MIN(AC10,1),"0%")&" ","")&IF(AND(N10>0,AD10>0),IF(AD10/N10>=설정!$C$16,"SA대체 ",""),"")&IF(AE10>0,"역분개"&AE10&"건 ","")&IF(O10>=설정!$C$13,"이상치 ","")&IF(AND(I10=0,F10>0),"신규지출 ",""))) | AA10: =IF($A10="","",ROUND((AF10+AG10+AH10+AI10)*IF(AND(F10<설정!$C$10,N10<설정!$C$10),0.3,1),1)) | AB10: =IF($A10="","",AA10+ROW()/1000000) | AC10: =IF(OR($A10="",N10<=0),"",SUMPRODUCT(MAX((전표_원본!$O$5:$O$100000=$E10)*(전표_원본!$M$5:$M$100000=설정!$C$20)*전표_원본!$P$5:$P$100000))/N10) | AD10: =IF($A10="","",SUMIFS(전표_원본!$P$5:$P$100000,전표_원본!$O$5:$O$100000,$E10,전표_원본!$M$5:$M$100000,설정!$C$20,전표_원본!$E$5:$E$100000,"SA")-SUMIFS(전표_원본!$P$5:$P$100000,전표_원본!$O$5:$O$100000,$E10,전표_원본!$M$5:$M$100000,설정!$C$20-1,전표_원본!$E$5:$E$100000,"SA")) | AE10: =IF($A10="","",COUNTIFS(전표_원본!$O$5:$O$100000,$E10,전표_원본!$M$5:$M$100000,설정!$C$20,전표_원본!$P$5:$P$100000,"<0")) | AF10: =IF($A10="","",MIN(MAX(0,N10)/(설정!$C$10*5),1)*30) | AG10: =IF($A10="","",MIN(MAX(0,H10,J10),1)*20) | AH10: =IF($A10="","",MIN(MAX(0,O10)/3,1)*25) | AI10: =IF($A10="","",IF(OR(W10="부족 예상",W10="무예산",AO10="한도 초과",AO10="초과 예상",AO10="무예산"),25,IF(OR(W10="주의",AO10="주의"),15,0))) | AJ10: =IF($A10="","",SUMIFS(예산판_원본!$O$5:$O$5000,예산판_원본!$L$5:$L$5000,$E10,예산판_원본!$M$5:$M$5000,설정!$C$6,예산판_원본!$N$5:$N$5000,설정!$C$21)) | AK10: =IF($A10="","",K10) | AL10: =IF($A10="","",AJ10-AK10) | AM10: =IF($A10="","",AK10+AVERAGE(월별집계!X10:Z10)*MAX(0,설정!$C$22+2-설정!$C$20)) | AN10: =IF($A10="","",IF(AJ10=0,0,AM10/AJ10)) | AO10: =IF($A10="","",IF(AND(AJ10=0,AK10>0),"무예산",IF(AJ10=0,"-",IF(AK10>AJ10,"한도 초과",IF(AN10>설정!$C$12,"초과 예상",IF(AN10>설정!$C$11,"주의","여유")))))) | AP10: =IF($A10="","",IF(설정!$C$19="최근월",(INDEX(월별집계!$AB10:$AM10,설정!$C$7)-INDEX(월별집계!$AB10:$AM10,MAX(1,설정!$C$7-1))*(설정!$C$7>1)),IF(설정!$C$19="최근분기",((INDEX(월별집계!$AB10:$AM10,설정!$C$7)-INDEX(월별집계!$AB10:$AM10,MAX(1,설정!$C$7-3))*(설정!$C$7>3))/MIN(3,설정!$C$7)),IF(설정!$C$19="전년추세",AZ10,((설정!$C$7+1)*SUMPRODUCT(월별집계!$AB$5:$AM$5,월별집계!$AB10:$AM10)-(설정!$C$7*(설정!$C$7+1)/2)*SUM(월별집계!$AB10:$AM10))/((설정!$C$7+1)*(설정!$C$7*(설정!$C$7+1)*(2*설정!$C$7+1)/6)-(설정!$C$7*(설정!$C$7+1)/2)^2))))) | AQ10: =IF($A10="","",IF(설정!$C$19="연내누적",(SUM(월별집계!$AB10:$AM10)-AP10*(설정!$C$7*(설정!$C$7+1)/2))/(설정!$C$7+1),INDEX(월별집계!$AB10:$AM10,설정!$C$7)-AP10*설정!$C$7)) | AR10: =IF($A10="","",AQ10+AP10*12) | AS10: =IF($A10="","",IF(OR(P10<=0,Q10>=P10,AP10<=0),"",MAX(설정!$C$7,(P10-AQ10)/AP10))) | AT10: =IF($A10="","",IF(AS10="",IF(AU10="이미 소진","소진됨",""),YEAR((DATE(설정!$C$6,1,1)+ROUND(AS10*365/12,0)-1))&"-"&TEXT(MONTH((DATE(설정!$C$6,1,1)+ROUND(AS10*365/12,0)-1)),"00")&"-"&TEXT(DAY((DATE(설정!$C$6,1,1)+ROUND(AS10*365/12,0)-1)),"00"))) | AU10: =IF($A10="","",IF(AND(P10<=0,Q10>0),"무예산",IF(P10<=0,"-",IF(Q10>=P10,"이미 소진",IF(AP10<=0,"소진 안 됨",IF(AS10<=12,"연내 고갈","연내 여유")))))) | AV10: =IF($A10="","",IF(AJ10<=0,"",IF(AK10>=AJ10,"한도 소진",IF(AK10<=0,"",IF(AJ10/(AK10/(설정!$C$20-설정!$C$22+1))>3,"분기 내 여유",YEAR((DATE(설정!$C$6,설정!$C$22-설정!$C$6*12,1)+ROUND(MAX((설정!$C$20-설정!$C$22+1),AJ10/(AK10/(설정!$C$20-설정!$C$22+1)))*365/12,0)-1))&"-"&TEXT(MONTH((DATE(설정!$C$6,설정!$C$22-설정!$C$6*12,1)+ROUND(MAX((설정!$C$20-설정!$C$22+1),AJ10/(AK10/(설정!$C$20-설정!$C$22+1)))*365/12,0)-1)),"00")&"-"&TEXT(DAY((DATE(설정!$C$6,설정!$C$22-설정!$C$6*12,1)+ROUND(MAX((설정!$C$20-설정!$C$22+1),AJ10/(AK10/(설정!$C$20-설정!$C$22+1)))*365/12,0)-1)),"00")))))) | AW10: =IF($A10="",999+ROW()/1000000,IF(AU10="이미 소진",ROW()/1000000,IF(AU10="연내 고갈",AS10+ROW()/1000000,99+ROW()/1000000))) | AX10: =IF($A10="","",SUMIFS(월별집계!$C10:$Z10,월별집계!$C$5:$Z$5,">="&((설정!$C$6-1)*12+1),월별집계!$C$5:$Z$5,"<="&(설정!$C$20-12))) | AY10: =IF($A10="","",IF(AX10<=0,IF(Q10>0,1,0),Q10/AX10-1)) | AZ10: =IF($A10="","",SUMIFS(월별집계!$C10:$Z10,월별집계!$C$5:$Z$5,">"&(설정!$C$20-12),월별집계!$C$5:$Z$5,"<="&((설정!$C$6-1)*12+12))/MAX(1,12-설정!$C$7))
A11: D100 | B11: =IF($A11="","",IFERROR(INDEX(부서매핑!$D$5:$D$504,MATCH($A11,부서매핑!$C$5:$C$504,0)),"부서매핑 없음")) | C11: 62501000 | D11: =IF($A11="","",IFERROR(INDEX(계정매핑!$B$5:$B$504,MATCH($C11&"",계정매핑!$A$5:$A$504,0)),"계정매핑 없음")) | E11: =IF($A11="","",$A11&"|"&$C11) | F11: =IF($A11="","",월별집계!$Z11) | G11: =IF($A11="","",월별집계!$Y11) | H11: =IF($A11="","",IF(G11<=0,IF(F11>0,1,0),F11/G11-1)) | I11: =IF($A11="","",월별집계!$N11) | J11: =IF($A11="","",IF(I11<=0,IF(F11>0,1,0),F11/I11-1)) | K11: =IF($A11="","",SUMIFS(월별집계!$C11:$Z11,월별집계!$C$5:$Z$5,">="&설정!$C$22,월별집계!$C$5:$Z$5,"<="&설정!$C$20)) | L11: =IF($A11="","",SUMIFS(월별집계!$C11:$Z11,월별집계!$C$5:$Z$5,">="&(설정!$C$22-3),월별집계!$C$5:$Z$5,"<="&(설정!$C$20-3))) | M11: =IF($A11="","",IF(L11<=0,IF(K11>0,1,0),K11/L11-1)) | N11: =IF($A11="","",MAX(F11-G11,F11-I11)) | O11: =IF($A11="","",IFERROR((월별집계!$Z11-AVERAGE(월별집계!N11:Y11))/STDEV(월별집계!N11:Y11),0)) | P11: =IF($A11="","",SUMIFS(예산판_원본!$O$5:$O$5000,예산판_원본!$L$5:$L$5000,$E11,예산판_원본!$M$5:$M$5000,설정!$C$6)) | Q11: =IF($A11="","",SUMIFS(월별집계!$C11:$Z11,월별집계!$C$5:$Z$5,">="&(설정!$C$6*12+1),월별집계!$C$5:$Z$5,"<="&설정!$C$20)) | R11: =IF($A11="","",P11-Q11) | S11: =IF($A11="","",AVERAGE(월별집계!X11:Z11)*(12-설정!$C$7)) | T11: =IF($A11="","",IFERROR(Q11/(SUMIFS(월별집계!$C11:$Z11,월별집계!$C$5:$Z$5,">="&((설정!$C$6-1)*12+1),월별집계!$C$5:$Z$5,"<="&(설정!$C$20-12))/SUMIFS(월별집계!$C11:$Z11,월별집계!$C$5:$Z$5,">="&((설정!$C$6-1)*12+1),월별집계!$C$5:$Z$5,"<="&((설정!$C$6-1)*12+12)))-Q11,S11)) | U11: =IF($A11="","",Q11+MAX(S11,T11)) | V11: =IF($A11="","",IF(P11=0,0,U11/P11)) | W11: =IF($A11="","",IF(AND(P11=0,Q11>0),"무예산",IF(P11=0,"-",IF(V11>설정!$C$12,"부족 예상",IF(V11>설정!$C$11,"주의","여유"))))) | X11: =IF($A11="","",IF(P11=0,0,MAX(0,U11-P11))) | Y11: =IF($A11="","",IF(OR(W11<>"부족 예상",설정!$C$7=12),"",IF(R11<=0,"이미 초과",MIN(12,설정!$C$7+ROUNDUP(R11/(MAX(S11,T11)/(12-설정!$C$7)),0))&"월"))) | Z11: =IF($A11="","",TRIM(IF(AND(N(AC11)>=설정!$C$14,N11>=설정!$C$10),"단건"&TEXT(MIN(AC11,1),"0%")&" ","")&IF(AND(N11>0,AD11>0),IF(AD11/N11>=설정!$C$16,"SA대체 ",""),"")&IF(AE11>0,"역분개"&AE11&"건 ","")&IF(O11>=설정!$C$13,"이상치 ","")&IF(AND(I11=0,F11>0),"신규지출 ",""))) | AA11: =IF($A11="","",ROUND((AF11+AG11+AH11+AI11)*IF(AND(F11<설정!$C$10,N11<설정!$C$10),0.3,1),1)) | AB11: =IF($A11="","",AA11+ROW()/1000000) | AC11: =IF(OR($A11="",N11<=0),"",SUMPRODUCT(MAX((전표_원본!$O$5:$O$100000=$E11)*(전표_원본!$M$5:$M$100000=설정!$C$20)*전표_원본!$P$5:$P$100000))/N11) | AD11: =IF($A11="","",SUMIFS(전표_원본!$P$5:$P$100000,전표_원본!$O$5:$O$100000,$E11,전표_원본!$M$5:$M$100000,설정!$C$20,전표_원본!$E$5:$E$100000,"SA")-SUMIFS(전표_원본!$P$5:$P$100000,전표_원본!$O$5:$O$100000,$E11,전표_원본!$M$5:$M$100000,설정!$C$20-1,전표_원본!$E$5:$E$100000,"SA")) | AE11: =IF($A11="","",COUNTIFS(전표_원본!$O$5:$O$100000,$E11,전표_원본!$M$5:$M$100000,설정!$C$20,전표_원본!$P$5:$P$100000,"<0")) | AF11: =IF($A11="","",MIN(MAX(0,N11)/(설정!$C$10*5),1)*30) | AG11: =IF($A11="","",MIN(MAX(0,H11,J11),1)*20) | AH11: =IF($A11="","",MIN(MAX(0,O11)/3,1)*25) | AI11: =IF($A11="","",IF(OR(W11="부족 예상",W11="무예산",AO11="한도 초과",AO11="초과 예상",AO11="무예산"),25,IF(OR(W11="주의",AO11="주의"),15,0))) | AJ11: =IF($A11="","",SUMIFS(예산판_원본!$O$5:$O$5000,예산판_원본!$L$5:$L$5000,$E11,예산판_원본!$M$5:$M$5000,설정!$C$6,예산판_원본!$N$5:$N$5000,설정!$C$21)) | AK11: =IF($A11="","",K11) | AL11: =IF($A11="","",AJ11-AK11) | AM11: =IF($A11="","",AK11+AVERAGE(월별집계!X11:Z11)*MAX(0,설정!$C$22+2-설정!$C$20)) | AN11: =IF($A11="","",IF(AJ11=0,0,AM11/AJ11)) | AO11: =IF($A11="","",IF(AND(AJ11=0,AK11>0),"무예산",IF(AJ11=0,"-",IF(AK11>AJ11,"한도 초과",IF(AN11>설정!$C$12,"초과 예상",IF(AN11>설정!$C$11,"주의","여유")))))) | AP11: =IF($A11="","",IF(설정!$C$19="최근월",(INDEX(월별집계!$AB11:$AM11,설정!$C$7)-INDEX(월별집계!$AB11:$AM11,MAX(1,설정!$C$7-1))*(설정!$C$7>1)),IF(설정!$C$19="최근분기",((INDEX(월별집계!$AB11:$AM11,설정!$C$7)-INDEX(월별집계!$AB11:$AM11,MAX(1,설정!$C$7-3))*(설정!$C$7>3))/MIN(3,설정!$C$7)),IF(설정!$C$19="전년추세",AZ11,((설정!$C$7+1)*SUMPRODUCT(월별집계!$AB$5:$AM$5,월별집계!$AB11:$AM11)-(설정!$C$7*(설정!$C$7+1)/2)*SUM(월별집계!$AB11:$AM11))/((설정!$C$7+1)*(설정!$C$7*(설정!$C$7+1)*(2*설정!$C$7+1)/6)-(설정!$C$7*(설정!$C$7+1)/2)^2))))) | AQ11: =IF($A11="","",IF(설정!$C$19="연내누적",(SUM(월별집계!$AB11:$AM11)-AP11*(설정!$C$7*(설정!$C$7+1)/2))/(설정!$C$7+1),INDEX(월별집계!$AB11:$AM11,설정!$C$7)-AP11*설정!$C$7)) | AR11: =IF($A11="","",AQ11+AP11*12) | AS11: =IF($A11="","",IF(OR(P11<=0,Q11>=P11,AP11<=0),"",MAX(설정!$C$7,(P11-AQ11)/AP11))) | AT11: =IF($A11="","",IF(AS11="",IF(AU11="이미 소진","소진됨",""),YEAR((DATE(설정!$C$6,1,1)+ROUND(AS11*365/12,0)-1))&"-"&TEXT(MONTH((DATE(설정!$C$6,1,1)+ROUND(AS11*365/12,0)-1)),"00")&"-"&TEXT(DAY((DATE(설정!$C$6,1,1)+ROUND(AS11*365/12,0)-1)),"00"))) | AU11: =IF($A11="","",IF(AND(P11<=0,Q11>0),"무예산",IF(P11<=0,"-",IF(Q11>=P11,"이미 소진",IF(AP11<=0,"소진 안 됨",IF(AS11<=12,"연내 고갈","연내 여유")))))) | AV11: =IF($A11="","",IF(AJ11<=0,"",IF(AK11>=AJ11,"한도 소진",IF(AK11<=0,"",IF(AJ11/(AK11/(설정!$C$20-설정!$C$22+1))>3,"분기 내 여유",YEAR((DATE(설정!$C$6,설정!$C$22-설정!$C$6*12,1)+ROUND(MAX((설정!$C$20-설정!$C$22+1),AJ11/(AK11/(설정!$C$20-설정!$C$22+1)))*365/12,0)-1))&"-"&TEXT(MONTH((DATE(설정!$C$6,설정!$C$22-설정!$C$6*12,1)+ROUND(MAX((설정!$C$20-설정!$C$22+1),AJ11/(AK11/(설정!$C$20-설정!$C$22+1)))*365/12,0)-1)),"00")&"-"&TEXT(DAY((DATE(설정!$C$6,설정!$C$22-설정!$C$6*12,1)+ROUND(MAX((설정!$C$20-설정!$C$22+1),AJ11/(AK11/(설정!$C$20-설정!$C$22+1)))*365/12,0)-1)),"00")))))) | AW11: =IF($A11="",999+ROW()/1000000,IF(AU11="이미 소진",ROW()/1000000,IF(AU11="연내 고갈",AS11+ROW()/1000000,99+ROW()/1000000))) | AX11: =IF($A11="","",SUMIFS(월별집계!$C11:$Z11,월별집계!$C$5:$Z$5,">="&((설정!$C$6-1)*12+1),월별집계!$C$5:$Z$5,"<="&(설정!$C$20-12))) | AY11: =IF($A11="","",IF(AX11<=0,IF(Q11>0,1,0),Q11/AX11-1)) | AZ11: =IF($A11="","",SUMIFS(월별집계!$C11:$Z11,월별집계!$C$5:$Z$5,">"&(설정!$C$20-12),월별집계!$C$5:$Z$5,"<="&((설정!$C$6-1)*12+12))/MAX(1,12-설정!$C$7))
A12: D100 | B12: =IF($A12="","",IFERROR(INDEX(부서매핑!$D$5:$D$504,MATCH($A12,부서매핑!$C$5:$C$504,0)),"부서매핑 없음")) | C12: 62601000 | D12: =IF($A12="","",IFERROR(INDEX(계정매핑!$B$5:$B$504,MATCH($C12&"",계정매핑!$A$5:$A$504,0)),"계정매핑 없음")) | E12: =IF($A12="","",$A12&"|"&$C12) | F12: =IF($A12="","",월별집계!$Z12) | G12: =IF($A12="","",월별집계!$Y12) | H12: =IF($A12="","",IF(G12<=0,IF(F12>0,1,0),F12/G12-1)) | I12: =IF($A12="","",월별집계!$N12) | J12: =IF($A12="","",IF(I12<=0,IF(F12>0,1,0),F12/I12-1)) | K12: =IF($A12="","",SUMIFS(월별집계!$C12:$Z12,월별집계!$C$5:$Z$5,">="&설정!$C$22,월별집계!$C$5:$Z$5,"<="&설정!$C$20)) | L12: =IF($A12="","",SUMIFS(월별집계!$C12:$Z12,월별집계!$C$5:$Z$5,">="&(설정!$C$22-3),월별집계!$C$5:$Z$5,"<="&(설정!$C$20-3))) | M12: =IF($A12="","",IF(L12<=0,IF(K12>0,1,0),K12/L12-1)) | N12: =IF($A12="","",MAX(F12-G12,F12-I12)) | O12: =IF($A12="","",IFERROR((월별집계!$Z12-AVERAGE(월별집계!N12:Y12))/STDEV(월별집계!N12:Y12),0)) | P12: =IF($A12="","",SUMIFS(예산판_원본!$O$5:$O$5000,예산판_원본!$L$5:$L$5000,$E12,예산판_원본!$M$5:$M$5000,설정!$C$6)) | Q12: =IF($A12="","",SUMIFS(월별집계!$C12:$Z12,월별집계!$C$5:$Z$5,">="&(설정!$C$6*12+1),월별집계!$C$5:$Z$5,"<="&설정!$C$20)) | R12: =IF($A12="","",P12-Q12) | S12: =IF($A12="","",AVERAGE(월별집계!X12:Z12)*(12-설정!$C$7)) | T12: =IF($A12="","",IFERROR(Q12/(SUMIFS(월별집계!$C12:$Z12,월별집계!$C$5:$Z$5,">="&((설정!$C$6-1)*12+1),월별집계!$C$5:$Z$5,"<="&(설정!$C$20-12))/SUMIFS(월별집계!$C12:$Z12,월별집계!$C$5:$Z$5,">="&((설정!$C$6-1)*12+1),월별집계!$C$5:$Z$5,"<="&((설정!$C$6-1)*12+12)))-Q12,S12)) | U12: =IF($A12="","",Q12+MAX(S12,T12)) | V12: =IF($A12="","",IF(P12=0,0,U12/P12)) | W12: =IF($A12="","",IF(AND(P12=0,Q12>0),"무예산",IF(P12=0,"-",IF(V12>설정!$C$12,"부족 예상",IF(V12>설정!$C$11,"주의","여유"))))) | X12: =IF($A12="","",IF(P12=0,0,MAX(0,U12-P12))) | Y12: =IF($A12="","",IF(OR(W12<>"부족 예상",설정!$C$7=12),"",IF(R12<=0,"이미 초과",MIN(12,설정!$C$7+ROUNDUP(R12/(MAX(S12,T12)/(12-설정!$C$7)),0))&"월"))) | Z12: =IF($A12="","",TRIM(IF(AND(N(AC12)>=설정!$C$14,N12>=설정!$C$10),"단건"&TEXT(MIN(AC12,1),"0%")&" ","")&IF(AND(N12>0,AD12>0),IF(AD12/N12>=설정!$C$16,"SA대체 ",""),"")&IF(AE12>0,"역분개"&AE12&"건 ","")&IF(O12>=설정!$C$13,"이상치 ","")&IF(AND(I12=0,F12>0),"신규지출 ",""))) | AA12: =IF($A12="","",ROUND((AF12+AG12+AH12+AI12)*IF(AND(F12<설정!$C$10,N12<설정!$C$10),0.3,1),1)) | AB12: =IF($A12="","",AA12+ROW()/1000000) | AC12: =IF(OR($A12="",N12<=0),"",SUMPRODUCT(MAX((전표_원본!$O$5:$O$100000=$E12)*(전표_원본!$M$5:$M$100000=설정!$C$20)*전표_원본!$P$5:$P$100000))/N12) | AD12: =IF($A12="","",SUMIFS(전표_원본!$P$5:$P$100000,전표_원본!$O$5:$O$100000,$E12,전표_원본!$M$5:$M$100000,설정!$C$20,전표_원본!$E$5:$E$100000,"SA")-SUMIFS(전표_원본!$P$5:$P$100000,전표_원본!$O$5:$O$100000,$E12,전표_원본!$M$5:$M$100000,설정!$C$20-1,전표_원본!$E$5:$E$100000,"SA")) | AE12: =IF($A12="","",COUNTIFS(전표_원본!$O$5:$O$100000,$E12,전표_원본!$M$5:$M$100000,설정!$C$20,전표_원본!$P$5:$P$100000,"<0")) | AF12: =IF($A12="","",MIN(MAX(0,N12)/(설정!$C$10*5),1)*30) | AG12: =IF($A12="","",MIN(MAX(0,H12,J12),1)*20) | AH12: =IF($A12="","",MIN(MAX(0,O12)/3,1)*25) | AI12: =IF($A12="","",IF(OR(W12="부족 예상",W12="무예산",AO12="한도 초과",AO12="초과 예상",AO12="무예산"),25,IF(OR(W12="주의",AO12="주의"),15,0))) | AJ12: =IF($A12="","",SUMIFS(예산판_원본!$O$5:$O$5000,예산판_원본!$L$5:$L$5000,$E12,예산판_원본!$M$5:$M$5000,설정!$C$6,예산판_원본!$N$5:$N$5000,설정!$C$21)) | AK12: =IF($A12="","",K12) | AL12: =IF($A12="","",AJ12-AK12) | AM12: =IF($A12="","",AK12+AVERAGE(월별집계!X12:Z12)*MAX(0,설정!$C$22+2-설정!$C$20)) | AN12: =IF($A12="","",IF(AJ12=0,0,AM12/AJ12)) | AO12: =IF($A12="","",IF(AND(AJ12=0,AK12>0),"무예산",IF(AJ12=0,"-",IF(AK12>AJ12,"한도 초과",IF(AN12>설정!$C$12,"초과 예상",IF(AN12>설정!$C$11,"주의","여유")))))) | AP12: =IF($A12="","",IF(설정!$C$19="최근월",(INDEX(월별집계!$AB12:$AM12,설정!$C$7)-INDEX(월별집계!$AB12:$AM12,MAX(1,설정!$C$7-1))*(설정!$C$7>1)),IF(설정!$C$19="최근분기",((INDEX(월별집계!$AB12:$AM12,설정!$C$7)-INDEX(월별집계!$AB12:$AM12,MAX(1,설정!$C$7-3))*(설정!$C$7>3))/MIN(3,설정!$C$7)),IF(설정!$C$19="전년추세",AZ12,((설정!$C$7+1)*SUMPRODUCT(월별집계!$AB$5:$AM$5,월별집계!$AB12:$AM12)-(설정!$C$7*(설정!$C$7+1)/2)*SUM(월별집계!$AB12:$AM12))/((설정!$C$7+1)*(설정!$C$7*(설정!$C$7+1)*(2*설정!$C$7+1)/6)-(설정!$C$7*(설정!$C$7+1)/2)^2))))) | AQ12: =IF($A12="","",IF(설정!$C$19="연내누적",(SUM(월별집계!$AB12:$AM12)-AP12*(설정!$C$7*(설정!$C$7+1)/2))/(설정!$C$7+1),INDEX(월별집계!$AB12:$AM12,설정!$C$7)-AP12*설정!$C$7)) | AR12: =IF($A12="","",AQ12+AP12*12) | AS12: =IF($A12="","",IF(OR(P12<=0,Q12>=P12,AP12<=0),"",MAX(설정!$C$7,(P12-AQ12)/AP12))) | AT12: =IF($A12="","",IF(AS12="",IF(AU12="이미 소진","소진됨",""),YEAR((DATE(설정!$C$6,1,1)+ROUND(AS12*365/12,0)-1))&"-"&TEXT(MONTH((DATE(설정!$C$6,1,1)+ROUND(AS12*365/12,0)-1)),"00")&"-"&TEXT(DAY((DATE(설정!$C$6,1,1)+ROUND(AS12*365/12,0)-1)),"00"))) | AU12: =IF($A12="","",IF(AND(P12<=0,Q12>0),"무예산",IF(P12<=0,"-",IF(Q12>=P12,"이미 소진",IF(AP12<=0,"소진 안 됨",IF(AS12<=12,"연내 고갈","연내 여유")))))) | AV12: =IF($A12="","",IF(AJ12<=0,"",IF(AK12>=AJ12,"한도 소진",IF(AK12<=0,"",IF(AJ12/(AK12/(설정!$C$20-설정!$C$22+1))>3,"분기 내 여유",YEAR((DATE(설정!$C$6,설정!$C$22-설정!$C$6*12,1)+ROUND(MAX((설정!$C$20-설정!$C$22+1),AJ12/(AK12/(설정!$C$20-설정!$C$22+1)))*365/12,0)-1))&"-"&TEXT(MONTH((DATE(설정!$C$6,설정!$C$22-설정!$C$6*12,1)+ROUND(MAX((설정!$C$20-설정!$C$22+1),AJ12/(AK12/(설정!$C$20-설정!$C$22+1)))*365/12,0)-1)),"00")&"-"&TEXT(DAY((DATE(설정!$C$6,설정!$C$22-설정!$C$6*12,1)+ROUND(MAX((설정!$C$20-설정!$C$22+1),AJ12/(AK12/(설정!$C$20-설정!$C$22+1)))*365/12,0)-1)),"00")))))) | AW12: =IF($A12="",999+ROW()/1000000,IF(AU12="이미 소진",ROW()/1000000,IF(AU12="연내 고갈",AS12+ROW()/1000000,99+ROW()/1000000))) | AX12: =IF($A12="","",SUMIFS(월별집계!$C12:$Z12,월별집계!$C$5:$Z$5,">="&((설정!$C$6-1)*12+1),월별집계!$C$5:$Z$5,"<="&(설정!$C$20-12))) | AY12: =IF($A12="","",IF(AX12<=0,IF(Q12>0,1,0),Q12/AX12-1)) | AZ12: =IF($A12="","",SUMIFS(월별집계!$C12:$Z12,월별집계!$C$5:$Z$5,">"&(설정!$C$20-12),월별집계!$C$5:$Z$5,"<="&((설정!$C$6-1)*12+12))/MAX(1,12-설정!$C$7))
A13: D100 | B13: =IF($A13="","",IFERROR(INDEX(부서매핑!$D$5:$D$504,MATCH($A13,부서매핑!$C$5:$C$504,0)),"부서매핑 없음")) | C13: 62901000 | D13: =IF($A13="","",IFERROR(INDEX(계정매핑!$B$5:$B$504,MATCH($C13&"",계정매핑!$A$5:$A$504,0)),"계정매핑 없음")) | E13: =IF($A13="","",$A13&"|"&$C13) | F13: =IF($A13="","",월별집계!$Z13) | G13: =IF($A13="","",월별집계!$Y13) | H13: =IF($A13="","",IF(G13<=0,IF(F13>0,1,0),F13/G13-1)) | I13: =IF($A13="","",월별집계!$N13) | J13: =IF($A13="","",IF(I13<=0,IF(F13>0,1,0),F13/I13-1)) | K13: =IF($A13="","",SUMIFS(월별집계!$C13:$Z13,월별집계!$C$5:$Z$5,">="&설정!$C$22,월별집계!$C$5:$Z$5,"<="&설정!$C$20)) | L13: =IF($A13="","",SUMIFS(월별집계!$C13:$Z13,월별집계!$C$5:$Z$5,">="&(설정!$C$22-3),월별집계!$C$5:$Z$5,"<="&(설정!$C$20-3))) | M13: =IF($A13="","",IF(L13<=0,IF(K13>0,1,0),K13/L13-1)) | N13: =IF($A13="","",MAX(F13-G13,F13-I13)) | O13: =IF($A13="","",IFERROR((월별집계!$Z13-AVERAGE(월별집계!N13:Y13))/STDEV(월별집계!N13:Y13),0)) | P13: =IF($A13="","",SUMIFS(예산판_원본!$O$5:$O$5000,예산판_원본!$L$5:$L$5000,$E13,예산판_원본!$M$5:$M$5000,설정!$C$6)) | Q13: =IF($A13="","",SUMIFS(월별집계!$C13:$Z13,월별집계!$C$5:$Z$5,">="&(설정!$C$6*12+1),월별집계!$C$5:$Z$5,"<="&설정!$C$20)) | R13: =IF($A13="","",P13-Q13) | S13: =IF($A13="","",AVERAGE(월별집계!X13:Z13)*(12-설정!$C$7)) | T13: =IF($A13="","",IFERROR(Q13/(SUMIFS(월별집계!$C13:$Z13,월별집계!$C$5:$Z$5,">="&((설정!$C$6-1)*12+1),월별집계!$C$5:$Z$5,"<="&(설정!$C$20-12))/SUMIFS(월별집계!$C13:$Z13,월별집계!$C$5:$Z$5,">="&((설정!$C$6-1)*12+1),월별집계!$C$5:$Z$5,"<="&((설정!$C$6-1)*12+12)))-Q13,S13)) | U13: =IF($A13="","",Q13+MAX(S13,T13)) | V13: =IF($A13="","",IF(P13=0,0,U13/P13)) | W13: =IF($A13="","",IF(AND(P13=0,Q13>0),"무예산",IF(P13=0,"-",IF(V13>설정!$C$12,"부족 예상",IF(V13>설정!$C$11,"주의","여유"))))) | X13: =IF($A13="","",IF(P13=0,0,MAX(0,U13-P13))) | Y13: =IF($A13="","",IF(OR(W13<>"부족 예상",설정!$C$7=12),"",IF(R13<=0,"이미 초과",MIN(12,설정!$C$7+ROUNDUP(R13/(MAX(S13,T13)/(12-설정!$C$7)),0))&"월"))) | Z13: =IF($A13="","",TRIM(IF(AND(N(AC13)>=설정!$C$14,N13>=설정!$C$10),"단건"&TEXT(MIN(AC13,1),"0%")&" ","")&IF(AND(N13>0,AD13>0),IF(AD13/N13>=설정!$C$16,"SA대체 ",""),"")&IF(AE13>0,"역분개"&AE13&"건 ","")&IF(O13>=설정!$C$13,"이상치 ","")&IF(AND(I13=0,F13>0),"신규지출 ",""))) | AA13: =IF($A13="","",ROUND((AF13+AG13+AH13+AI13)*IF(AND(F13<설정!$C$10,N13<설정!$C$10),0.3,1),1)) | AB13: =IF($A13="","",AA13+ROW()/1000000) | AC13: =IF(OR($A13="",N13<=0),"",SUMPRODUCT(MAX((전표_원본!$O$5:$O$100000=$E13)*(전표_원본!$M$5:$M$100000=설정!$C$20)*전표_원본!$P$5:$P$100000))/N13) | AD13: =IF($A13="","",SUMIFS(전표_원본!$P$5:$P$100000,전표_원본!$O$5:$O$100000,$E13,전표_원본!$M$5:$M$100000,설정!$C$20,전표_원본!$E$5:$E$100000,"SA")-SUMIFS(전표_원본!$P$5:$P$100000,전표_원본!$O$5:$O$100000,$E13,전표_원본!$M$5:$M$100000,설정!$C$20-1,전표_원본!$E$5:$E$100000,"SA")) | AE13: =IF($A13="","",COUNTIFS(전표_원본!$O$5:$O$100000,$E13,전표_원본!$M$5:$M$100000,설정!$C$20,전표_원본!$P$5:$P$100000,"<0")) | AF13: =IF($A13="","",MIN(MAX(0,N13)/(설정!$C$10*5),1)*30) | AG13: =IF($A13="","",MIN(MAX(0,H13,J13),1)*20) | AH13: =IF($A13="","",MIN(MAX(0,O13)/3,1)*25) | AI13: =IF($A13="","",IF(OR(W13="부족 예상",W13="무예산",AO13="한도 초과",AO13="초과 예상",AO13="무예산"),25,IF(OR(W13="주의",AO13="주의"),15,0))) | AJ13: =IF($A13="","",SUMIFS(예산판_원본!$O$5:$O$5000,예산판_원본!$L$5:$L$5000,$E13,예산판_원본!$M$5:$M$5000,설정!$C$6,예산판_원본!$N$5:$N$5000,설정!$C$21)) | AK13: =IF($A13="","",K13) | AL13: =IF($A13="","",AJ13-AK13) | AM13: =IF($A13="","",AK13+AVERAGE(월별집계!X13:Z13)*MAX(0,설정!$C$22+2-설정!$C$20)) | AN13: =IF($A13="","",IF(AJ13=0,0,AM13/AJ13)) | AO13: =IF($A13="","",IF(AND(AJ13=0,AK13>0),"무예산",IF(AJ13=0,"-",IF(AK13>AJ13,"한도 초과",IF(AN13>설정!$C$12,"초과 예상",IF(AN13>설정!$C$11,"주의","여유")))))) | AP13: =IF($A13="","",IF(설정!$C$19="최근월",(INDEX(월별집계!$AB13:$AM13,설정!$C$7)-INDEX(월별집계!$AB13:$AM13,MAX(1,설정!$C$7-1))*(설정!$C$7>1)),IF(설정!$C$19="최근분기",((INDEX(월별집계!$AB13:$AM13,설정!$C$7)-INDEX(월별집계!$AB13:$AM13,MAX(1,설정!$C$7-3))*(설정!$C$7>3))/MIN(3,설정!$C$7)),IF(설정!$C$19="전년추세",AZ13,((설정!$C$7+1)*SUMPRODUCT(월별집계!$AB$5:$AM$5,월별집계!$AB13:$AM13)-(설정!$C$7*(설정!$C$7+1)/2)*SUM(월별집계!$AB13:$AM13))/((설정!$C$7+1)*(설정!$C$7*(설정!$C$7+1)*(2*설정!$C$7+1)/6)-(설정!$C$7*(설정!$C$7+1)/2)^2))))) | AQ13: =IF($A13="","",IF(설정!$C$19="연내누적",(SUM(월별집계!$AB13:$AM13)-AP13*(설정!$C$7*(설정!$C$7+1)/2))/(설정!$C$7+1),INDEX(월별집계!$AB13:$AM13,설정!$C$7)-AP13*설정!$C$7)) | AR13: =IF($A13="","",AQ13+AP13*12) | AS13: =IF($A13="","",IF(OR(P13<=0,Q13>=P13,AP13<=0),"",MAX(설정!$C$7,(P13-AQ13)/AP13))) | AT13: =IF($A13="","",IF(AS13="",IF(AU13="이미 소진","소진됨",""),YEAR((DATE(설정!$C$6,1,1)+ROUND(AS13*365/12,0)-1))&"-"&TEXT(MONTH((DATE(설정!$C$6,1,1)+ROUND(AS13*365/12,0)-1)),"00")&"-"&TEXT(DAY((DATE(설정!$C$6,1,1)+ROUND(AS13*365/12,0)-1)),"00"))) | AU13: =IF($A13="","",IF(AND(P13<=0,Q13>0),"무예산",IF(P13<=0,"-",IF(Q13>=P13,"이미 소진",IF(AP13<=0,"소진 안 됨",IF(AS13<=12,"연내 고갈","연내 여유")))))) | AV13: =IF($A13="","",IF(AJ13<=0,"",IF(AK13>=AJ13,"한도 소진",IF(AK13<=0,"",IF(AJ13/(AK13/(설정!$C$20-설정!$C$22+1))>3,"분기 내 여유",YEAR((DATE(설정!$C$6,설정!$C$22-설정!$C$6*12,1)+ROUND(MAX((설정!$C$20-설정!$C$22+1),AJ13/(AK13/(설정!$C$20-설정!$C$22+1)))*365/12,0)-1))&"-"&TEXT(MONTH((DATE(설정!$C$6,설정!$C$22-설정!$C$6*12,1)+ROUND(MAX((설정!$C$20-설정!$C$22+1),AJ13/(AK13/(설정!$C$20-설정!$C$22+1)))*365/12,0)-1)),"00")&"-"&TEXT(DAY((DATE(설정!$C$6,설정!$C$22-설정!$C$6*12,1)+ROUND(MAX((설정!$C$20-설정!$C$22+1),AJ13/(AK13/(설정!$C$20-설정!$C$22+1)))*365/12,0)-1)),"00")))))) | AW13: =IF($A13="",999+ROW()/1000000,IF(AU13="이미 소진",ROW()/1000000,IF(AU13="연내 고갈",AS13+ROW()/1000000,99+ROW()/1000000))) | AX13: =IF($A13="","",SUMIFS(월별집계!$C13:$Z13,월별집계!$C$5:$Z$5,">="&((설정!$C$6-1)*12+1),월별집계!$C$5:$Z$5,"<="&(설정!$C$20-12))) | AY13: =IF($A13="","",IF(AX13<=0,IF(Q13>0,1,0),Q13/AX13-1)) | AZ13: =IF($A13="","",SUMIFS(월별집계!$C13:$Z13,월별집계!$C$5:$Z$5,">"&(설정!$C$20-12),월별집계!$C$5:$Z$5,"<="&((설정!$C$6-1)*12+12))/MAX(1,12-설정!$C$7))
